Workbook

Sheet ml_challenge_dataset
A1: unique_id | B1: Painting | C1: On a scale of 1‚Äì10, how intense is the emotion conveyed by the artwork? | D1: Describe how this painting makes you feel. | E1: This art piece makes me feel sombre. | F1: This art piece makes me feel content. | G1: This art piece makes me feel calm. | H1: This art piece makes me feel uneasy. | I1: How many prominent colours do you notice in this painting? | J1: How many objects caught your eye in the painting? | K1: How much (in Canadian dollars) would you be willing to pay for this painting? | L1: If you could purchase this painting, which room would you put that painting in? | M1: If you could view this art in person, who would you want to view it with? | N1: What season does this art piece remind you of? | O1: If this painting was a food, what would be? | P1: Imagine a soundtrack for this painting. Describe that soundtrack without naming any objects in the painting. | Q1: Sombre Score | R1: Content Score | S1: Calm Score | T1: Uneasy Score | U1: Willingness to Pay (CAD) | V1: Bathroom | W1: Dining room | X1: Office | Y1: Bedroom | Z1: Living room | AA1: By Yourself | AB1: Friends | AC1: Family members | AD1: Coworkers/Classmates | AE1: Strangers | AF1: Spring | AG1: Summer | AH1: Fall | AI1: Winter
A2: 1 | B2: The Persistence of Memory | I2: 5 | Q2: =IF(E2="", "", LEFT(E2, 1) * 1) | R2: =IF(F2="","",VALUE(LEFT(F2,FIND(" ",F2)-1))) | S2: =IF(G2="","",VALUE(LEFT(G2,FIND(" ",G2)-1))) | T2: =IF(H2="","",VALUE(LEFT(H2,FIND(" ",H2)-1))) | V2: =IF(L2="",0,IF(ISNUMBER(SEARCH("Bathroom",L2)),1,0)) -> 0 | W2: =IF(L2="",0,IF(ISNUMBER(SEARCH("Dining room",L2)),1,0)) -> 0 | X2: =IF(L2="",0,IF(ISNUMBER(SEARCH("Office",L2)),1,0)) -> 0 | Y2: =IF(L2="",0,IF(ISNUMBER(SEARCH("Bedroom",L2)),1,0)) -> 0 | Z2: =IF(L2="",0,IF(ISNUMBER(SEARCH("Living room",L2)),1,0)) -> 0 | AA2: =IF(M2="",0, IF(ISNUMBER(SEARCH("By yourself",M2)), 1, 0)) -> 0 | AB2: =IF(M2="", 0, IF(ISNUMBER(SEARCH("Friends", M2)), 1, 0)) -> 0 | AC2: =IF(M2="",0,IF(ISNUMBER(SEARCH("Family members", M2)), 1, 0)) -> 0 | AD2: =IF(M2="", 0, IF(ISNUMBER(SEARCH("Coworkers/Classmates", M2)), 1, 0)) -> 0 | AE2: =IF(M2="", 0, IF(ISNUMBER(SEARCH("Strangers", M2)), 1, 0)) -> 0 | AF2: =IF(N2="", 0, IF(ISNUMBER(SEARCH("Spring", N2)), 1, 0)) -> 0 | AG2: =IF(N2="", 0, IF(ISNUMBER(SEARCH("Summer", N2)), 1, 0)) -> 0 | AH2: =IF(N2="", 0, IF(ISNUMBER(SEARCH("Fall", N2)), 1, 0)) -> 0 | AI2: =IF(N2="", 0, IF(ISNUMBER(SEARCH("Winter", N2)), 1, 0)) -> 0
A3: 2 | B3: The Persistence of Memory | C3: 5 | D3: The clocks are burnt on a hot desert, it embodies the melancholy of time passing. The dominant yellow hue intensifies this sensation. | E3: 4 - Agree | F3: 3 - Neutral/Unsure | G3: 2 - Disagree | H3: 1 - Strongly disagree | I3: 2 | J3: 4 | K3: 0 | L3: Bathroom | M3: By yourself | N3: Fall | O3: Fries | P3: A country song that contrasts nostalgia for the past with dissatisfaction with the present. | Q3: =IF(E3="", "", LEFT(E3, 1) * 1) -> 4 | R3: =IF(F3="","",VALUE(LEFT(F3,FIND(" ",F3)-1))) -> 3 | S3: =IF(G3="","",VALUE(LEFT(G3,FIND(" ",G3)-1))) -> 2 | T3: =IF(H3="","",VALUE(LEFT(H3,FIND(" ",H3)-1))) -> 1 | U3: 0 | V3: =IF(L3="",0,IF(ISNUMBER(SEARCH("Bathroom",L3)),1,0)) -> 1 | W3: =IF(L3="",0,IF(ISNUMBER(SEARCH("Dining room",L3)),1,0)) -> 0 | X3: =IF(L3="",0,IF(ISNUMBER(SEARCH("Office",L3)),1,0)) -> 0 | Y3: =IF(L3="",0,IF(ISNUMBER(SEARCH("Bedroom",L3)),1,0)) -> 0 | Z3: =IF(L3="",0,IF(ISNUMBER(SEARCH("Living room",L3)),1,0)) -> 0 | AA3: =IF(M3="",0, IF(ISNUMBER(SEARCH("By yourself",M3)), 1, 0)) -> 1 | AB3: =IF(M3="", 0, IF(ISNUMBER(SEARCH("Friends", M3)), 1, 0)) -> 0 | AC3: =IF(M3="",0,IF(ISNUMBER(SEARCH("Family members", M3)), 1, 0)) -> 0 | AD3: =IF(M3="", 0, IF(ISNUMBER(SEARCH("Coworkers/Classmates", M3)), 1, 0)) -> 0 | AE3: =IF(M3="", 0, IF(ISNUMBER(SEARCH("Strangers", M3)), 1, 0)) -> 0 | AF3: =IF(N3="", 0, IF(ISNUMBER(SEARCH("Spring", N3)), 1, 0)) -> 0 | AG3: =IF(N3="", 0, IF(ISNUMBER(SEARCH("Summer", N3)), 1, 0)) -> 0 | AH3: =IF(N3="", 0, IF(ISNUMBER(SEARCH("Fall", N3)), 1, 0)) -> 1 | AI3: =IF(N3="", 0, IF(ISNUMBER(SEARCH("Winter", N3)), 1, 0)) -> 0
A4: 3 | B4: The Persistence of Memory | C4: 7 | D4: This painting makes me feel dread. The clock reminds me of a ticking time until the death of the creature in the picture. | E4: 4 - Agree | F4: 1 - Strongly disagree | G4: 1 - Strongly disagree | H4: 4 - Agree | I4: 4 | J4: 3 | K4: 5 | L4: Bathroom,Dining room | M4: Coworkers/Classmates,By yourself | N4: Fall | O4: Sardines | P4: A melancholy instrumental with a monotone voice singing gloomy lyrics like Creep by radiohead. | Q4: =IF(E4="", "", LEFT(E4, 1) * 1) -> 4 | R4: =IF(F4="","",VALUE(LEFT(F4,FIND(" ",F4)-1))) -> 1 | S4: =IF(G4="","",VALUE(LEFT(G4,FIND(" ",G4)-1))) -> 1 | T4: =IF(H4="","",VALUE(LEFT(H4,FIND(" ",H4)-1))) -> 4 | U4: 5 | V4: =IF(L4="",0,IF(ISNUMBER(SEARCH("Bathroom",L4)),1,0)) -> 1 | W4: =IF(L4="",0,IF(ISNUMBER(SEARCH("Dining room",L4)),1,0)) -> 1 | X4: =IF(L4="",0,IF(ISNUMBER(SEARCH("Office",L4)),1,0)) -> 0 | Y4: =IF(L4="",0,IF(ISNUMBER(SEARCH("Bedroom",L4)),1,0)) -> 0 | Z4: =IF(L4="",0,IF(ISNUMBER(SEARCH("Living room",L4)),1,0)) -> 0 | AA4: =IF(M4="",0, IF(ISNUMBER(SEARCH("By yourself",M4)), 1, 0)) -> 1 | AB4: =IF(M4="", 0, IF(ISNUMBER(SEARCH("Friends", M4)), 1, 0)) -> 0 | AC4: =IF(M4="",0,IF(ISNUMBER(SEARCH("Family members", M4)), 1, 0)) -> 0 | AD4: =IF(M4="", 0, IF(ISNUMBER(SEARCH("Coworkers/Classmates", M4)), 1, 0)) -> 1 | AE4: =IF(M4="", 0, IF(ISNUMBER(SEARCH("Strangers", M4)), 1, 0)) -> 0 | AF4: =IF(N4="", 0, IF(ISNUMBER(SEARCH("Spring", N4)), 1, 0)) -> 0 | AG4: =IF(N4="", 0, IF(ISNUMBER(SEARCH("Summer", N4)), 1, 0)) -> 0 | AH4: =IF(N4="", 0, IF(ISNUMBER(SEARCH("Fall", N4)), 1, 0)) -> 1 | AI4: =IF(N4="", 0, IF(ISNUMBER(SEARCH("Winter", N4)), 1, 0)) -> 0
A5: 4 | B5: The Persistence of Memory | C5: 7 | D5: Deflated | E5: 4 - Agree | F5: 1 - Strongly disagree | G5: 2 - Disagree | H5: 4 - Agree | I5: 10 | J5: 7 | K5: a | L5: Bedroom,Bathroom | M5: Coworkers/Classmates | N5: Winter | O5: a | P5: q | Q5: =IF(E5="", "", LEFT(E5, 1) * 1) -> 4 | R5: =IF(F5="","",VALUE(LEFT(F5,FIND(" ",F5)-1))) -> 1 | S5: =IF(G5="","",VALUE(LEFT(G5,FIND(" ",G5)-1))) -> 2 | T5: =IF(H5="","",VALUE(LEFT(H5,FIND(" ",H5)-1))) -> 4 | V5: =IF(L5="",0,IF(ISNUMBER(SEARCH("Bathroom",L5)),1,0)) -> 1 | W5: =IF(L5="",0,IF(ISNUMBER(SEARCH("Dining room",L5)),1,0)) -> 0 | X5: =IF(L5="",0,IF(ISNUMBER(SEARCH("Office",L5)),1,0)) -> 0 | Y5: =IF(L5="",0,IF(ISNUMBER(SEARCH("Bedroom",L5)),1,0)) -> 1 | Z5: =IF(L5="",0,IF(ISNUMBER(SEARCH("Living room",L5)),1,0)) -> 0 | AA5: =IF(M5="",0, IF(ISNUMBER(SEARCH("By yourself",M5)), 1, 0)) -> 0 | AB5: =IF(M5="", 0, IF(ISNUMBER(SEARCH("Friends", M5)), 1, 0)) -> 0 | AC5: =IF(M5="",0,IF(ISNUMBER(SEARCH("Family members", M5)), 1, 0)) -> 0 | AD5: =IF(M5="", 0, IF(ISNUMBER(SEARCH("Coworkers/Classmates", M5)), 1, 0)) -> 1 | AE5: =IF(M5="", 0, IF(ISNUMBER(SEARCH("Strangers", M5)), 1, 0)) -> 0 | AF5: =IF(N5="", 0, IF(ISNUMBER(SEARCH("Spring", N5)), 1, 0)) -> 0 | AG5: =IF(N5="", 0, IF(ISNUMBER(SEARCH("Summer", N5)), 1, 0)) -> 0 | AH5: =IF(N5="", 0, IF(ISNUMBER(SEARCH("Fall", N5)), 1, 0)) -> 0 | AI5: =IF(N5="", 0, IF(ISNUMBER(SEARCH("Winter", N5)), 1, 0)) -> 1
A6: 5 | B6: The Persistence of Memory | C6: 7 | D6: The painting gives me a sense of calmness and plenitude. It has an ominous and nostalgic feeling similar to time passing.¬† | E6: 3 - Neutral/Unsure | F6: 4 - Agree | G6: 5 - Strongly agree | H6: 3 - Neutral/Unsure | I6: 4 | J6: 6 | K6: 300 dollars. | L6: Living room | M6: Friends | N6: Spring,Summer | O6: Churros. | P6: Radiohead's album in rainbows. | Q6: =IF(E6="", "", LEFT(E6, 1) * 1) -> 3 | R6: =IF(F6="","",VALUE(LEFT(F6,FIND(" ",F6)-1))) -> 4 | S6: =IF(G6="","",VALUE(LEFT(G6,FIND(" ",G6)-1))) -> 5 | T6: =IF(H6="","",VALUE(LEFT(H6,FIND(" ",H6)-1))) -> 3 | U6: 300 | V6: =IF(L6="",0,IF(ISNUMBER(SEARCH("Bathroom",L6)),1,0)) -> 0 | W6: =IF(L6="",0,IF(ISNUMBER(SEARCH("Dining room",L6)),1,0)) -> 0 | X6: =IF(L6="",0,IF(ISNUMBER(SEARCH("Office",L6)),1,0)) -> 0 | Y6: =IF(L6="",0,IF(ISNUMBER(SEARCH("Bedroom",L6)),1,0)) -> 0 | Z6: =IF(L6="",0,IF(ISNUMBER(SEARCH("Living room",L6)),1,0)) -> 1 | AA6: =IF(M6="",0, IF(ISNUMBER(SEARCH("By yourself",M6)), 1, 0)) -> 0 | AB6: =IF(M6="", 0, IF(ISNUMBER(SEARCH("Friends", M6)), 1, 0)) -> 1 | AC6: =IF(M6="",0,IF(ISNUMBER(SEARCH("Family members", M6)), 1, 0)) -> 0 | AD6: =IF(M6="", 0, IF(ISNUMBER(SEARCH("Coworkers/Classmates", M6)), 1, 0)) -> 0 | AE6: =IF(M6="", 0, IF(ISNUMBER(SEARCH("Strangers", M6)), 1, 0)) -> 0 | AF6: =IF(N6="", 0, IF(ISNUMBER(SEARCH("Spring", N6)), 1, 0)) -> 1 | AG6: =IF(N6="", 0, IF(ISNUMBER(SEARCH("Summer", N6)), 1, 0)) -> 1 | AH6: =IF(N6="", 0, IF(ISNUMBER(SEARCH("Fall", N6)), 1, 0)) -> 0 | AI6: =IF(N6="", 0, IF(ISNUMBER(SEARCH("Winter", N6)), 1, 0)) -> 0
A7: 6 | B7: The Persistence of Memory | C7: 7 | D7: This painting makes me feel a bit confused and bewildered, as the objects and art style make me feel detached from reality. | E7: 4 - Agree | F7: 2 - Disagree | G7: 1 - Strongly disagree | H7: 5 - Strongly agree | I7: 5 | J7: 6 | K7: 90000 | L7: Office,Living room | M7: Friends,Family members,By yourself | N7: Summer,Fall | O7: Shepherd's pie | P7: The soundtrack should sound heavy, sombre, and like a finale to an event. It should be slow but without too much emotion. | Q7: =IF(E7="", "", LEFT(E7, 1) * 1) -> 4 | R7: =IF(F7="","",VALUE(LEFT(F7,FIND(" ",F7)-1))) -> 2 | S7: =IF(G7="","",VALUE(LEFT(G7,FIND(" ",G7)-1))) -> 1 | T7: =IF(H7="","",VALUE(LEFT(H7,FIND(" ",H7)-1))) -> 5 | U7: 90000 | V7: =IF(L7="",0,IF(ISNUMBER(SEARCH("Bathroom",L7)),1,0)) -> 0 | W7: =IF(L7="",0,IF(ISNUMBER(SEARCH("Dining room",L7)),1,0)) -> 0 | X7: =IF(L7="",0,IF(ISNUMBER(SEARCH("Office",L7)),1,0)) -> 1 | Y7: =IF(L7="",0,IF(ISNUMBER(SEARCH("Bedroom",L7)),1,0)) -> 0 | Z7: =IF(L7="",0,IF(ISNUMBER(SEARCH("Living room",L7)),1,0)) -> 1 | AA7: =IF(M7="",0, IF(ISNUMBER(SEARCH("By yourself",M7)), 1, 0)) -> 1 | AB7: =IF(M7="", 0, IF(ISNUMBER(SEARCH("Friends", M7)), 1, 0)) -> 1 | AC7: =IF(M7="",0,IF(ISNUMBER(SEARCH("Family members", M7)), 1, 0)) -> 1 | AD7: =IF(M7="", 0, IF(ISNUMBER(SEARCH("Coworkers/Classmates", M7)), 1, 0)) -> 0 | AE7: =IF(M7="", 0, IF(ISNUMBER(SEARCH("Strangers", M7)), 1, 0)) -> 0 | AF7: =IF(N7="", 0, IF(ISNUMBER(SEARCH("Spring", N7)), 1, 0)) -> 0 | AG7: =IF(N7="", 0, IF(ISNUMBER(SEARCH("Summer", N7)), 1, 0)) -> 1 | AH7: =IF(N7="", 0, IF(ISNUMBER(SEARCH("Fall", N7)), 1, 0)) -> 1 | AI7: =IF(N7="", 0, IF(ISNUMBER(SEARCH("Winter", N7)), 1, 0)) -> 0
A8: 7 | B8: The Persistence of Memory | C8: 8 | D8: It has a sorrow feeling and clock is melting feel like time is decaying. | E8: 4 - Agree | F8: 2 - Disagree | G8: 2 - Disagree | H8: 4 - Agree | I8: 3 | J8: 3 | K8: 0 | L8: Office | M8: By yourself | N8: Winter | O8: 10 days old lasagna | P8: A truly sorrow, minor key orchestra piece | Q8: =IF(E8="", "", LEFT(E8, 1) * 1) -> 4 | R8: =IF(F8="","",VALUE(LEFT(F8,FIND(" ",F8)-1))) -> 2 | S8: =IF(G8="","",VALUE(LEFT(G8,FIND(" ",G8)-1))) -> 2 | T8: =IF(H8="","",VALUE(LEFT(H8,FIND(" ",H8)-1))) -> 4 | U8: 0 | V8: =IF(L8="",0,IF(ISNUMBER(SEARCH("Bathroom",L8)),1,0)) -> 0 | W8: =IF(L8="",0,IF(ISNUMBER(SEARCH("Dining room",L8)),1,0)) -> 0 | X8: =IF(L8="",0,IF(ISNUMBER(SEARCH("Office",L8)),1,0)) -> 1 | Y8: =IF(L8="",0,IF(ISNUMBER(SEARCH("Bedroom",L8)),1,0)) -> 0 | Z8: =IF(L8="",0,IF(ISNUMBER(SEARCH("Living room",L8)),1,0)) -> 0 | AA8: =IF(M8="",0, IF(ISNUMBER(SEARCH("By yourself",M8)), 1, 0)) -> 1 | AB8: =IF(M8="", 0, IF(ISNUMBER(SEARCH("Friends", M8)), 1, 0)) -> 0 | AC8: =IF(M8="",0,IF(ISNUMBER(SEARCH("Family members", M8)), 1, 0)) -> 0 | AD8: =IF(M8="", 0, IF(ISNUMBER(SEARCH("Coworkers/Classmates", M8)), 1, 0)) -> 0 | AE8: =IF(M8="", 0, IF(ISNUMBER(SEARCH("Strangers", M8)), 1, 0)) -> 0 | AF8: =IF(N8="", 0, IF(ISNUMBER(SEARCH("Spring", N8)), 1, 0)) -> 0 | AG8: =IF(N8="", 0, IF(ISNUMBER(SEARCH("Summer", N8)), 1, 0)) -> 0 | AH8: =IF(N8="", 0, IF(ISNUMBER(SEARCH("Fall", N8)), 1, 0)) -> 0 | AI8: =IF(N8="", 0, IF(ISNUMBER(SEARCH("Winter", N8)), 1, 0)) -> 1
A9: 8 | B9: The Persistence of Memory | C9: 4 | D9: The painting makes me feel somewhat sad, thinking about the passage of time. | E9: 4 - Agree | F9: 2 - Disagree | G9: 2 - Disagree | H9: 4 - Agree | I9: 7 | J9: 8 | K9: 150 | L9: Office | M9: By yourself | N9: Winter | O9: Grilled Salmon with a Beurre Blanc sauce. | P9: Slow, somewhat sad piano or violin piece. | Q9: =IF(E9="", "", LEFT(E9, 1) * 1) -> 4 | R9: =IF(F9="","",VALUE(LEFT(F9,FIND(" ",F9)-1))) -> 2 | S9: =IF(G9="","",VALUE(LEFT(G9,FIND(" ",G9)-1))) -> 2 | T9: =IF(H9="","",VALUE(LEFT(H9,FIND(" ",H9)-1))) -> 4 | U9: 150 | V9: =IF(L9="",0,IF(ISNUMBER(SEARCH("Bathroom",L9)),1,0)) -> 0 | W9: =IF(L9="",0,IF(ISNUMBER(SEARCH("Dining room",L9)),1,0)) -> 0 | X9: =IF(L9="",0,IF(ISNUMBER(SEARCH("Office",L9)),1,0)) -> 1 | Y9: =IF(L9="",0,IF(ISNUMBER(SEARCH("Bedroom",L9)),1,0)) -> 0 | Z9: =IF(L9="",0,IF(ISNUMBER(SEARCH("Living room",L9)),1,0)) -> 0 | AA9: =IF(M9="",0, IF(ISNUMBER(SEARCH("By yourself",M9)), 1, 0)) -> 1 | AB9: =IF(M9="", 0, IF(ISNUMBER(SEARCH("Friends", M9)), 1, 0)) -> 0 | AC9: =IF(M9="",0,IF(ISNUMBER(SEARCH("Family members", M9)), 1, 0)) -> 0 | AD9: =IF(M9="", 0, IF(ISNUMBER(SEARCH("Coworkers/Classmates", M9)), 1, 0)) -> 0 | AE9: =IF(M9="", 0, IF(ISNUMBER(SEARCH("Strangers", M9)), 1, 0)) -> 0 | AF9: =IF(N9="", 0, IF(ISNUMBER(SEARCH("Spring", N9)), 1, 0)) -> 0 | AG9: =IF(N9="", 0, IF(ISNUMBER(SEARCH("Summer", N9)), 1, 0)) -> 0 | AH9: =IF(N9="", 0, IF(ISNUMBER(SEARCH("Fall", N9)), 1, 0)) -> 0 | AI9: =IF(N9="", 0, IF(ISNUMBER(SEARCH("Winter", N9)), 1, 0)) -> 1
A10: 9 | B10: The Persistence of Memory | C10: 8 | D10: eerie, moody, confused | E10: 5 - Strongly agree | F10: 2 - Disagree | G10: 2 - Disagree | H10: 4 - Agree | I10: 3 | J10: 4 | K10: 20 | L10: Office | M10: Friends | N10: Fall | O10: pizza | P10: ticking clock horror movie soundtrack | Q10: =IF(E10="", "", LEFT(E10, 1) * 1) -> 5 | R10: =IF(F10="","",VALUE(LEFT(F10,FIND(" ",F10)-1))) -> 2 | S10: =IF(G10="","",VALUE(LEFT(G10,FIND(" ",G10)-1))) -> 2 | T10: =IF(H10="","",VALUE(LEFT(H10,FIND(" ",H10)-1))) -> 4 | U10: 20 | V10: =IF(L10="",0,IF(ISNUMBER(SEARCH("Bathroom",L10)),1,0)) -> 0 | W10: =IF(L10="",0,IF(ISNUMBER(SEARCH("Dining room",L10)),1,0)) -> 0 | X10: =IF(L10="",0,IF(ISNUMBER(SEARCH("Office",L10)),1,0)) -> 1 | Y10: =IF(L10="",0,IF(ISNUMBER(SEARCH("Bedroom",L10)),1,0)) -> 0 | Z10: =IF(L10="",0,IF(ISNUMBER(SEARCH("Living room",L10)),1,0)) -> 0 | AA10: =IF(M10="",0, IF(ISNUMBER(SEARCH("By yourself",M10)), 1, 0)) -> 0 | AB10: =IF(M10="", 0, IF(ISNUMBER(SEARCH("Friends", M10)), 1, 0)) -> 1 | AC10: =IF(M10="",0,IF(ISNUMBER(SEARCH("Family members", M10)), 1, 0)) -> 0 | AD10: =IF(M10="", 0, IF(ISNUMBER(SEARCH("Coworkers/Classmates", M10)), 1, 0)) -> 0 | AE10: =IF(M10="", 0, IF(ISNUMBER(SEARCH("Strangers", M10)), 1, 0)) -> 0 | AF10: =IF(N10="", 0, IF(ISNUMBER(SEARCH("Spring", N10)), 1, 0)) -> 0 | AG10: =IF(N10="", 0, IF(ISNUMBER(SEARCH("Summer", N10)), 1, 0)) -> 0 | AH10: =IF(N10="", 0, IF(ISNUMBER(SEARCH("Fall", N10)), 1, 0)) -> 1 | AI10: =IF(N10="", 0, IF(ISNUMBER(SEARCH("Winter", N10)), 1, 0)) -> 0
A11: 10 | B11: The Persistence of Memory | C11: 10 | D11: The painting gives me a sense of nostalgia and mourning. Although the setting is surreal, it feels like I am looking at a part of my life which has gone and passed forever and is warped upon reflection. | E11: 5 - Strongly agree | F11: 3 - Neutral/Unsure | G11: 1 - Strongly disagree | H11: 5 - Strongly agree | I11: 3 | J11: 5 | K11: 100000000 | L11: Living room | M11: Friends,Family members,By yourself | N11: Fall | O11: flan | P11: The soundtrack would be somber and nostalgic, with a solemn yearning for the past.¬† | Q11: =IF(E11="", "", LEFT(E11, 1) * 1) -> 5 | R11: =IF(F11="","",VALUE(LEFT(F11,FIND(" ",F11)-1))) -> 3 | S11: =IF(G11="","",VALUE(LEFT(G11,FIND(" ",G11)-1))) -> 1 | T11: =IF(H11="","",VALUE(LEFT(H11,FIND(" ",H11)-1))) -> 5 | U11: 100000000 | V11: =IF(L11="",0,IF(ISNUMBER(SEARCH("Bathroom",L11)),1,0)) -> 0 | W11: =IF(L11="",0,IF(ISNUMBER(SEARCH("Dining room",L11)),1,0)) -> 0 | X11: =IF(L11="",0,IF(ISNUMBER(SEARCH("Office",L11)),1,0)) -> 0 | Y11: =IF(L11="",0,IF(ISNUMBER(SEARCH("Bedroom",L11)),1,0)) -> 0 | Z11: =IF(L11="",0,IF(ISNUMBER(SEARCH("Living room",L11)),1,0)) -> 1 | AA11: =IF(M11="",0, IF(ISNUMBER(SEARCH("By yourself",M11)), 1, 0)) -> 1 | AB11: =IF(M11="", 0, IF(ISNUMBER(SEARCH("Friends", M11)), 1, 0)) -> 1 | AC11: =IF(M11="",0,IF(ISNUMBER(SEARCH("Family members", M11)), 1, 0)) -> 1 | AD11: =IF(M11="", 0, IF(ISNUMBER(SEARCH("Coworkers/Classmates", M11)), 1, 0)) -> 0 | AE11: =IF(M11="", 0, IF(ISNUMBER(SEARCH("Strangers", M11)), 1, 0)) -> 0 | AF11: =IF(N11="", 0, IF(ISNUMBER(SEARCH("Spring", N11)), 1, 0)) -> 0 | AG11: =IF(N11="", 0, IF(ISNUMBER(SEARCH("Summer", N11)), 1, 0)) -> 0 | AH11: =IF(N11="", 0, IF(ISNUMBER(SEARCH("Fall", N11)), 1, 0)) -> 1 | AI11: =IF(N11="", 0, IF(ISNUMBER(SEARCH("Winter", N11)), 1, 0)) -> 0
A12: 11 | B12: The Persistence of Memory | C12: 7 | D12: The painting makes me feel lathargic. | E12: 4 - Agree | F12: 2 - Disagree | G12: 4 - Agree | H12: 3 - Neutral/Unsure | I12: 3 | J12: 5 | K12: 400 | L12: Office,Dining room | M12: By yourself | N12: Fall | O12: Soup | P12: Low bpm | Q12: =IF(E12="", "", LEFT(E12, 1) * 1) -> 4 | R12: =IF(F12="","",VALUE(LEFT(F12,FIND(" ",F12)-1))) -> 2 | S12: =IF(G12="","",VALUE(LEFT(G12,FIND(" ",G12)-1))) -> 4 | T12: =IF(H12="","",VALUE(LEFT(H12,FIND(" ",H12)-1))) -> 3 | U12: 400 | V12: =IF(L12="",0,IF(ISNUMBER(SEARCH("Bathroom",L12)),1,0)) -> 0 | W12: =IF(L12="",0,IF(ISNUMBER(SEARCH("Dining room",L12)),1,0)) -> 1 | X12: =IF(L12="",0,IF(ISNUMBER(SEARCH("Office",L12)),1,0)) -> 1 | Y12: =IF(L12="",0,IF(ISNUMBER(SEARCH("Bedroom",L12)),1,0)) -> 0 | Z12: =IF(L12="",0,IF(ISNUMBER(SEARCH("Living room",L12)),1,0)) -> 0 | AA12: =IF(M12="",0, IF(ISNUMBER(SEARCH("By yourself",M12)), 1, 0)) -> 1 | AB12: =IF(M12="", 0, IF(ISNUMBER(SEARCH("Friends", M12)), 1, 0)) -> 0 | AC12: =IF(M12="",0,IF(ISNUMBER(SEARCH("Family members", M12)), 1, 0)) -> 0 | AD12: =IF(M12="", 0, IF(ISNUMBER(SEARCH("Coworkers/Classmates", M12)), 1, 0)) -> 0 | AE12: =IF(M12="", 0, IF(ISNUMBER(SEARCH("Strangers", M12)), 1, 0)) -> 0 | AF12: =IF(N12="", 0, IF(ISNUMBER(SEARCH("Spring", N12)), 1, 0)) -> 0 | AG12: =IF(N12="", 0, IF(ISNUMBER(SEARCH("Summer", N12)), 1, 0)) -> 0 | AH12: =IF(N12="", 0, IF(ISNUMBER(SEARCH("Fall", N12)), 1, 0)) -> 1 | AI12: =IF(N12="", 0, IF(ISNUMBER(SEARCH("Winter", N12)), 1, 0)) -> 0
A13: 12 | B13: The Persistence of Memory | C13: 8 | D13: World goes to an end. | E13: 3 - Neutral/Unsure | F13: 2 - Disagree | G13: 3 - Neutral/Unsure | H13: 3 - Neutral/Unsure | I13: 3 | J13: 3 | K13: 1000 | L13: Bedroom | M13: Friends,Family members,By yourself | N13: Fall | O13: A black chocolate. | P13: The soundtrack is cold, giving a scene of ¬†million years after a global disaster. | Q13: =IF(E13="", "", LEFT(E13, 1) * 1) -> 3 | R13: =IF(F13="","",VALUE(LEFT(F13,FIND(" ",F13)-1))) -> 2 | S13: =IF(G13="","",VALUE(LEFT(G13,FIND(" ",G13)-1))) -> 3 | T13: =IF(H13="","",VALUE(LEFT(H13,FIND(" ",H13)-1))) -> 3 | U13: 1000 | V13: =IF(L13="",0,IF(ISNUMBER(SEARCH("Bathroom",L13)),1,0)) -> 0 | W13: =IF(L13="",0,IF(ISNUMBER(SEARCH("Dining room",L13)),1,0)) -> 0 | X13: =IF(L13="",0,IF(ISNUMBER(SEARCH("Office",L13)),1,0)) -> 0 | Y13: =IF(L13="",0,IF(ISNUMBER(SEARCH("Bedroom",L13)),1,0)) -> 1 | Z13: =IF(L13="",0,IF(ISNUMBER(SEARCH("Living room",L13)),1,0)) -> 0 | AA13: =IF(M13="",0, IF(ISNUMBER(SEARCH("By yourself",M13)), 1, 0)) -> 1 | AB13: =IF(M13="", 0, IF(ISNUMBER(SEARCH("Friends", M13)), 1, 0)) -> 1 | AC13: =IF(M13="",0,IF(ISNUMBER(SEARCH("Family members", M13)), 1, 0)) -> 1 | AD13: =IF(M13="", 0, IF(ISNUMBER(SEARCH("Coworkers/Classmates", M13)), 1, 0)) -> 0 | AE13: =IF(M13="", 0, IF(ISNUMBER(SEARCH("Strangers", M13)), 1, 0)) -> 0 | AF13: =IF(N13="", 0, IF(ISNUMBER(SEARCH("Spring", N13)), 1, 0)) -> 0 | AG13: =IF(N13="", 0, IF(ISNUMBER(SEARCH("Summer", N13)), 1, 0)) -> 0 | AH13: =IF(N13="", 0, IF(ISNUMBER(SEARCH("Fall", N13)), 1, 0)) -> 1 | AI13: =IF(N13="", 0, IF(ISNUMBER(SEARCH("Winter", N13)), 1, 0)) -> 0
A14: 13 | B14: The Persistence of Memory | C14: 7 | D14: I feel shocked and discomfort. | E14: 5 - Strongly agree | F14: 1 - Strongly disagree | G14: 2 - Disagree | H14: 5 - Strongly agree | I14: 7 | J14: 8 | K14: 5 000 000$ | L14: Bedroom,Office | M14: Friends,Family members,By yourself | N14: Fall | O14: oreo | P14: A very solemn soundtrack. | Q14: =IF(E14="", "", LEFT(E14, 1) * 1) -> 5 | R14: =IF(F14="","",VALUE(LEFT(F14,FIND(" ",F14)-1))) -> 1 | S14: =IF(G14="","",VALUE(LEFT(G14,FIND(" ",G14)-1))) -> 2 | T14: =IF(H14="","",VALUE(LEFT(H14,FIND(" ",H14)-1))) -> 5 | U14: 5000000 | V14: =IF(L14="",0,IF(ISNUMBER(SEARCH("Bathroom",L14)),1,0)) -> 0 | W14: =IF(L14="",0,IF(ISNUMBER(SEARCH("Dining room",L14)),1,0)) -> 0 | X14: =IF(L14="",0,IF(ISNUMBER(SEARCH("Office",L14)),1,0)) -> 1 | Y14: =IF(L14="",0,IF(ISNUMBER(SEARCH("Bedroom",L14)),1,0)) -> 1 | Z14: =IF(L14="",0,IF(ISNUMBER(SEARCH("Living room",L14)),1,0)) -> 0 | AA14: =IF(M14="",0, IF(ISNUMBER(SEARCH("By yourself",M14)), 1, 0)) -> 1 | AB14: =IF(M14="", 0, IF(ISNUMBER(SEARCH("Friends", M14)), 1, 0)) -> 1 | AC14: =IF(M14="",0,IF(ISNUMBER(SEARCH("Family members", M14)), 1, 0)) -> 1 | AD14: =IF(M14="", 0, IF(ISNUMBER(SEARCH("Coworkers/Classmates", M14)), 1, 0)) -> 0 | AE14: =IF(M14="", 0, IF(ISNUMBER(SEARCH("Strangers", M14)), 1, 0)) -> 0 | AF14: =IF(N14="", 0, IF(ISNUMBER(SEARCH("Spring", N14)), 1, 0)) -> 0 | AG14: =IF(N14="", 0, IF(ISNUMBER(SEARCH("Summer", N14)), 1, 0)) -> 0 | AH14: =IF(N14="", 0, IF(ISNUMBER(SEARCH("Fall", N14)), 1, 0)) -> 1 | AI14: =IF(N14="", 0, IF(ISNUMBER(SEARCH("Winter", N14)), 1, 0)) -> 0
A15: 14 | B15: The Persistence of Memory | C15: 6 | D15: The painting makes me feel nostalgic and sad. The sunset conveys a calming ending feeling while the clocks melting away induces a feeling of the duration and longing where time loses its meaning. While it conveys to me of the inevitable passing of my limited amount of time, it also reminds me of the greatest times and memories I have experienced in my life. | E15: 4 - Agree | F15: 3 - Neutral/Unsure | G15: 4 - Agree | H15: 4 - Agree | I15: 5 | J15: 3 | K15: 100000 | L15: Living room,Dining room | M15: Friends,Strangers,By yourself | N15: Summer,Fall | O15: A chocolate dessert | P15: Slow, calm rhythm. No intense variations in melody. Strongly harmonic. | Q15: =IF(E15="", "", LEFT(E15, 1) * 1) -> 4 | R15: =IF(F15="","",VALUE(LEFT(F15,FIND(" ",F15)-1))) -> 3 | S15: =IF(G15="","",VALUE(LEFT(G15,FIND(" ",G15)-1))) -> 4 | T15: =IF(H15="","",VALUE(LEFT(H15,FIND(" ",H15)-1))) -> 4 | U15: 100000 | V15: =IF(L15="",0,IF(ISNUMBER(SEARCH("Bathroom",L15)),1,0)) -> 0 | W15: =IF(L15="",0,IF(ISNUMBER(SEARCH("Dining room",L15)),1,0)) -> 1 | X15: =IF(L15="",0,IF(ISNUMBER(SEARCH("Office",L15)),1,0)) -> 0 | Y15: =IF(L15="",0,IF(ISNUMBER(SEARCH("Bedroom",L15)),1,0)) -> 0 | Z15: =IF(L15="",0,IF(ISNUMBER(SEARCH("Living room",L15)),1,0)) -> 1 | AA15: =IF(M15="",0, IF(ISNUMBER(SEARCH("By yourself",M15)), 1, 0)) -> 1 | AB15: =IF(M15="", 0, IF(ISNUMBER(SEARCH("Friends", M15)), 1, 0)) -> 1 | AC15: =IF(M15="",0,IF(ISNUMBER(SEARCH("Family members", M15)), 1, 0)) -> 0 | AD15: =IF(M15="", 0, IF(ISNUMBER(SEARCH("Coworkers/Classmates", M15)), 1, 0)) -> 0 | AE15: =IF(M15="", 0, IF(ISNUMBER(SEARCH("Strangers", M15)), 1, 0)) -> 1 | AF15: =IF(N15="", 0, IF(ISNUMBER(SEARCH("Spring", N15)), 1, 0)) -> 0 | AG15: =IF(N15="", 0, IF(ISNUMBER(SEARCH("Summer", N15)), 1, 0)) -> 1 | AH15: =IF(N15="", 0, IF(ISNUMBER(SEARCH("Fall", N15)), 1, 0)) -> 1 | AI15: =IF(N15="", 0, IF(ISNUMBER(SEARCH("Winter", N15)), 1, 0)) -> 0
A16: 15 | B16: The Persistence of Memory | C16: 3 | D16: It makes me feel a bit anxious or sad since it seems to symbolize time melting away. | E16: 4 - Agree | F16: 3 - Neutral/Unsure | G16: 4 - Agree | H16: 1 - Strongly disagree | I16: 3 | J16: 5 | K16: 5000 | L16: Office | M16: By yourself | N16: Summer | O16: Scrambled eggs | P16: It would probably be slow and a little sad but not creepy or eerie. | Q16: =IF(E16="", "", LEFT(E16, 1) * 1) -> 4 | R16: =IF(F16="","",VALUE(LEFT(F16,FIND(" ",F16)-1))) -> 3 | S16: =IF(G16="","",VALUE(LEFT(G16,FIND(" ",G16)-1))) -> 4 | T16: =IF(H16="","",VALUE(LEFT(H16,FIND(" ",H16)-1))) -> 1 | U16: 5000 | V16: =IF(L16="",0,IF(ISNUMBER(SEARCH("Bathroom",L16)),1,0)) -> 0 | W16: =IF(L16="",0,IF(ISNUMBER(SEARCH("Dining room",L16)),1,0)) -> 0 | X16: =IF(L16="",0,IF(ISNUMBER(SEARCH("Office",L16)),1,0)) -> 1 | Y16: =IF(L16="",0,IF(ISNUMBER(SEARCH("Bedroom",L16)),1,0)) -> 0 | Z16: =IF(L16="",0,IF(ISNUMBER(SEARCH("Living room",L16)),1,0)) -> 0 | AA16: =IF(M16="",0, IF(ISNUMBER(SEARCH("By yourself",M16)), 1, 0)) -> 1 | AB16: =IF(M16="", 0, IF(ISNUMBER(SEARCH("Friends", M16)), 1, 0)) -> 0 | AC16: =IF(M16="",0,IF(ISNUMBER(SEARCH("Family members", M16)), 1, 0)) -> 0 | AD16: =IF(M16="", 0, IF(ISNUMBER(SEARCH("Coworkers/Classmates", M16)), 1, 0)) -> 0 | AE16: =IF(M16="", 0, IF(ISNUMBER(SEARCH("Strangers", M16)), 1, 0)) -> 0 | AF16: =IF(N16="", 0, IF(ISNUMBER(SEARCH("Spring", N16)), 1, 0)) -> 0 | AG16: =IF(N16="", 0, IF(ISNUMBER(SEARCH("Summer", N16)), 1, 0)) -> 1 | AH16: =IF(N16="", 0, IF(ISNUMBER(SEARCH("Fall", N16)), 1, 0)) -> 0 | AI16: =IF(N16="", 0, IF(ISNUMBER(SEARCH("Winter", N16)), 1, 0)) -> 0
A17: 16 | B17: The Persistence of Memory | C17: 8 | D17: This painting makes me feel a sense a fleeting emotions and temporality. I like the use of colour because as the sun sets, it makes me feel like there will be a tomorrow whilst grieving the today. | E17: 4 - Agree | F17: 3 - Neutral/Unsure | G17: 4 - Agree | H17: 2 - Disagree | I17: 4 | J17: 4 | K17: 1500000 | L17: Living room | M17: By yourself | N17: Fall | O17: Banana | P17: The soundtrack would be calm and serene. There's a weird uneasiness to it though, that things won't last and a feeling that you'll lose it all. | Q17: =IF(E17="", "", LEFT(E17, 1) * 1) -> 4 | R17: =IF(F17="","",VALUE(LEFT(F17,FIND(" ",F17)-1))) -> 3 | S17: =IF(G17="","",VALUE(LEFT(G17,FIND(" ",G17)-1))) -> 4 | T17: =IF(H17="","",VALUE(LEFT(H17,FIND(" ",H17)-1))) -> 2 | U17: 1500000 | V17: =IF(L17="",0,IF(ISNUMBER(SEARCH("Bathroom",L17)),1,0)) -> 0 | W17: =IF(L17="",0,IF(ISNUMBER(SEARCH("Dining room",L17)),1,0)) -> 0 | X17: =IF(L17="",0,IF(ISNUMBER(SEARCH("Office",L17)),1,0)) -> 0 | Y17: =IF(L17="",0,IF(ISNUMBER(SEARCH("Bedroom",L17)),1,0)) -> 0 | Z17: =IF(L17="",0,IF(ISNUMBER(SEARCH("Living room",L17)),1,0)) -> 1 | AA17: =IF(M17="",0, IF(ISNUMBER(SEARCH("By yourself",M17)), 1, 0)) -> 1 | AB17: =IF(M17="", 0, IF(ISNUMBER(SEARCH("Friends", M17)), 1, 0)) -> 0 | AC17: =IF(M17="",0,IF(ISNUMBER(SEARCH("Family members", M17)), 1, 0)) -> 0 | AD17: =IF(M17="", 0, IF(ISNUMBER(SEARCH("Coworkers/Classmates", M17)), 1, 0)) -> 0 | AE17: =IF(M17="", 0, IF(ISNUMBER(SEARCH("Strangers", M17)), 1, 0)) -> 0 | AF17: =IF(N17="", 0, IF(ISNUMBER(SEARCH("Spring", N17)), 1, 0)) -> 0 | AG17: =IF(N17="", 0, IF(ISNUMBER(SEARCH("Summer", N17)), 1, 0)) -> 0 | AH17: =IF(N17="", 0, IF(ISNUMBER(SEARCH("Fall", N17)), 1, 0)) -> 1 | AI17: =IF(N17="", 0, IF(ISNUMBER(SEARCH("Winter", N17)), 1, 0)) -> 0
A18: 17 | B18: The Persistence of Memory | C18: 8 | D18: This painting make me feel weird and little sad. Time look melting and nothing feel normal. It make me think life go fast. | E18: 4 - Agree | F18: 2 - Disagree | G18: 2 - Disagree | H18: 4 - Agree | I18: 5 | J18: 6 | K18: 50 | L18: Office | M18: By yourself | N18: Summer | O18: Old cheese that stay too long | P18: The soundtrack is very slow and quiet. Sound feel empty and long. Notes stretch and feel tired, like waiting and nothing happen. Music feel lonely and strange. | Q18: =IF(E18="", "", LEFT(E18, 1) * 1) -> 4 | R18: =IF(F18="","",VALUE(LEFT(F18,FIND(" ",F18)-1))) -> 2 | S18: =IF(G18="","",VALUE(LEFT(G18,FIND(" ",G18)-1))) -> 2 | T18: =IF(H18="","",VALUE(LEFT(H18,FIND(" ",H18)-1))) -> 4 | U18: 50 | V18: =IF(L18="",0,IF(ISNUMBER(SEARCH("Bathroom",L18)),1,0)) -> 0 | W18: =IF(L18="",0,IF(ISNUMBER(SEARCH("Dining room",L18)),1,0)) -> 0 | X18: =IF(L18="",0,IF(ISNUMBER(SEARCH("Office",L18)),1,0)) -> 1 | Y18: =IF(L18="",0,IF(ISNUMBER(SEARCH("Bedroom",L18)),1,0)) -> 0 | Z18: =IF(L18="",0,IF(ISNUMBER(SEARCH("Living room",L18)),1,0)) -> 0 | AA18: =IF(M18="",0, IF(ISNUMBER(SEARCH("By yourself",M18)), 1, 0)) -> 1 | AB18: =IF(M18="", 0, IF(ISNUMBER(SEARCH("Friends", M18)), 1, 0)) -> 0 | AC18: =IF(M18="",0,IF(ISNUMBER(SEARCH("Family members", M18)), 1, 0)) -> 0 | AD18: =IF(M18="", 0, IF(ISNUMBER(SEARCH("Coworkers/Classmates", M18)), 1, 0)) -> 0 | AE18: =IF(M18="", 0, IF(ISNUMBER(SEARCH("Strangers", M18)), 1, 0)) -> 0 | AF18: =IF(N18="", 0, IF(ISNUMBER(SEARCH("Spring", N18)), 1, 0)) -> 0 | AG18: =IF(N18="", 0, IF(ISNUMBER(SEARCH("Summer", N18)), 1, 0)) -> 1 | AH18: =IF(N18="", 0, IF(ISNUMBER(SEARCH("Fall", N18)), 1, 0)) -> 0 | AI18: =IF(N18="", 0, IF(ISNUMBER(SEARCH("Winter", N18)), 1, 0)) -> 0
A19: 18 | B19: The Persistence of Memory | C19: 9 | D19: It makes me feel lost and sad.¬† | E19: 5 - Strongly agree | F19: 2 - Disagree | G19: 3 - Neutral/Unsure | H19: 4 - Agree | I19: 3 | J19: 5 | K19: 200$ | L19: Office | M19: By yourself | N19: Fall | O19: coconut | P19: the soundtrack would be a violin piece. it would be slow but intense. | Q19: =IF(E19="", "", LEFT(E19, 1) * 1) -> 5 | R19: =IF(F19="","",VALUE(LEFT(F19,FIND(" ",F19)-1))) -> 2 | S19: =IF(G19="","",VALUE(LEFT(G19,FIND(" ",G19)-1))) -> 3 | T19: =IF(H19="","",VALUE(LEFT(H19,FIND(" ",H19)-1))) -> 4 | U19: 200 | V19: =IF(L19="",0,IF(ISNUMBER(SEARCH("Bathroom",L19)),1,0)) -> 0 | W19: =IF(L19="",0,IF(ISNUMBER(SEARCH("Dining room",L19)),1,0)) -> 0 | X19: =IF(L19="",0,IF(ISNUMBER(SEARCH("Office",L19)),1,0)) -> 1 | Y19: =IF(L19="",0,IF(ISNUMBER(SEARCH("Bedroom",L19)),1,0)) -> 0 | Z19: =IF(L19="",0,IF(ISNUMBER(SEARCH("Living room",L19)),1,0)) -> 0 | AA19: =IF(M19="",0, IF(ISNUMBER(SEARCH("By yourself",M19)), 1, 0)) -> 1 | AB19: =IF(M19="", 0, IF(ISNUMBER(SEARCH("Friends", M19)), 1, 0)) -> 0 | AC19: =IF(M19="",0,IF(ISNUMBER(SEARCH("Family members", M19)), 1, 0)) -> 0 | AD19: =IF(M19="", 0, IF(ISNUMBER(SEARCH("Coworkers/Classmates", M19)), 1, 0)) -> 0 | AE19: =IF(M19="", 0, IF(ISNUMBER(SEARCH("Strangers", M19)), 1, 0)) -> 0 | AF19: =IF(N19="", 0, IF(ISNUMBER(SEARCH("Spring", N19)), 1, 0)) -> 0 | AG19: =IF(N19="", 0, IF(ISNUMBER(SEARCH("Summer", N19)), 1, 0)) -> 0 | AH19: =IF(N19="", 0, IF(ISNUMBER(SEARCH("Fall", N19)), 1, 0)) -> 1 | AI19: =IF(N19="", 0, IF(ISNUMBER(SEARCH("Winter", N19)), 1, 0)) -> 0
A20: 19 | B20: The Persistence of Memory | C20: 3 | D20: Shocked, mysterious, unreal¬† | E20: 4 - Agree | F20: 1 - Strongly disagree | G20: 1 - Strongly disagree | H20: 4 - Agree | I20: 3 | J20: 6 | K20: 100 | L20: Dining room | M20: Strangers,By yourself | N20: Winter | O20: A single soft-boiled egg, yolk just barely holding together. | P20: Suspended, quietly unsettling. A single distant piano note drops into the air and lingers far longer than it should, as if streched. | Q20: =IF(E20="", "", LEFT(E20, 1) * 1) -> 4 | R20: =IF(F20="","",VALUE(LEFT(F20,FIND(" ",F20)-1))) -> 1 | S20: =IF(G20="","",VALUE(LEFT(G20,FIND(" ",G20)-1))) -> 1 | T20: =IF(H20="","",VALUE(LEFT(H20,FIND(" ",H20)-1))) -> 4 | U20: 100 | V20: =IF(L20="",0,IF(ISNUMBER(SEARCH("Bathroom",L20)),1,0)) -> 0 | W20: =IF(L20="",0,IF(ISNUMBER(SEARCH("Dining room",L20)),1,0)) -> 1 | X20: =IF(L20="",0,IF(ISNUMBER(SEARCH("Office",L20)),1,0)) -> 0 | Y20: =IF(L20="",0,IF(ISNUMBER(SEARCH("Bedroom",L20)),1,0)) -> 0 | Z20: =IF(L20="",0,IF(ISNUMBER(SEARCH("Living room",L20)),1,0)) -> 0 | AA20: =IF(M20="",0, IF(ISNUMBER(SEARCH("By yourself",M20)), 1, 0)) -> 1 | AB20: =IF(M20="", 0, IF(ISNUMBER(SEARCH("Friends", M20)), 1, 0)) -> 0 | AC20: =IF(M20="",0,IF(ISNUMBER(SEARCH("Family members", M20)), 1, 0)) -> 0 | AD20: =IF(M20="", 0, IF(ISNUMBER(SEARCH("Coworkers/Classmates", M20)), 1, 0)) -> 0 | AE20: =IF(M20="", 0, IF(ISNUMBER(SEARCH("Strangers", M20)), 1, 0)) -> 1 | AF20: =IF(N20="", 0, IF(ISNUMBER(SEARCH("Spring", N20)), 1, 0)) -> 0 | AG20: =IF(N20="", 0, IF(ISNUMBER(SEARCH("Summer", N20)), 1, 0)) -> 0 | AH20: =IF(N20="", 0, IF(ISNUMBER(SEARCH("Fall", N20)), 1, 0)) -> 0 | AI20: =IF(N20="", 0, IF(ISNUMBER(SEARCH("Winter", N20)), 1, 0)) -> 1
A21: 20 | B21: The Persistence of Memory | C21: 6 | D21: Very uneasy | E21: 4 - Agree | F21: 2 - Disagree | G21: 2 - Disagree | H21: 5 - Strongly agree | I21: 4 | J21: 3 | K21: 100 | L21: Office | M21: Coworkers/Classmates | N21: Fall | O21: Coffee | P21: Slow orchestral strings ensemble | Q21: =IF(E21="", "", LEFT(E21, 1) * 1) -> 4 | R21: =IF(F21="","",VALUE(LEFT(F21,FIND(" ",F21)-1))) -> 2 | S21: =IF(G21="","",VALUE(LEFT(G21,FIND(" ",G21)-1))) -> 2 | T21: =IF(H21="","",VALUE(LEFT(H21,FIND(" ",H21)-1))) -> 5 | U21: 100 | V21: =IF(L21="",0,IF(ISNUMBER(SEARCH("Bathroom",L21)),1,0)) -> 0 | W21: =IF(L21="",0,IF(ISNUMBER(SEARCH("Dining room",L21)),1,0)) -> 0 | X21: =IF(L21="",0,IF(ISNUMBER(SEARCH("Office",L21)),1,0)) -> 1 | Y21: =IF(L21="",0,IF(ISNUMBER(SEARCH("Bedroom",L21)),1,0)) -> 0 | Z21: =IF(L21="",0,IF(ISNUMBER(SEARCH("Living room",L21)),1,0)) -> 0 | AA21: =IF(M21="",0, IF(ISNUMBER(SEARCH("By yourself",M21)), 1, 0)) -> 0 | AB21: =IF(M21="", 0, IF(ISNUMBER(SEARCH("Friends", M21)), 1, 0)) -> 0 | AC21: =IF(M21="",0,IF(ISNUMBER(SEARCH("Family members", M21)), 1, 0)) -> 0 | AD21: =IF(M21="", 0, IF(ISNUMBER(SEARCH("Coworkers/Classmates", M21)), 1, 0)) -> 1 | AE21: =IF(M21="", 0, IF(ISNUMBER(SEARCH("Strangers", M21)), 1, 0)) -> 0 | AF21: =IF(N21="", 0, IF(ISNUMBER(SEARCH("Spring", N21)), 1, 0)) -> 0 | AG21: =IF(N21="", 0, IF(ISNUMBER(SEARCH("Summer", N21)), 1, 0)) -> 0 | AH21: =IF(N21="", 0, IF(ISNUMBER(SEARCH("Fall", N21)), 1, 0)) -> 1 | AI21: =IF(N21="", 0, IF(ISNUMBER(SEARCH("Winter", N21)), 1, 0)) -> 0
A22: 21 | B22: The Persistence of Memory | C22: 7 | D22: Perhaps the fragility of time as it passes so quickly. Seeing as the clocks are bended, one almost gets this feeling that the past also loses its importance or fades away as time moves forward. Overall, its sort of a weird feeling.¬† | E22: 4 - Agree | F22: 2 - Disagree | G22: 1 - Strongly disagree | H22: 4 - Agree | I22: 5 | J22: 3 | K22: 50 | L22: Living room | M22: Friends | N22: Winter | O22: Birthday cake | P22: The tides of history move forward and people either choose to stay caught in a specific tide or surf past it.¬† | Q22: =IF(E22="", "", LEFT(E22, 1) * 1) -> 4 | R22: =IF(F22="","",VALUE(LEFT(F22,FIND(" ",F22)-1))) -> 2 | S22: =IF(G22="","",VALUE(LEFT(G22,FIND(" ",G22)-1))) -> 1 | T22: =IF(H22="","",VALUE(LEFT(H22,FIND(" ",H22)-1))) -> 4 | U22: 50 | V22: =IF(L22="",0,IF(ISNUMBER(SEARCH("Bathroom",L22)),1,0)) -> 0 | W22: =IF(L22="",0,IF(ISNUMBER(SEARCH("Dining room",L22)),1,0)) -> 0 | X22: =IF(L22="",0,IF(ISNUMBER(SEARCH("Office",L22)),1,0)) -> 0 | Y22: =IF(L22="",0,IF(ISNUMBER(SEARCH("Bedroom",L22)),1,0)) -> 0 | Z22: =IF(L22="",0,IF(ISNUMBER(SEARCH("Living room",L22)),1,0)) -> 1 | AA22: =IF(M22="",0, IF(ISNUMBER(SEARCH("By yourself",M22)), 1, 0)) -> 0 | AB22: =IF(M22="", 0, IF(ISNUMBER(SEARCH("Friends", M22)), 1, 0)) -> 1 | AC22: =IF(M22="",0,IF(ISNUMBER(SEARCH("Family members", M22)), 1, 0)) -> 0 | AD22: =IF(M22="", 0, IF(ISNUMBER(SEARCH("Coworkers/Classmates", M22)), 1, 0)) -> 0 | AE22: =IF(M22="", 0, IF(ISNUMBER(SEARCH("Strangers", M22)), 1, 0)) -> 0 | AF22: =IF(N22="", 0, IF(ISNUMBER(SEARCH("Spring", N22)), 1, 0)) -> 0 | AG22: =IF(N22="", 0, IF(ISNUMBER(SEARCH("Summer", N22)), 1, 0)) -> 0 | AH22: =IF(N22="", 0, IF(ISNUMBER(SEARCH("Fall", N22)), 1, 0)) -> 0 | AI22: =IF(N22="", 0, IF(ISNUMBER(SEARCH("Winter", N22)), 1, 0)) -> 1
A23: 22 | B23: The Persistence of Memory | C23: 5 | D23: Ominous, it seems like the painting is trying to show how memory, even after years of time spending by, persists, and stays within ones body. | E23: 4 - Agree | F23: 2 - Disagree | G23: 3 - Neutral/Unsure | H23: 4 - Agree | I23: 8 | J23: 9 | K23: 50 | L23: Bedroom | M23: Friends | N23: Winter | O23: rotten tomato | P23: An orchestral soundtrack that commences with a very slow and sombre timbre and steadily keeps on increasing intensity and frequency till it reaches a dull minor scale peak, before descending back into silence. | Q23: =IF(E23="", "", LEFT(E23, 1) * 1) -> 4 | R23: =IF(F23="","",VALUE(LEFT(F23,FIND(" ",F23)-1))) -> 2 | S23: =IF(G23="","",VALUE(LEFT(G23,FIND(" ",G23)-1))) -> 3 | T23: =IF(H23="","",VALUE(LEFT(H23,FIND(" ",H23)-1))) -> 4 | U23: 50 | V23: =IF(L23="",0,IF(ISNUMBER(SEARCH("Bathroom",L23)),1,0)) -> 0 | W23: =IF(L23="",0,IF(ISNUMBER(SEARCH("Dining room",L23)),1,0)) -> 0 | X23: =IF(L23="",0,IF(ISNUMBER(SEARCH("Office",L23)),1,0)) -> 0 | Y23: =IF(L23="",0,IF(ISNUMBER(SEARCH("Bedroom",L23)),1,0)) -> 1 | Z23: =IF(L23="",0,IF(ISNUMBER(SEARCH("Living room",L23)),1,0)) -> 0 | AA23: =IF(M23="",0, IF(ISNUMBER(SEARCH("By yourself",M23)), 1, 0)) -> 0 | AB23: =IF(M23="", 0, IF(ISNUMBER(SEARCH("Friends", M23)), 1, 0)) -> 1 | AC23: =IF(M23="",0,IF(ISNUMBER(SEARCH("Family members", M23)), 1, 0)) -> 0 | AD23: =IF(M23="", 0, IF(ISNUMBER(SEARCH("Coworkers/Classmates", M23)), 1, 0)) -> 0 | AE23: =IF(M23="", 0, IF(ISNUMBER(SEARCH("Strangers", M23)), 1, 0)) -> 0 | AF23: =IF(N23="", 0, IF(ISNUMBER(SEARCH("Spring", N23)), 1, 0)) -> 0 | AG23: =IF(N23="", 0, IF(ISNUMBER(SEARCH("Summer", N23)), 1, 0)) -> 0 | AH23: =IF(N23="", 0, IF(ISNUMBER(SEARCH("Fall", N23)), 1, 0)) -> 0 | AI23: =IF(N23="", 0, IF(ISNUMBER(SEARCH("Winter", N23)), 1, 0)) -> 1
A24: 23 | B24: The Persistence of Memory | C24: 3 | D24: slowed down and lazy. | E24: 4 - Agree | F24: 2 - Disagree | G24: 2 - Disagree | H24: 5 - Strongly agree | I24: 5 | J24: 4 | K24: 50 | L24: Bathroom | M24: By yourself | N24: Winter | O24: cheesecake | P24: slowed classical | Q24: =IF(E24="", "", LEFT(E24, 1) * 1) -> 4 | R24: =IF(F24="","",VALUE(LEFT(F24,FIND(" ",F24)-1))) -> 2 | S24: =IF(G24="","",VALUE(LEFT(G24,FIND(" ",G24)-1))) -> 2 | T24: =IF(H24="","",VALUE(LEFT(H24,FIND(" ",H24)-1))) -> 5 | U24: 50 | V24: =IF(L24="",0,IF(ISNUMBER(SEARCH("Bathroom",L24)),1,0)) -> 1 | W24: =IF(L24="",0,IF(ISNUMBER(SEARCH("Dining room",L24)),1,0)) -> 0 | X24: =IF(L24="",0,IF(ISNUMBER(SEARCH("Office",L24)),1,0)) -> 0 | Y24: =IF(L24="",0,IF(ISNUMBER(SEARCH("Bedroom",L24)),1,0)) -> 0 | Z24: =IF(L24="",0,IF(ISNUMBER(SEARCH("Living room",L24)),1,0)) -> 0 | AA24: =IF(M24="",0, IF(ISNUMBER(SEARCH("By yourself",M24)), 1, 0)) -> 1 | AB24: =IF(M24="", 0, IF(ISNUMBER(SEARCH("Friends", M24)), 1, 0)) -> 0 | AC24: =IF(M24="",0,IF(ISNUMBER(SEARCH("Family members", M24)), 1, 0)) -> 0 | AD24: =IF(M24="", 0, IF(ISNUMBER(SEARCH("Coworkers/Classmates", M24)), 1, 0)) -> 0 | AE24: =IF(M24="", 0, IF(ISNUMBER(SEARCH("Strangers", M24)), 1, 0)) -> 0 | AF24: =IF(N24="", 0, IF(ISNUMBER(SEARCH("Spring", N24)), 1, 0)) -> 0 | AG24: =IF(N24="", 0, IF(ISNUMBER(SEARCH("Summer", N24)), 1, 0)) -> 0 | AH24: =IF(N24="", 0, IF(ISNUMBER(SEARCH("Fall", N24)), 1, 0)) -> 0 | AI24: =IF(N24="", 0, IF(ISNUMBER(SEARCH("Winter", N24)), 1, 0)) -> 1
A25: 24 | B25: The Persistence of Memory | C25: 5 | D25: This painting makes me feel a bit strange. The content in the painting goes against reality, and it feels like there are many elements of imagination and distortion. | E25: 3 - Neutral/Unsure | F25: 3 - Neutral/Unsure | G25: 3 - Neutral/Unsure | H25: 3 - Neutral/Unsure | I25: 5 | J25: 4 | K25: 100 | L25: Bedroom | M25: Family members | N25: Fall | O25: Sandwich | P25: It sounds a bit strange, fairly calm, and somewhat random. | Q25: =IF(E25="", "", LEFT(E25, 1) * 1) -> 3 | R25: =IF(F25="","",VALUE(LEFT(F25,FIND(" ",F25)-1))) -> 3 | S25: =IF(G25="","",VALUE(LEFT(G25,FIND(" ",G25)-1))) -> 3 | T25: =IF(H25="","",VALUE(LEFT(H25,FIND(" ",H25)-1))) -> 3 | U25: 100 | V25: =IF(L25="",0,IF(ISNUMBER(SEARCH("Bathroom",L25)),1,0)) -> 0 | W25: =IF(L25="",0,IF(ISNUMBER(SEARCH("Dining room",L25)),1,0)) -> 0 | X25: =IF(L25="",0,IF(ISNUMBER(SEARCH("Office",L25)),1,0)) -> 0 | Y25: =IF(L25="",0,IF(ISNUMBER(SEARCH("Bedroom",L25)),1,0)) -> 1 | Z25: =IF(L25="",0,IF(ISNUMBER(SEARCH("Living room",L25)),1,0)) -> 0 | AA25: =IF(M25="",0, IF(ISNUMBER(SEARCH("By yourself",M25)), 1, 0)) -> 0 | AB25: =IF(M25="", 0, IF(ISNUMBER(SEARCH("Friends", M25)), 1, 0)) -> 0 | AC25: =IF(M25="",0,IF(ISNUMBER(SEARCH("Family members", M25)), 1, 0)) -> 1 | AD25: =IF(M25="", 0, IF(ISNUMBER(SEARCH("Coworkers/Classmates", M25)), 1, 0)) -> 0 | AE25: =IF(M25="", 0, IF(ISNUMBER(SEARCH("Strangers", M25)), 1, 0)) -> 0 | AF25: =IF(N25="", 0, IF(ISNUMBER(SEARCH("Spring", N25)), 1, 0)) -> 0 | AG25: =IF(N25="", 0, IF(ISNUMBER(SEARCH("Summer", N25)), 1, 0)) -> 0 | AH25: =IF(N25="", 0, IF(ISNUMBER(SEARCH("Fall", N25)), 1, 0)) -> 1 | AI25: =IF(N25="", 0, IF(ISNUMBER(SEARCH("Winter", N25)), 1, 0)) -> 0
A26: 25 | B26: The Persistence of Memory | C26: 7 | D26: This painting makes me feel as though my life is becoming foggy and I am reflecting on life as it was in a better time. As if I can no longer dream and my time is running out in a bleak world where I can no longer return to the person I once was. | E26: 4 - Agree | F26: 2 - Disagree | G26: 2 - Disagree | H26: 4 - Agree | I26: 4 | J26: 7 | K26: 150 | L26: Bedroom,Bathroom | M26: By yourself | N26: Fall | O26: puffer fish | P26: A slightly joyous melody that starts off fast but slows down as the track goes on becoming sadder, with eerie background music that grows louder and faster until the end where the track abruptly stops. | Q26: =IF(E26="", "", LEFT(E26, 1) * 1) -> 4 | R26: =IF(F26="","",VALUE(LEFT(F26,FIND(" ",F26)-1))) -> 2 | S26: =IF(G26="","",VALUE(LEFT(G26,FIND(" ",G26)-1))) -> 2 | T26: =IF(H26="","",VALUE(LEFT(H26,FIND(" ",H26)-1))) -> 4 | U26: 150 | V26: =IF(L26="",0,IF(ISNUMBER(SEARCH("Bathroom",L26)),1,0)) -> 1 | W26: =IF(L26="",0,IF(ISNUMBER(SEARCH("Dining room",L26)),1,0)) -> 0 | X26: =IF(L26="",0,IF(ISNUMBER(SEARCH("Office",L26)),1,0)) -> 0 | Y26: =IF(L26="",0,IF(ISNUMBER(SEARCH("Bedroom",L26)),1,0)) -> 1 | Z26: =IF(L26="",0,IF(ISNUMBER(SEARCH("Living room",L26)),1,0)) -> 0 | AA26: =IF(M26="",0, IF(ISNUMBER(SEARCH("By yourself",M26)), 1, 0)) -> 1 | AB26: =IF(M26="", 0, IF(ISNUMBER(SEARCH("Friends", M26)), 1, 0)) -> 0 | AC26: =IF(M26="",0,IF(ISNUMBER(SEARCH("Family members", M26)), 1, 0)) -> 0 | AD26: =IF(M26="", 0, IF(ISNUMBER(SEARCH("Coworkers/Classmates", M26)), 1, 0)) -> 0 | AE26: =IF(M26="", 0, IF(ISNUMBER(SEARCH("Strangers", M26)), 1, 0)) -> 0 | AF26: =IF(N26="", 0, IF(ISNUMBER(SEARCH("Spring", N26)), 1, 0)) -> 0 | AG26: =IF(N26="", 0, IF(ISNUMBER(SEARCH("Summer", N26)), 1, 0)) -> 0 | AH26: =IF(N26="", 0, IF(ISNUMBER(SEARCH("Fall", N26)), 1, 0)) -> 1 | AI26: =IF(N26="", 0, IF(ISNUMBER(SEARCH("Winter", N26)), 1, 0)) -> 0
A27: 26 | B27: The Persistence of Memory | C27: 4 | D27: Uncanny, lonely, still, anxious | E27: 5 - Strongly agree | F27: 2 - Disagree | G27: 2 - Disagree | H27: 4 - Agree | I27: 3 | J27: 8 | K27: 100 | L27: Bathroom,Office,Living room | M27: Friends,Family members | N27: Summer,Fall | O27: Cheesecake | P27: A low, steady hum and a long, shaking whistle and the static of radio. | Q27: =IF(E27="", "", LEFT(E27, 1) * 1) -> 5 | R27: =IF(F27="","",VALUE(LEFT(F27,FIND(" ",F27)-1))) -> 2 | S27: =IF(G27="","",VALUE(LEFT(G27,FIND(" ",G27)-1))) -> 2 | T27: =IF(H27="","",VALUE(LEFT(H27,FIND(" ",H27)-1))) -> 4 | U27: 100 | V27: =IF(L27="",0,IF(ISNUMBER(SEARCH("Bathroom",L27)),1,0)) -> 1 | W27: =IF(L27="",0,IF(ISNUMBER(SEARCH("Dining room",L27)),1,0)) -> 0 | X27: =IF(L27="",0,IF(ISNUMBER(SEARCH("Office",L27)),1,0)) -> 1 | Y27: =IF(L27="",0,IF(ISNUMBER(SEARCH("Bedroom",L27)),1,0)) -> 0 | Z27: =IF(L27="",0,IF(ISNUMBER(SEARCH("Living room",L27)),1,0)) -> 1 | AA27: =IF(M27="",0, IF(ISNUMBER(SEARCH("By yourself",M27)), 1, 0)) -> 0 | AB27: =IF(M27="", 0, IF(ISNUMBER(SEARCH("Friends", M27)), 1, 0)) -> 1 | AC27: =IF(M27="",0,IF(ISNUMBER(SEARCH("Family members", M27)), 1, 0)) -> 1 | AD27: =IF(M27="", 0, IF(ISNUMBER(SEARCH("Coworkers/Classmates", M27)), 1, 0)) -> 0 | AE27: =IF(M27="", 0, IF(ISNUMBER(SEARCH("Strangers", M27)), 1, 0)) -> 0 | AF27: =IF(N27="", 0, IF(ISNUMBER(SEARCH("Spring", N27)), 1, 0)) -> 0 | AG27: =IF(N27="", 0, IF(ISNUMBER(SEARCH("Summer", N27)), 1, 0)) -> 1 | AH27: =IF(N27="", 0, IF(ISNUMBER(SEARCH("Fall", N27)), 1, 0)) -> 1 | AI27: =IF(N27="", 0, IF(ISNUMBER(SEARCH("Winter", N27)), 1, 0)) -> 0
A28: 27 | B28: The Persistence of Memory | C28: 7 | D28: Sad, uncertain, slightly disoriented. | E28: 4 - Agree | F28: 1 - Strongly disagree | G28: 2 - Disagree | H28: 5 - Strongly agree | I28: 6 | J28: 5 | K28: I don't like feeling uneasy so I wouldn't pay much, maybe $10 | L28: Bathroom,Office | M28: Friends,Family members | N28: Summer | O28: Poutine | P28: I'd imagine a very sombre soundtrack, something that would play in a movie after a very beloved character dies. | Q28: =IF(E28="", "", LEFT(E28, 1) * 1) -> 4 | R28: =IF(F28="","",VALUE(LEFT(F28,FIND(" ",F28)-1))) -> 1 | S28: =IF(G28="","",VALUE(LEFT(G28,FIND(" ",G28)-1))) -> 2 | T28: =IF(H28="","",VALUE(LEFT(H28,FIND(" ",H28)-1))) -> 5 | U28: 10 | V28: =IF(L28="",0,IF(ISNUMBER(SEARCH("Bathroom",L28)),1,0)) -> 1 | W28: =IF(L28="",0,IF(ISNUMBER(SEARCH("Dining room",L28)),1,0)) -> 0 | X28: =IF(L28="",0,IF(ISNUMBER(SEARCH("Office",L28)),1,0)) -> 1 | Y28: =IF(L28="",0,IF(ISNUMBER(SEARCH("Bedroom",L28)),1,0)) -> 0 | Z28: =IF(L28="",0,IF(ISNUMBER(SEARCH("Living room",L28)),1,0)) -> 0 | AA28: =IF(M28="",0, IF(ISNUMBER(SEARCH("By yourself",M28)), 1, 0)) -> 0 | AB28: =IF(M28="", 0, IF(ISNUMBER(SEARCH("Friends", M28)), 1, 0)) -> 1 | AC28: =IF(M28="",0,IF(ISNUMBER(SEARCH("Family members", M28)), 1, 0)) -> 1 | AD28: =IF(M28="", 0, IF(ISNUMBER(SEARCH("Coworkers/Classmates", M28)), 1, 0)) -> 0 | AE28: =IF(M28="", 0, IF(ISNUMBER(SEARCH("Strangers", M28)), 1, 0)) -> 0 | AF28: =IF(N28="", 0, IF(ISNUMBER(SEARCH("Spring", N28)), 1, 0)) -> 0 | AG28: =IF(N28="", 0, IF(ISNUMBER(SEARCH("Summer", N28)), 1, 0)) -> 1 | AH28: =IF(N28="", 0, IF(ISNUMBER(SEARCH("Fall", N28)), 1, 0)) -> 0 | AI28: =IF(N28="", 0, IF(ISNUMBER(SEARCH("Winter", N28)), 1, 0)) -> 0
A29: 28 | B29: The Persistence of Memory | C29: 6 | D29: Uneasy since time in this picture doesn't seem to be a rigid construct | E29: 4 - Agree | F29: 3 - Neutral/Unsure | G29: 2 - Disagree | H29: 4 - Agree | I29: 7 | J29: 8 | K29: 50 | L29: Office,Living room | M29: Strangers,By yourself | N29: Summer | O29: cheese sandwich¬† | P29: slow dramatic violin notes¬† | Q29: =IF(E29="", "", LEFT(E29, 1) * 1) -> 4 | R29: =IF(F29="","",VALUE(LEFT(F29,FIND(" ",F29)-1))) -> 3 | S29: =IF(G29="","",VALUE(LEFT(G29,FIND(" ",G29)-1))) -> 2 | T29: =IF(H29="","",VALUE(LEFT(H29,FIND(" ",H29)-1))) -> 4 | U29: 50 | V29: =IF(L29="",0,IF(ISNUMBER(SEARCH("Bathroom",L29)),1,0)) -> 0 | W29: =IF(L29="",0,IF(ISNUMBER(SEARCH("Dining room",L29)),1,0)) -> 0 | X29: =IF(L29="",0,IF(ISNUMBER(SEARCH("Office",L29)),1,0)) -> 1 | Y29: =IF(L29="",0,IF(ISNUMBER(SEARCH("Bedroom",L29)),1,0)) -> 0 | Z29: =IF(L29="",0,IF(ISNUMBER(SEARCH("Living room",L29)),1,0)) -> 1 | AA29: =IF(M29="",0, IF(ISNUMBER(SEARCH("By yourself",M29)), 1, 0)) -> 1 | AB29: =IF(M29="", 0, IF(ISNUMBER(SEARCH("Friends", M29)), 1, 0)) -> 0 | AC29: =IF(M29="",0,IF(ISNUMBER(SEARCH("Family members", M29)), 1, 0)) -> 0 | AD29: =IF(M29="", 0, IF(ISNUMBER(SEARCH("Coworkers/Classmates", M29)), 1, 0)) -> 0 | AE29: =IF(M29="", 0, IF(ISNUMBER(SEARCH("Strangers", M29)), 1, 0)) -> 1 | AF29: =IF(N29="", 0, IF(ISNUMBER(SEARCH("Spring", N29)), 1, 0)) -> 0 | AG29: =IF(N29="", 0, IF(ISNUMBER(SEARCH("Summer", N29)), 1, 0)) -> 1 | AH29: =IF(N29="", 0, IF(ISNUMBER(SEARCH("Fall", N29)), 1, 0)) -> 0 | AI29: =IF(N29="", 0, IF(ISNUMBER(SEARCH("Winter", N29)), 1, 0)) -> 0
A30: 29 | B30: The Persistence of Memory | C30: 8 | D30: It makes me feel sad and drowsy. | E30: 4 - Agree | F30: 2 - Disagree | G30: 3 - Neutral/Unsure | H30: 4 - Agree | I30: 5 | J30: 8 | K30: 1000 | L30: Living room | M30: Friends,By yourself | N30: Fall | O30: Mashed Potatoes. | P30: Slow jazz. | Q30: =IF(E30="", "", LEFT(E30, 1) * 1) -> 4 | R30: =IF(F30="","",VALUE(LEFT(F30,FIND(" ",F30)-1))) -> 2 | S30: =IF(G30="","",VALUE(LEFT(G30,FIND(" ",G30)-1))) -> 3 | T30: =IF(H30="","",VALUE(LEFT(H30,FIND(" ",H30)-1))) -> 4 | U30: 1000 | V30: =IF(L30="",0,IF(ISNUMBER(SEARCH("Bathroom",L30)),1,0)) -> 0 | W30: =IF(L30="",0,IF(ISNUMBER(SEARCH("Dining room",L30)),1,0)) -> 0 | X30: =IF(L30="",0,IF(ISNUMBER(SEARCH("Office",L30)),1,0)) -> 0 | Y30: =IF(L30="",0,IF(ISNUMBER(SEARCH("Bedroom",L30)),1,0)) -> 0 | Z30: =IF(L30="",0,IF(ISNUMBER(SEARCH("Living room",L30)),1,0)) -> 1 | AA30: =IF(M30="",0, IF(ISNUMBER(SEARCH("By yourself",M30)), 1, 0)) -> 1 | AB30: =IF(M30="", 0, IF(ISNUMBER(SEARCH("Friends", M30)), 1, 0)) -> 1 | AC30: =IF(M30="",0,IF(ISNUMBER(SEARCH("Family members", M30)), 1, 0)) -> 0 | AD30: =IF(M30="", 0, IF(ISNUMBER(SEARCH("Coworkers/Classmates", M30)), 1, 0)) -> 0 | AE30: =IF(M30="", 0, IF(ISNUMBER(SEARCH("Strangers", M30)), 1, 0)) -> 0 | AF30: =IF(N30="", 0, IF(ISNUMBER(SEARCH("Spring", N30)), 1, 0)) -> 0 | AG30: =IF(N30="", 0, IF(ISNUMBER(SEARCH("Summer", N30)), 1, 0)) -> 0 | AH30: =IF(N30="", 0, IF(ISNUMBER(SEARCH("Fall", N30)), 1, 0)) -> 1 | AI30: =IF(N30="", 0, IF(ISNUMBER(SEARCH("Winter", N30)), 1, 0)) -> 0
A31: 30 | B31: The Persistence of Memory | C31: 10 | D31: This painting makes me feel sad and feel like I am running out of time | E31: 5 - Strongly agree | F31: 1 - Strongly disagree | G31: 1 - Strongly disagree | H31: 5 - Strongly agree | I31: 2 | J31: 3 | K31: 300 | L31: Dining room | M31: By yourself | N31: Fall | O31: Soup | P31: Slow and sad music played by a violine of a cello. Burns the Heart | Q31: =IF(E31="", "", LEFT(E31, 1) * 1) -> 5 | R31: =IF(F31="","",VALUE(LEFT(F31,FIND(" ",F31)-1))) -> 1 | S31: =IF(G31="","",VALUE(LEFT(G31,FIND(" ",G31)-1))) -> 1 | T31: =IF(H31="","",VALUE(LEFT(H31,FIND(" ",H31)-1))) -> 5 | U31: 300 | V31: =IF(L31="",0,IF(ISNUMBER(SEARCH("Bathroom",L31)),1,0)) -> 0 | W31: =IF(L31="",0,IF(ISNUMBER(SEARCH("Dining room",L31)),1,0)) -> 1 | X31: =IF(L31="",0,IF(ISNUMBER(SEARCH("Office",L31)),1,0)) -> 0 | Y31: =IF(L31="",0,IF(ISNUMBER(SEARCH("Bedroom",L31)),1,0)) -> 0 | Z31: =IF(L31="",0,IF(ISNUMBER(SEARCH("Living room",L31)),1,0)) -> 0 | AA31: =IF(M31="",0, IF(ISNUMBER(SEARCH("By yourself",M31)), 1, 0)) -> 1 | AB31: =IF(M31="", 0, IF(ISNUMBER(SEARCH("Friends", M31)), 1, 0)) -> 0 | AC31: =IF(M31="",0,IF(ISNUMBER(SEARCH("Family members", M31)), 1, 0)) -> 0 | AD31: =IF(M31="", 0, IF(ISNUMBER(SEARCH("Coworkers/Classmates", M31)), 1, 0)) -> 0 | AE31: =IF(M31="", 0, IF(ISNUMBER(SEARCH("Strangers", M31)), 1, 0)) -> 0 | AF31: =IF(N31="", 0, IF(ISNUMBER(SEARCH("Spring", N31)), 1, 0)) -> 0 | AG31: =IF(N31="", 0, IF(ISNUMBER(SEARCH("Summer", N31)), 1, 0)) -> 0 | AH31: =IF(N31="", 0, IF(ISNUMBER(SEARCH("Fall", N31)), 1, 0)) -> 1 | AI31: =IF(N31="", 0, IF(ISNUMBER(SEARCH("Winter", N31)), 1, 0)) -> 0
A32: 31 | B32: The Persistence of Memory | C32: 5 | D32: Old, lonely¬† | E32: 3 - Neutral/Unsure | F32: 2 - Disagree | G32: 3 - Neutral/Unsure | H32: 4 - Agree | I32: 5 | J32: 3 | K32: 1 | L32: Bathroom | M32: Strangers,By yourself | N32: Fall | O32: Bread | P32: Slow music | Q32: =IF(E32="", "", LEFT(E32, 1) * 1) -> 3 | R32: =IF(F32="","",VALUE(LEFT(F32,FIND(" ",F32)-1))) -> 2 | S32: =IF(G32="","",VALUE(LEFT(G32,FIND(" ",G32)-1))) -> 3 | T32: =IF(H32="","",VALUE(LEFT(H32,FIND(" ",H32)-1))) -> 4 | U32: 1 | V32: =IF(L32="",0,IF(ISNUMBER(SEARCH("Bathroom",L32)),1,0)) -> 1 | W32: =IF(L32="",0,IF(ISNUMBER(SEARCH("Dining room",L32)),1,0)) -> 0 | X32: =IF(L32="",0,IF(ISNUMBER(SEARCH("Office",L32)),1,0)) -> 0 | Y32: =IF(L32="",0,IF(ISNUMBER(SEARCH("Bedroom",L32)),1,0)) -> 0 | Z32: =IF(L32="",0,IF(ISNUMBER(SEARCH("Living room",L32)),1,0)) -> 0 | AA32: =IF(M32="",0, IF(ISNUMBER(SEARCH("By yourself",M32)), 1, 0)) -> 1 | AB32: =IF(M32="", 0, IF(ISNUMBER(SEARCH("Friends", M32)), 1, 0)) -> 0 | AC32: =IF(M32="",0,IF(ISNUMBER(SEARCH("Family members", M32)), 1, 0)) -> 0 | AD32: =IF(M32="", 0, IF(ISNUMBER(SEARCH("Coworkers/Classmates", M32)), 1, 0)) -> 0 | AE32: =IF(M32="", 0, IF(ISNUMBER(SEARCH("Strangers", M32)), 1, 0)) -> 1 | AF32: =IF(N32="", 0, IF(ISNUMBER(SEARCH("Spring", N32)), 1, 0)) -> 0 | AG32: =IF(N32="", 0, IF(ISNUMBER(SEARCH("Summer", N32)), 1, 0)) -> 0 | AH32: =IF(N32="", 0, IF(ISNUMBER(SEARCH("Fall", N32)), 1, 0)) -> 1 | AI32: =IF(N32="", 0, IF(ISNUMBER(SEARCH("Winter", N32)), 1, 0)) -> 0
A33: 32 | B33: The Persistence of Memory | C33: 4 | D33: This painting makes me feel cognizant of the connection between and relativity of space and time. | E33: 4 - Agree | F33: 2 - Disagree | G33: 2 - Disagree | H33: 4 - Agree | I33: 5 | J33: 9 | K33: 20 | L33: Office | M33: By yourself | N33: Summer | O33: Bitter melon | P33: The soundtrack would be slow, contemplative, maybe even a little experimental at times. | Q33: =IF(E33="", "", LEFT(E33, 1) * 1) -> 4 | R33: =IF(F33="","",VALUE(LEFT(F33,FIND(" ",F33)-1))) -> 2 | S33: =IF(G33="","",VALUE(LEFT(G33,FIND(" ",G33)-1))) -> 2 | T33: =IF(H33="","",VALUE(LEFT(H33,FIND(" ",H33)-1))) -> 4 | U33: 20 | V33: =IF(L33="",0,IF(ISNUMBER(SEARCH("Bathroom",L33)),1,0)) -> 0 | W33: =IF(L33="",0,IF(ISNUMBER(SEARCH("Dining room",L33)),1,0)) -> 0 | X33: =IF(L33="",0,IF(ISNUMBER(SEARCH("Office",L33)),1,0)) -> 1 | Y33: =IF(L33="",0,IF(ISNUMBER(SEARCH("Bedroom",L33)),1,0)) -> 0 | Z33: =IF(L33="",0,IF(ISNUMBER(SEARCH("Living room",L33)),1,0)) -> 0 | AA33: =IF(M33="",0, IF(ISNUMBER(SEARCH("By yourself",M33)), 1, 0)) -> 1 | AB33: =IF(M33="", 0, IF(ISNUMBER(SEARCH("Friends", M33)), 1, 0)) -> 0 | AC33: =IF(M33="",0,IF(ISNUMBER(SEARCH("Family members", M33)), 1, 0)) -> 0 | AD33: =IF(M33="", 0, IF(ISNUMBER(SEARCH("Coworkers/Classmates", M33)), 1, 0)) -> 0 | AE33: =IF(M33="", 0, IF(ISNUMBER(SEARCH("Strangers", M33)), 1, 0)) -> 0 | AF33: =IF(N33="", 0, IF(ISNUMBER(SEARCH("Spring", N33)), 1, 0)) -> 0 | AG33: =IF(N33="", 0, IF(ISNUMBER(SEARCH("Summer", N33)), 1, 0)) -> 1 | AH33: =IF(N33="", 0, IF(ISNUMBER(SEARCH("Fall", N33)), 1, 0)) -> 0 | AI33: =IF(N33="", 0, IF(ISNUMBER(SEARCH("Winter", N33)), 1, 0)) -> 0
A34: 33 | B34: The Persistence of Memory | C34: 8 | D34: The painting makes me feel a sense of longing, almost as if time is passing as symbolized by the clocks melting. Accompanied by this, it also makes me feel a sense of urgency since I recognize that time is passing so I feel like I should be doing more with my time!¬† | E34: 5 - Strongly agree | F34: 2 - Disagree | G34: 2 - Disagree | H34: 3 - Neutral/Unsure | I34: 3 | J34: 4 | K34: 50 | L34: Office | M34: Friends,Strangers,By yourself | N34: Fall,Winter | O34: Pizza | P34: Slow brass instruments, trumpets, playing in minor key, lower register notes.¬† | Q34: =IF(E34="", "", LEFT(E34, 1) * 1) -> 5 | R34: =IF(F34="","",VALUE(LEFT(F34,FIND(" ",F34)-1))) -> 2 | S34: =IF(G34="","",VALUE(LEFT(G34,FIND(" ",G34)-1))) -> 2 | T34: =IF(H34="","",VALUE(LEFT(H34,FIND(" ",H34)-1))) -> 3 | U34: 50 | V34: =IF(L34="",0,IF(ISNUMBER(SEARCH("Bathroom",L34)),1,0)) -> 0 | W34: =IF(L34="",0,IF(ISNUMBER(SEARCH("Dining room",L34)),1,0)) -> 0 | X34: =IF(L34="",0,IF(ISNUMBER(SEARCH("Office",L34)),1,0)) -> 1 | Y34: =IF(L34="",0,IF(ISNUMBER(SEARCH("Bedroom",L34)),1,0)) -> 0 | Z34: =IF(L34="",0,IF(ISNUMBER(SEARCH("Living room",L34)),1,0)) -> 0 | AA34: =IF(M34="",0, IF(ISNUMBER(SEARCH("By yourself",M34)), 1, 0)) -> 1 | AB34: =IF(M34="", 0, IF(ISNUMBER(SEARCH("Friends", M34)), 1, 0)) -> 1 | AC34: =IF(M34="",0,IF(ISNUMBER(SEARCH("Family members", M34)), 1, 0)) -> 0 | AD34: =IF(M34="", 0, IF(ISNUMBER(SEARCH("Coworkers/Classmates", M34)), 1, 0)) -> 0 | AE34: =IF(M34="", 0, IF(ISNUMBER(SEARCH("Strangers", M34)), 1, 0)) -> 1 | AF34: =IF(N34="", 0, IF(ISNUMBER(SEARCH("Spring", N34)), 1, 0)) -> 0 | AG34: =IF(N34="", 0, IF(ISNUMBER(SEARCH("Summer", N34)), 1, 0)) -> 0 | AH34: =IF(N34="", 0, IF(ISNUMBER(SEARCH("Fall", N34)), 1, 0)) -> 1 | AI34: =IF(N34="", 0, IF(ISNUMBER(SEARCH("Winter", N34)), 1, 0)) -> 1
A35: 34 | B35: The Persistence of Memory | C35: 7 | D35: It makes me feel slightly uneasy but also calm at the same time. The scene feels quiet and almost frozen, like everything is happening very slowly or outside of normal time. | E35: 3 - Neutral/Unsure | F35: 1 - Strongly disagree | G35: 4 - Agree | H35: 4 - Agree | I35: 5 | J35: 5 | K35: 500 | L35: Office | M35: By yourself | N35: Winter | O35: I can't imagine it as a food. | P35: The soundtrack would be very slow and minimal, with long stretches of silence between soft, drawn-out sounds. | Q35: =IF(E35="", "", LEFT(E35, 1) * 1) -> 3 | R35: =IF(F35="","",VALUE(LEFT(F35,FIND(" ",F35)-1))) -> 1 | S35: =IF(G35="","",VALUE(LEFT(G35,FIND(" ",G35)-1))) -> 4 | T35: =IF(H35="","",VALUE(LEFT(H35,FIND(" ",H35)-1))) -> 4 | U35: 500 | V35: =IF(L35="",0,IF(ISNUMBER(SEARCH("Bathroom",L35)),1,0)) -> 0 | W35: =IF(L35="",0,IF(ISNUMBER(SEARCH("Dining room",L35)),1,0)) -> 0 | X35: =IF(L35="",0,IF(ISNUMBER(SEARCH("Office",L35)),1,0)) -> 1 | Y35: =IF(L35="",0,IF(ISNUMBER(SEARCH("Bedroom",L35)),1,0)) -> 0 | Z35: =IF(L35="",0,IF(ISNUMBER(SEARCH("Living room",L35)),1,0)) -> 0 | AA35: =IF(M35="",0, IF(ISNUMBER(SEARCH("By yourself",M35)), 1, 0)) -> 1 | AB35: =IF(M35="", 0, IF(ISNUMBER(SEARCH("Friends", M35)), 1, 0)) -> 0 | AC35: =IF(M35="",0,IF(ISNUMBER(SEARCH("Family members", M35)), 1, 0)) -> 0 | AD35: =IF(M35="", 0, IF(ISNUMBER(SEARCH("Coworkers/Classmates", M35)), 1, 0)) -> 0 | AE35: =IF(M35="", 0, IF(ISNUMBER(SEARCH("Strangers", M35)), 1, 0)) -> 0 | AF35: =IF(N35="", 0, IF(ISNUMBER(SEARCH("Spring", N35)), 1, 0)) -> 0 | AG35: =IF(N35="", 0, IF(ISNUMBER(SEARCH("Summer", N35)), 1, 0)) -> 0 | AH35: =IF(N35="", 0, IF(ISNUMBER(SEARCH("Fall", N35)), 1, 0)) -> 0 | AI35: =IF(N35="", 0, IF(ISNUMBER(SEARCH("Winter", N35)), 1, 0)) -> 1
A36: 35 | B36: The Persistence of Memory | C36: 1 | D36: Strange, repressed | E36: 5 - Strongly agree | F36: 1 - Strongly disagree | G36: 3 - Neutral/Unsure | H36: 4 - Agree | I36: 3 | J36: 5 | K36: 3.14 | L36: Office | M36: Family members,By yourself | N36: Fall | O36: expired but unmelted ice cream | P36: The sound produced by the continuous vibration of metal | Q36: =IF(E36="", "", LEFT(E36, 1) * 1) -> 5 | R36: =IF(F36="","",VALUE(LEFT(F36,FIND(" ",F36)-1))) -> 1 | S36: =IF(G36="","",VALUE(LEFT(G36,FIND(" ",G36)-1))) -> 3 | T36: =IF(H36="","",VALUE(LEFT(H36,FIND(" ",H36)-1))) -> 4 | U36: 3.14 | V36: =IF(L36="",0,IF(ISNUMBER(SEARCH("Bathroom",L36)),1,0)) -> 0 | W36: =IF(L36="",0,IF(ISNUMBER(SEARCH("Dining room",L36)),1,0)) -> 0 | X36: =IF(L36="",0,IF(ISNUMBER(SEARCH("Office",L36)),1,0)) -> 1 | Y36: =IF(L36="",0,IF(ISNUMBER(SEARCH("Bedroom",L36)),1,0)) -> 0 | Z36: =IF(L36="",0,IF(ISNUMBER(SEARCH("Living room",L36)),1,0)) -> 0 | AA36: =IF(M36="",0, IF(ISNUMBER(SEARCH("By yourself",M36)), 1, 0)) -> 1 | AB36: =IF(M36="", 0, IF(ISNUMBER(SEARCH("Friends", M36)), 1, 0)) -> 0 | AC36: =IF(M36="",0,IF(ISNUMBER(SEARCH("Family members", M36)), 1, 0)) -> 1 | AD36: =IF(M36="", 0, IF(ISNUMBER(SEARCH("Coworkers/Classmates", M36)), 1, 0)) -> 0 | AE36: =IF(M36="", 0, IF(ISNUMBER(SEARCH("Strangers", M36)), 1, 0)) -> 0 | AF36: =IF(N36="", 0, IF(ISNUMBER(SEARCH("Spring", N36)), 1, 0)) -> 0 | AG36: =IF(N36="", 0, IF(ISNUMBER(SEARCH("Summer", N36)), 1, 0)) -> 0 | AH36: =IF(N36="", 0, IF(ISNUMBER(SEARCH("Fall", N36)), 1, 0)) -> 1 | AI36: =IF(N36="", 0, IF(ISNUMBER(SEARCH("Winter", N36)), 1, 0)) -> 0
A37: 36 | B37: The Persistence of Memory | C37: 7 | D37: This picture gives me a sense of desparation, a feeling of sunset. | E37: 5 - Strongly agree | F37: 2 - Disagree | G37: 3 - Neutral/Unsure | H37: 4 - Agree | I37: 4 | J37: 4 | K37: 888 | L37: Office | M37: By yourself | N37: Fall | O37: It would be an icecream. | P37: The soundtrack would be rushed piano in the beginning, slows down gradually with tickling sound, then goes to very slow and sad string ensemble. | Q37: =IF(E37="", "", LEFT(E37, 1) * 1) -> 5 | R37: =IF(F37="","",VALUE(LEFT(F37,FIND(" ",F37)-1))) -> 2 | S37: =IF(G37="","",VALUE(LEFT(G37,FIND(" ",G37)-1))) -> 3 | T37: =IF(H37="","",VALUE(LEFT(H37,FIND(" ",H37)-1))) -> 4 | U37: 888 | V37: =IF(L37="",0,IF(ISNUMBER(SEARCH("Bathroom",L37)),1,0)) -> 0 | W37: =IF(L37="",0,IF(ISNUMBER(SEARCH("Dining room",L37)),1,0)) -> 0 | X37: =IF(L37="",0,IF(ISNUMBER(SEARCH("Office",L37)),1,0)) -> 1 | Y37: =IF(L37="",0,IF(ISNUMBER(SEARCH("Bedroom",L37)),1,0)) -> 0 | Z37: =IF(L37="",0,IF(ISNUMBER(SEARCH("Living room",L37)),1,0)) -> 0 | AA37: =IF(M37="",0, IF(ISNUMBER(SEARCH("By yourself",M37)), 1, 0)) -> 1 | AB37: =IF(M37="", 0, IF(ISNUMBER(SEARCH("Friends", M37)), 1, 0)) -> 0 | AC37: =IF(M37="",0,IF(ISNUMBER(SEARCH("Family members", M37)), 1, 0)) -> 0 | AD37: =IF(M37="", 0, IF(ISNUMBER(SEARCH("Coworkers/Classmates", M37)), 1, 0)) -> 0 | AE37: =IF(M37="", 0, IF(ISNUMBER(SEARCH("Strangers", M37)), 1, 0)) -> 0 | AF37: =IF(N37="", 0, IF(ISNUMBER(SEARCH("Spring", N37)), 1, 0)) -> 0 | AG37: =IF(N37="", 0, IF(ISNUMBER(SEARCH("Summer", N37)), 1, 0)) -> 0 | AH37: =IF(N37="", 0, IF(ISNUMBER(SEARCH("Fall", N37)), 1, 0)) -> 1 | AI37: =IF(N37="", 0, IF(ISNUMBER(SEARCH("Winter", N37)), 1, 0)) -> 0
A38: 37 | B38: The Persistence of Memory | C38: 8 | D38: Time is not very important when in the middle of nature. | E38: 4 - Agree | F38: 2 - Disagree | G38: 5 - Strongly agree | H38: 4 - Agree | I38: 5 | J38: 2 | K38: 20 | L38: Office | M38: Friends,Family members,Coworkers/Classmates,By yourself | N38: Summer | O38: Lobster | P38: melancholic | Q38: =IF(E38="", "", LEFT(E38, 1) * 1) -> 4 | R38: =IF(F38="","",VALUE(LEFT(F38,FIND(" ",F38)-1))) -> 2 | S38: =IF(G38="","",VALUE(LEFT(G38,FIND(" ",G38)-1))) -> 5 | T38: =IF(H38="","",VALUE(LEFT(H38,FIND(" ",H38)-1))) -> 4 | U38: 20 | V38: =IF(L38="",0,IF(ISNUMBER(SEARCH("Bathroom",L38)),1,0)) -> 0 | W38: =IF(L38="",0,IF(ISNUMBER(SEARCH("Dining room",L38)),1,0)) -> 0 | X38: =IF(L38="",0,IF(ISNUMBER(SEARCH("Office",L38)),1,0)) -> 1 | Y38: =IF(L38="",0,IF(ISNUMBER(SEARCH("Bedroom",L38)),1,0)) -> 0 | Z38: =IF(L38="",0,IF(ISNUMBER(SEARCH("Living room",L38)),1,0)) -> 0 | AA38: =IF(M38="",0, IF(ISNUMBER(SEARCH("By yourself",M38)), 1, 0)) -> 1 | AB38: =IF(M38="", 0, IF(ISNUMBER(SEARCH("Friends", M38)), 1, 0)) -> 1 | AC38: =IF(M38="",0,IF(ISNUMBER(SEARCH("Family members", M38)), 1, 0)) -> 1 | AD38: =IF(M38="", 0, IF(ISNUMBER(SEARCH("Coworkers/Classmates", M38)), 1, 0)) -> 1 | AE38: =IF(M38="", 0, IF(ISNUMBER(SEARCH("Strangers", M38)), 1, 0)) -> 0 | AF38: =IF(N38="", 0, IF(ISNUMBER(SEARCH("Spring", N38)), 1, 0)) -> 0 | AG38: =IF(N38="", 0, IF(ISNUMBER(SEARCH("Summer", N38)), 1, 0)) -> 1 | AH38: =IF(N38="", 0, IF(ISNUMBER(SEARCH("Fall", N38)), 1, 0)) -> 0 | AI38: =IF(N38="", 0, IF(ISNUMBER(SEARCH("Winter", N38)), 1, 0)) -> 0
A39: 38 | B39: The Persistence of Memory | C39: 8 | D39: Makes me feel like I am running out of time | E39: 4 - Agree | F39: 2 - Disagree | G39: 1 - Strongly disagree | H39: 5 - Strongly agree | I39: 6 | J39: 4 | K39: 1000 | L39: Bathroom | M39: Friends,Family members | N39: Fall | O39: Turkey with gravy | P39: slow Mozart song | Q39: =IF(E39="", "", LEFT(E39, 1) * 1) -> 4 | R39: =IF(F39="","",VALUE(LEFT(F39,FIND(" ",F39)-1))) -> 2 | S39: =IF(G39="","",VALUE(LEFT(G39,FIND(" ",G39)-1))) -> 1 | T39: =IF(H39="","",VALUE(LEFT(H39,FIND(" ",H39)-1))) -> 5 | U39: 1000 | V39: =IF(L39="",0,IF(ISNUMBER(SEARCH("Bathroom",L39)),1,0)) -> 1 | W39: =IF(L39="",0,IF(ISNUMBER(SEARCH("Dining room",L39)),1,0)) -> 0 | X39: =IF(L39="",0,IF(ISNUMBER(SEARCH("Office",L39)),1,0)) -> 0 | Y39: =IF(L39="",0,IF(ISNUMBER(SEARCH("Bedroom",L39)),1,0)) -> 0 | Z39: =IF(L39="",0,IF(ISNUMBER(SEARCH("Living room",L39)),1,0)) -> 0 | AA39: =IF(M39="",0, IF(ISNUMBER(SEARCH("By yourself",M39)), 1, 0)) -> 0 | AB39: =IF(M39="", 0, IF(ISNUMBER(SEARCH("Friends", M39)), 1, 0)) -> 1 | AC39: =IF(M39="",0,IF(ISNUMBER(SEARCH("Family members", M39)), 1, 0)) -> 1 | AD39: =IF(M39="", 0, IF(ISNUMBER(SEARCH("Coworkers/Classmates", M39)), 1, 0)) -> 0 | AE39: =IF(M39="", 0, IF(ISNUMBER(SEARCH("Strangers", M39)), 1, 0)) -> 0 | AF39: =IF(N39="", 0, IF(ISNUMBER(SEARCH("Spring", N39)), 1, 0)) -> 0 | AG39: =IF(N39="", 0, IF(ISNUMBER(SEARCH("Summer", N39)), 1, 0)) -> 0 | AH39: =IF(N39="", 0, IF(ISNUMBER(SEARCH("Fall", N39)), 1, 0)) -> 1 | AI39: =IF(N39="", 0, IF(ISNUMBER(SEARCH("Winter", N39)), 1, 0)) -> 0
A40: 39 | B40: The Persistence of Memory | C40: 7 | D40: I feel anxious, worried about time, endless and a little bit peaceful. | E40: 5 - Strongly agree | F40: 2 - Disagree | G40: 2 - Disagree | H40: 5 - Strongly agree | I40: 3 | J40: 5 | K40: 500 | L40: Dining room | M40: By yourself | N40: Fall,Winter | O40: Sandwich. | P40: A soothing combination of ocean waves and delicate piano. | Q40: =IF(E40="", "", LEFT(E40, 1) * 1) -> 5 | R40: =IF(F40="","",VALUE(LEFT(F40,FIND(" ",F40)-1))) -> 2 | S40: =IF(G40="","",VALUE(LEFT(G40,FIND(" ",G40)-1))) -> 2 | T40: =IF(H40="","",VALUE(LEFT(H40,FIND(" ",H40)-1))) -> 5 | U40: 500 | V40: =IF(L40="",0,IF(ISNUMBER(SEARCH("Bathroom",L40)),1,0)) -> 0 | W40: =IF(L40="",0,IF(ISNUMBER(SEARCH("Dining room",L40)),1,0)) -> 1 | X40: =IF(L40="",0,IF(ISNUMBER(SEARCH("Office",L40)),1,0)) -> 0 | Y40: =IF(L40="",0,IF(ISNUMBER(SEARCH("Bedroom",L40)),1,0)) -> 0 | Z40: =IF(L40="",0,IF(ISNUMBER(SEARCH("Living room",L40)),1,0)) -> 0 | AA40: =IF(M40="",0, IF(ISNUMBER(SEARCH("By yourself",M40)), 1, 0)) -> 1 | AB40: =IF(M40="", 0, IF(ISNUMBER(SEARCH("Friends", M40)), 1, 0)) -> 0 | AC40: =IF(M40="",0,IF(ISNUMBER(SEARCH("Family members", M40)), 1, 0)) -> 0 | AD40: =IF(M40="", 0, IF(ISNUMBER(SEARCH("Coworkers/Classmates", M40)), 1, 0)) -> 0 | AE40: =IF(M40="", 0, IF(ISNUMBER(SEARCH("Strangers", M40)), 1, 0)) -> 0 | AF40: =IF(N40="", 0, IF(ISNUMBER(SEARCH("Spring", N40)), 1, 0)) -> 0 | AG40: =IF(N40="", 0, IF(ISNUMBER(SEARCH("Summer", N40)), 1, 0)) -> 0 | AH40: =IF(N40="", 0, IF(ISNUMBER(SEARCH("Fall", N40)), 1, 0)) -> 1 | AI40: =IF(N40="", 0, IF(ISNUMBER(SEARCH("Winter", N40)), 1, 0)) -> 1
... A45: 44 | B45: The Persistence of Memory | C45: 8 | D45: It makes me feel anxious, uneasy, lonely, and tired. | E45: 3 - Neutral/Unsure | F45: 1 - Strongly disagree | G45: 2 - Disagree | H45: 5 - Strongly agree | I45: 4 | J45: 5 | K45: 50 | L45: Bedroom | M45: Family members,By yourself | N45: Summer | O45: toast | P45: Slow, quiet, soft, low, and foggy. | Q45: =IF(E45="", "", LEFT(E45, 1) * 1) -> 3 | R45: =IF(F45="","",VALUE(LEFT(F45,FIND(" ",F45)-1))) -> 1 | S45: =IF(G45="","",VALUE(LEFT(G45,FIND(" ",G45)-1))) -> 2 | T45: =IF(H45="","",VALUE(LEFT(H45,FIND(" ",H45)-1))) -> 5 | U45: 50 | V45: =IF(L45="",0,IF(ISNUMBER(SEARCH("Bathroom",L45)),1,0)) -> 0 | W45: =IF(L45="",0,IF(ISNUMBER(SEARCH("Dining room",L45)),1,0)) -> 0 | X45: =IF(L45="",0,IF(ISNUMBER(SEARCH("Office",L45)),1,0)) -> 0 | Y45: =IF(L45="",0,IF(ISNUMBER(SEARCH("Bedroom",L45)),1,0)) -> 1 | Z45: =IF(L45="",0,IF(ISNUMBER(SEARCH("Living room",L45)),1,0)) -> 0 | AA45: =IF(M45="",0, IF(ISNUMBER(SEARCH("By yourself",M45)), 1, 0)) -> 1 | AB45: =IF(M45="", 0, IF(ISNUMBER(SEARCH("Friends", M45)), 1, 0)) -> 0 | AC45: =IF(M45="",0,IF(ISNUMBER(SEARCH("Family members", M45)), 1, 0)) -> 1 | AD45: =IF(M45="", 0, IF(ISNUMBER(SEARCH("Coworkers/Classmates", M45)), 1, 0)) -> 0 | AE45: =IF(M45="", 0, IF(ISNUMBER(SEARCH("Strangers", M45)), 1, 0)) -> 0 | AF45: =IF(N45="", 0, IF(ISNUMBER(SEARCH("Spring", N45)), 1, 0)) -> 0 | AG45: =IF(N45="", 0, IF(ISNUMBER(SEARCH("Summer", N45)), 1, 0)) -> 1 | AH45: =IF(N45="", 0, IF(ISNUMBER(SEARCH("Fall", N45)), 1, 0)) -> 0 | AI45: =IF(N45="", 0, IF(ISNUMBER(SEARCH("Winter", N45)), 1, 0)) -> 0
A46: 45 | B46: The Persistence of Memory | C46: 7 | E46: 3 - Neutral/Unsure | F46: 4 - Agree | G46: 2 - Disagree | H46: 4 - Agree | I46: 5 | J46: 7 | K46: 20 | L46: Office | M46: Coworkers/Classmates | N46: Fall | O46: icecream | P46: Sci-fi movie themed song | Q46: =IF(E46="", "", LEFT(E46, 1) * 1) -> 3 | R46: =IF(F46="","",VALUE(LEFT(F46,FIND(" ",F46)-1))) -> 4 | S46: =IF(G46="","",VALUE(LEFT(G46,FIND(" ",G46)-1))) -> 2 | T46: =IF(H46="","",VALUE(LEFT(H46,FIND(" ",H46)-1))) -> 4 | U46: 20 | V46: =IF(L46="",0,IF(ISNUMBER(SEARCH("Bathroom",L46)),1,0)) -> 0 | W46: =IF(L46="",0,IF(ISNUMBER(SEARCH("Dining room",L46)),1,0)) -> 0 | X46: =IF(L46="",0,IF(ISNUMBER(SEARCH("Office",L46)),1,0)) -> 1 | Y46: =IF(L46="",0,IF(ISNUMBER(SEARCH("Bedroom",L46)),1,0)) -> 0 | Z46: =IF(L46="",0,IF(ISNUMBER(SEARCH("Living room",L46)),1,0)) -> 0 | AA46: =IF(M46="",0, IF(ISNUMBER(SEARCH("By yourself",M46)), 1, 0)) -> 0 | AB46: =IF(M46="", 0, IF(ISNUMBER(SEARCH("Friends", M46)), 1, 0)) -> 0 | AC46: =IF(M46="",0,IF(ISNUMBER(SEARCH("Family members", M46)), 1, 0)) -> 0 | AD46: =IF(M46="", 0, IF(ISNUMBER(SEARCH("Coworkers/Classmates", M46)), 1, 0)) -> 1 | AE46: =IF(M46="", 0, IF(ISNUMBER(SEARCH("Strangers", M46)), 1, 0)) -> 0 | AF46: =IF(N46="", 0, IF(ISNUMBER(SEARCH("Spring", N46)), 1, 0)) -> 0 | AG46: =IF(N46="", 0, IF(ISNUMBER(SEARCH("Summer", N46)), 1, 0)) -> 0 | AH46: =IF(N46="", 0, IF(ISNUMBER(SEARCH("Fall", N46)), 1, 0)) -> 1 | AI46: =IF(N46="", 0, IF(ISNUMBER(SEARCH("Winter", N46)), 1, 0)) -> 0
A47: 46 | B47: The Persistence of Memory | C47: 6 | D47: nostalgic and melancholic | E47: 4 - Agree | F47: 3 - Neutral/Unsure | G47: 4 - Agree | H47: 4 - Agree | I47: 5 | J47: 7 | K47: 0 | L47: Office | M47: By yourself | N47: Summer,Fall | O47: ombre cake | P47: The fading of summer | Q47: =IF(E47="", "", LEFT(E47, 1) * 1) -> 4 | R47: =IF(F47="","",VALUE(LEFT(F47,FIND(" ",F47)-1))) -> 3 | S47: =IF(G47="","",VALUE(LEFT(G47,FIND(" ",G47)-1))) -> 4 | T47: =IF(H47="","",VALUE(LEFT(H47,FIND(" ",H47)-1))) -> 4 | U47: 0 | V47: =IF(L47="",0,IF(ISNUMBER(SEARCH("Bathroom",L47)),1,0)) -> 0 | W47: =IF(L47="",0,IF(ISNUMBER(SEARCH("Dining room",L47)),1,0)) -> 0 | X47: =IF(L47="",0,IF(ISNUMBER(SEARCH("Office",L47)),1,0)) -> 1 | Y47: =IF(L47="",0,IF(ISNUMBER(SEARCH("Bedroom",L47)),1,0)) -> 0 | Z47: =IF(L47="",0,IF(ISNUMBER(SEARCH("Living room",L47)),1,0)) -> 0 | AA47: =IF(M47="",0, IF(ISNUMBER(SEARCH("By yourself",M47)), 1, 0)) -> 1 | AB47: =IF(M47="", 0, IF(ISNUMBER(SEARCH("Friends", M47)), 1, 0)) -> 0 | AC47: =IF(M47="",0,IF(ISNUMBER(SEARCH("Family members", M47)), 1, 0)) -> 0 | AD47: =IF(M47="", 0, IF(ISNUMBER(SEARCH("Coworkers/Classmates", M47)), 1, 0)) -> 0 | AE47: =IF(M47="", 0, IF(ISNUMBER(SEARCH("Strangers", M47)), 1, 0)) -> 0 | AF47: =IF(N47="", 0, IF(ISNUMBER(SEARCH("Spring", N47)), 1, 0)) -> 0 | AG47: =IF(N47="", 0, IF(ISNUMBER(SEARCH("Summer", N47)), 1, 0)) -> 1 | AH47: =IF(N47="", 0, IF(ISNUMBER(SEARCH("Fall", N47)), 1, 0)) -> 1 | AI47: =IF(N47="", 0, IF(ISNUMBER(SEARCH("Winter", N47)), 1, 0)) -> 0
A48: 47 | B48: The Persistence of Memory | C48: 7 | D48: Calm, introspective, somewhat dark | E48: 3 - Neutral/Unsure | F48: 1 - Strongly disagree | G48: 2 - Disagree | H48: 3 - Neutral/Unsure | I48: 7 | J48: 5 | K48: 25 | L48: Living room | M48: Friends,Family members | N48: Fall | O48: Cookie | P48: A breeze and leaves gently blowing, with a gentle, constant, and rhythmic hum in the background | Q48: =IF(E48="", "", LEFT(E48, 1) * 1) -> 3 | R48: =IF(F48="","",VALUE(LEFT(F48,FIND(" ",F48)-1))) -> 1 | S48: =IF(G48="","",VALUE(LEFT(G48,FIND(" ",G48)-1))) -> 2 | T48: =IF(H48="","",VALUE(LEFT(H48,FIND(" ",H48)-1))) -> 3 | U48: 25 | V48: =IF(L48="",0,IF(ISNUMBER(SEARCH("Bathroom",L48)),1,0)) -> 0 | W48: =IF(L48="",0,IF(ISNUMBER(SEARCH("Dining room",L48)),1,0)) -> 0 | X48: =IF(L48="",0,IF(ISNUMBER(SEARCH("Office",L48)),1,0)) -> 0 | Y48: =IF(L48="",0,IF(ISNUMBER(SEARCH("Bedroom",L48)),1,0)) -> 0 | Z48: =IF(L48="",0,IF(ISNUMBER(SEARCH("Living room",L48)),1,0)) -> 1 | AA48: =IF(M48="",0, IF(ISNUMBER(SEARCH("By yourself",M48)), 1, 0)) -> 0 | AB48: =IF(M48="", 0, IF(ISNUMBER(SEARCH("Friends", M48)), 1, 0)) -> 1 | AC48: =IF(M48="",0,IF(ISNUMBER(SEARCH("Family members", M48)), 1, 0)) -> 1 | AD48: =IF(M48="", 0, IF(ISNUMBER(SEARCH("Coworkers/Classmates", M48)), 1, 0)) -> 0 | AE48: =IF(M48="", 0, IF(ISNUMBER(SEARCH("Strangers", M48)), 1, 0)) -> 0 | AF48: =IF(N48="", 0, IF(ISNUMBER(SEARCH("Spring", N48)), 1, 0)) -> 0 | AG48: =IF(N48="", 0, IF(ISNUMBER(SEARCH("Summer", N48)), 1, 0)) -> 0 | AH48: =IF(N48="", 0, IF(ISNUMBER(SEARCH("Fall", N48)), 1, 0)) -> 1 | AI48: =IF(N48="", 0, IF(ISNUMBER(SEARCH("Winter", N48)), 1, 0)) -> 0
A49: 48 | B49: The Persistence of Memory | C49: 7 | D49: The painting makes me feel like time is passing by very slowly. The clocks are hung up on the cliff or on the tree branches in a fluid and in melting motion. The melting represent that the clocks itself had been exposed to the sun for a long time indicating the passing of long time. Since the clock is located far from the water in the abyss with no people there stands a separate between present which is the water that flows and time being on the shore. | E49: 5 - Strongly agree | F49: 2 - Disagree | G49: 5 - Strongly agree | H49: 5 - Strongly agree | I49: 4 | J49: 5 | K49: 1000 | L49: Bedroom,Living room | M49: Family members,By yourself | N49: Fall | O49: Cheese | P49: The godfather | Q49: =IF(E49="", "", LEFT(E49, 1) * 1) -> 5 | R49: =IF(F49="","",VALUE(LEFT(F49,FIND(" ",F49)-1))) -> 2 | S49: =IF(G49="","",VALUE(LEFT(G49,FIND(" ",G49)-1))) -> 5 | T49: =IF(H49="","",VALUE(LEFT(H49,FIND(" ",H49)-1))) -> 5 | U49: 1000 | V49: =IF(L49="",0,IF(ISNUMBER(SEARCH("Bathroom",L49)),1,0)) -> 0 | W49: =IF(L49="",0,IF(ISNUMBER(SEARCH("Dining room",L49)),1,0)) -> 0 | X49: =IF(L49="",0,IF(ISNUMBER(SEARCH("Office",L49)),1,0)) -> 0 | Y49: =IF(L49="",0,IF(ISNUMBER(SEARCH("Bedroom",L49)),1,0)) -> 1 | Z49: =IF(L49="",0,IF(ISNUMBER(SEARCH("Living room",L49)),1,0)) -> 1 | AA49: =IF(M49="",0, IF(ISNUMBER(SEARCH("By yourself",M49)), 1, 0)) -> 1 | AB49: =IF(M49="", 0, IF(ISNUMBER(SEARCH("Friends", M49)), 1, 0)) -> 0 | AC49: =IF(M49="",0,IF(ISNUMBER(SEARCH("Family members", M49)), 1, 0)) -> 1 | AD49: =IF(M49="", 0, IF(ISNUMBER(SEARCH("Coworkers/Classmates", M49)), 1, 0)) -> 0 | AE49: =IF(M49="", 0, IF(ISNUMBER(SEARCH("Strangers", M49)), 1, 0)) -> 0 | AF49: =IF(N49="", 0, IF(ISNUMBER(SEARCH("Spring", N49)), 1, 0)) -> 0 | AG49: =IF(N49="", 0, IF(ISNUMBER(SEARCH("Summer", N49)), 1, 0)) -> 0 | AH49: =IF(N49="", 0, IF(ISNUMBER(SEARCH("Fall", N49)), 1, 0)) -> 1 | AI49: =IF(N49="", 0, IF(ISNUMBER(SEARCH("Winter", N49)), 1, 0)) -> 0
A50: 49 | B50: The Persistence of Memory | C50: 8 | D50: time is passing too fast, sense of urgency, missing out, inevitable | E50: 4 - Agree | F50: 2 - Disagree | G50: 4 - Agree | H50: 4 - Agree | I50: 9 | J50: 5 | K50: $20¬† | L50: Office,Living room | M50: By yourself | N50: Fall | O50: Noodles¬† | P50: lonely, nostalgic, depressing¬† | Q50: =IF(E50="", "", LEFT(E50, 1) * 1) -> 4 | R50: =IF(F50="","",VALUE(LEFT(F50,FIND(" ",F50)-1))) -> 2 | S50: =IF(G50="","",VALUE(LEFT(G50,FIND(" ",G50)-1))) -> 4 | T50: =IF(H50="","",VALUE(LEFT(H50,FIND(" ",H50)-1))) -> 4 | U50: 20 | V50: =IF(L50="",0,IF(ISNUMBER(SEARCH("Bathroom",L50)),1,0)) -> 0 | W50: =IF(L50="",0,IF(ISNUMBER(SEARCH("Dining room",L50)),1,0)) -> 0 | X50: =IF(L50="",0,IF(ISNUMBER(SEARCH("Office",L50)),1,0)) -> 1 | Y50: =IF(L50="",0,IF(ISNUMBER(SEARCH("Bedroom",L50)),1,0)) -> 0 | Z50: =IF(L50="",0,IF(ISNUMBER(SEARCH("Living room",L50)),1,0)) -> 1 | AA50: =IF(M50="",0, IF(ISNUMBER(SEARCH("By yourself",M50)), 1, 0)) -> 1 | AB50: =IF(M50="", 0, IF(ISNUMBER(SEARCH("Friends", M50)), 1, 0)) -> 0 | AC50: =IF(M50="",0,IF(ISNUMBER(SEARCH("Family members", M50)), 1, 0)) -> 0 | AD50: =IF(M50="", 0, IF(ISNUMBER(SEARCH("Coworkers/Classmates", M50)), 1, 0)) -> 0 | AE50: =IF(M50="", 0, IF(ISNUMBER(SEARCH("Strangers", M50)), 1, 0)) -> 0 | AF50: =IF(N50="", 0, IF(ISNUMBER(SEARCH("Spring", N50)), 1, 0)) -> 0 | AG50: =IF(N50="", 0, IF(ISNUMBER(SEARCH("Summer", N50)), 1, 0)) -> 0 | AH50: =IF(N50="", 0, IF(ISNUMBER(SEARCH("Fall", N50)), 1, 0)) -> 1 | AI50: =IF(N50="", 0, IF(ISNUMBER(SEARCH("Winter", N50)), 1, 0)) -> 0
A51: 50 | B51: The Persistence of Memory | C51: 6 | D51: Slightly melancholy and pensive. The dismal foreground contrasted with the sparkling clarity and optimism of the background leads to a bittersweet feeling.¬† | E51: 4 - Agree | F51: 2 - Disagree | G51: 2 - Disagree | H51: 4 - Agree | I51: 4 | J51: 5 | K51: 200000000 | L51: Living room | M51: By yourself | N51: Fall | O51: Something earthy like yam.¬† | P51: Slow paced, detuned/slightly off-key electronic music with an intermittent warm pad sound that is contrastingly pure, pretty, and consoling sounding. The music would have sparse, minimal drum sounds.¬† | Q51: =IF(E51="", "", LEFT(E51, 1) * 1) -> 4 | R51: =IF(F51="","",VALUE(LEFT(F51,FIND(" ",F51)-1))) -> 2 | S51: =IF(G51="","",VALUE(LEFT(G51,FIND(" ",G51)-1))) -> 2 | T51: =IF(H51="","",VALUE(LEFT(H51,FIND(" ",H51)-1))) -> 4 | U51: 200000000 | V51: =IF(L51="",0,IF(ISNUMBER(SEARCH("Bathroom",L51)),1,0)) -> 0 | W51: =IF(L51="",0,IF(ISNUMBER(SEARCH("Dining room",L51)),1,0)) -> 0 | X51: =IF(L51="",0,IF(ISNUMBER(SEARCH("Office",L51)),1,0)) -> 0 | Y51: =IF(L51="",0,IF(ISNUMBER(SEARCH("Bedroom",L51)),1,0)) -> 0 | Z51: =IF(L51="",0,IF(ISNUMBER(SEARCH("Living room",L51)),1,0)) -> 1 | AA51: =IF(M51="",0, IF(ISNUMBER(SEARCH("By yourself",M51)), 1, 0)) -> 1 | AB51: =IF(M51="", 0, IF(ISNUMBER(SEARCH("Friends", M51)), 1, 0)) -> 0 | AC51: =IF(M51="",0,IF(ISNUMBER(SEARCH("Family members", M51)), 1, 0)) -> 0 | AD51: =IF(M51="", 0, IF(ISNUMBER(SEARCH("Coworkers/Classmates", M51)), 1, 0)) -> 0 | AE51: =IF(M51="", 0, IF(ISNUMBER(SEARCH("Strangers", M51)), 1, 0)) -> 0 | AF51: =IF(N51="", 0, IF(ISNUMBER(SEARCH("Spring", N51)), 1, 0)) -> 0 | AG51: =IF(N51="", 0, IF(ISNUMBER(SEARCH("Summer", N51)), 1, 0)) -> 0 | AH51: =IF(N51="", 0, IF(ISNUMBER(SEARCH("Fall", N51)), 1, 0)) -> 1 | AI51: =IF(N51="", 0, IF(ISNUMBER(SEARCH("Winter", N51)), 1, 0)) -> 0
A52: 51 | B52: The Persistence of Memory | C52: 6 | D52: It makes me feel sad. Like the time is drippng. Kind of weird | E52: 4 - Agree | F52: 3 - Neutral/Unsure | G52: 2 - Disagree | H52: 4 - Agree | I52: 4 | J52: 4 | K52: 0 | L52: Bathroom | M52: By yourself | N52: Summer | O52: noodles | P52: The soundtrack would be melancholic and quietly unsettling, with slow, lingering tones that feel slightly off-balance. The melody drifts without fully resolving, creating a sense of unease beneath its sadness. Subtle, irregular rhythms and faint dissonance give the music a strange, almost dreamlike quality, as if something familiar has been gently distorted. | Q52: =IF(E52="", "", LEFT(E52, 1) * 1) -> 4 | R52: =IF(F52="","",VALUE(LEFT(F52,FIND(" ",F52)-1))) -> 3 | S52: =IF(G52="","",VALUE(LEFT(G52,FIND(" ",G52)-1))) -> 2 | T52: =IF(H52="","",VALUE(LEFT(H52,FIND(" ",H52)-1))) -> 4 | U52: 0 | V52: =IF(L52="",0,IF(ISNUMBER(SEARCH("Bathroom",L52)),1,0)) -> 1 | W52: =IF(L52="",0,IF(ISNUMBER(SEARCH("Dining room",L52)),1,0)) -> 0 | X52: =IF(L52="",0,IF(ISNUMBER(SEARCH("Office",L52)),1,0)) -> 0 | Y52: =IF(L52="",0,IF(ISNUMBER(SEARCH("Bedroom",L52)),1,0)) -> 0 | Z52: =IF(L52="",0,IF(ISNUMBER(SEARCH("Living room",L52)),1,0)) -> 0 | AA52: =IF(M52="",0, IF(ISNUMBER(SEARCH("By yourself",M52)), 1, 0)) -> 1 | AB52: =IF(M52="", 0, IF(ISNUMBER(SEARCH("Friends", M52)), 1, 0)) -> 0 | AC52: =IF(M52="",0,IF(ISNUMBER(SEARCH("Family members", M52)), 1, 0)) -> 0 | AD52: =IF(M52="", 0, IF(ISNUMBER(SEARCH("Coworkers/Classmates", M52)), 1, 0)) -> 0 | AE52: =IF(M52="", 0, IF(ISNUMBER(SEARCH("Strangers", M52)), 1, 0)) -> 0 | AF52: =IF(N52="", 0, IF(ISNUMBER(SEARCH("Spring", N52)), 1, 0)) -> 0 | AG52: =IF(N52="", 0, IF(ISNUMBER(SEARCH("Summer", N52)), 1, 0)) -> 1 | AH52: =IF(N52="", 0, IF(ISNUMBER(SEARCH("Fall", N52)), 1, 0)) -> 0 | AI52: =IF(N52="", 0, IF(ISNUMBER(SEARCH("Winter", N52)), 1, 0)) -> 0
A53: 52 | B53: The Persistence of Memory | C53: 5 | D53: I feel confused, but I really resonate with the depiction of the dropping clocks and sock platypus. Initially I feel a very strong wave of emotion but the more I look at it, the less I feel.¬† | E53: 3 - Neutral/Unsure | F53: 2 - Disagree | G53: 2 - Disagree | H53: 4 - Agree | I53: 4 | J53: 4 | K53: 3 | L53: Bathroom | M53: Coworkers/Classmates,Strangers | N53: Winter | O53: Lasagna | P53: Soundtrack is like <<everywhere at the end of time>> I guess | Q53: =IF(E53="", "", LEFT(E53, 1) * 1) -> 3 | R53: =IF(F53="","",VALUE(LEFT(F53,FIND(" ",F53)-1))) -> 2 | S53: =IF(G53="","",VALUE(LEFT(G53,FIND(" ",G53)-1))) -> 2 | T53: =IF(H53="","",VALUE(LEFT(H53,FIND(" ",H53)-1))) -> 4 | U53: 3 | V53: =IF(L53="",0,IF(ISNUMBER(SEARCH("Bathroom",L53)),1,0)) -> 1 | W53: =IF(L53="",0,IF(ISNUMBER(SEARCH("Dining room",L53)),1,0)) -> 0 | X53: =IF(L53="",0,IF(ISNUMBER(SEARCH("Office",L53)),1,0)) -> 0 | Y53: =IF(L53="",0,IF(ISNUMBER(SEARCH("Bedroom",L53)),1,0)) -> 0 | Z53: =IF(L53="",0,IF(ISNUMBER(SEARCH("Living room",L53)),1,0)) -> 0 | AA53: =IF(M53="",0, IF(ISNUMBER(SEARCH("By yourself",M53)), 1, 0)) -> 0 | AB53: =IF(M53="", 0, IF(ISNUMBER(SEARCH("Friends", M53)), 1, 0)) -> 0 | AC53: =IF(M53="",0,IF(ISNUMBER(SEARCH("Family members", M53)), 1, 0)) -> 0 | AD53: =IF(M53="", 0, IF(ISNUMBER(SEARCH("Coworkers/Classmates", M53)), 1, 0)) -> 1 | AE53: =IF(M53="", 0, IF(ISNUMBER(SEARCH("Strangers", M53)), 1, 0)) -> 1 | AF53: =IF(N53="", 0, IF(ISNUMBER(SEARCH("Spring", N53)), 1, 0)) -> 0 | AG53: =IF(N53="", 0, IF(ISNUMBER(SEARCH("Summer", N53)), 1, 0)) -> 0 | AH53: =IF(N53="", 0, IF(ISNUMBER(SEARCH("Fall", N53)), 1, 0)) -> 0 | AI53: =IF(N53="", 0, IF(ISNUMBER(SEARCH("Winter", N53)), 1, 0)) -> 1
A54: 53 | B54: The Persistence of Memory | C54: 5 | D54: Uneasy, due to the distorted face, melted watches, and impossible geometry4 | E54: 2 - Disagree | F54: 2 - Disagree | G54: 2 - Disagree | H54: 4 - Agree | I54: 4 | J54: 5 | K54: 25 | L54: Bathroom | M54: Friends | N54: Winter | O54: Meat jelly | P54: Something familiar, but slowed down and distorted | Q54: =IF(E54="", "", LEFT(E54, 1) * 1) -> 2 | R54: =IF(F54="","",VALUE(LEFT(F54,FIND(" ",F54)-1))) -> 2 | S54: =IF(G54="","",VALUE(LEFT(G54,FIND(" ",G54)-1))) -> 2 | T54: =IF(H54="","",VALUE(LEFT(H54,FIND(" ",H54)-1))) -> 4 | U54: 25 | V54: =IF(L54="",0,IF(ISNUMBER(SEARCH("Bathroom",L54)),1,0)) -> 1 | W54: =IF(L54="",0,IF(ISNUMBER(SEARCH("Dining room",L54)),1,0)) -> 0 | X54: =IF(L54="",0,IF(ISNUMBER(SEARCH("Office",L54)),1,0)) -> 0 | Y54: =IF(L54="",0,IF(ISNUMBER(SEARCH("Bedroom",L54)),1,0)) -> 0 | Z54: =IF(L54="",0,IF(ISNUMBER(SEARCH("Living room",L54)),1,0)) -> 0 | AA54: =IF(M54="",0, IF(ISNUMBER(SEARCH("By yourself",M54)), 1, 0)) -> 0 | AB54: =IF(M54="", 0, IF(ISNUMBER(SEARCH("Friends", M54)), 1, 0)) -> 1 | AC54: =IF(M54="",0,IF(ISNUMBER(SEARCH("Family members", M54)), 1, 0)) -> 0 | AD54: =IF(M54="", 0, IF(ISNUMBER(SEARCH("Coworkers/Classmates", M54)), 1, 0)) -> 0 | AE54: =IF(M54="", 0, IF(ISNUMBER(SEARCH("Strangers", M54)), 1, 0)) -> 0 | AF54: =IF(N54="", 0, IF(ISNUMBER(SEARCH("Spring", N54)), 1, 0)) -> 0 | AG54: =IF(N54="", 0, IF(ISNUMBER(SEARCH("Summer", N54)), 1, 0)) -> 0 | AH54: =IF(N54="", 0, IF(ISNUMBER(SEARCH("Fall", N54)), 1, 0)) -> 0 | AI54: =IF(N54="", 0, IF(ISNUMBER(SEARCH("Winter", N54)), 1, 0)) -> 1
A55: 54 | B55: The Persistence of Memory | C55: 7 | D55: This painting makes me feel a little conflicted.¬† At the foreground of the painting the setting is quite dark.¬† On the other hand, the background seems kind of peaceful as opposed to the bleak foreground.¬† The contrast seems both unsettling and calming in a sense.¬† | E55: 3 - Neutral/Unsure | F55: 3 - Neutral/Unsure | G55: 4 - Agree | H55: 4 - Agree | I55: 8 | J55: 7 | K55: I would pay about $1000 for this painting.¬† This painting is very complex and also reflective in a way.¬† | L55: Office | M55: By yourself | N55: Spring | O55: If this painting was a food, I guess it would be dark chocolate.¬† At first time looking at this painting it seems kind of bleak and unsettling.¬† The same way that dark chocolate isn't always the best tasting when you first try it.¬† However, the more you look at it, the more you acquire a calm appreciation for it, like how dark chocolate becomes enjoyable over time.¬† | P55: I would imagine it being an alternative rock playlist, something that is calm and reflective but with a strong emotional complexity.¬† Something that carries a relaxing melody with more uneasy and reflective lyrics.¬† | Q55: =IF(E55="", "", LEFT(E55, 1) * 1) -> 3 | R55: =IF(F55="","",VALUE(LEFT(F55,FIND(" ",F55)-1))) -> 3 | S55: =IF(G55="","",VALUE(LEFT(G55,FIND(" ",G55)-1))) -> 4 | T55: =IF(H55="","",VALUE(LEFT(H55,FIND(" ",H55)-1))) -> 4 | U55: 1000 | V55: =IF(L55="",0,IF(ISNUMBER(SEARCH("Bathroom",L55)),1,0)) -> 0 | W55: =IF(L55="",0,IF(ISNUMBER(SEARCH("Dining room",L55)),1,0)) -> 0 | X55: =IF(L55="",0,IF(ISNUMBER(SEARCH("Office",L55)),1,0)) -> 1 | Y55: =IF(L55="",0,IF(ISNUMBER(SEARCH("Bedroom",L55)),1,0)) -> 0 | Z55: =IF(L55="",0,IF(ISNUMBER(SEARCH("Living room",L55)),1,0)) -> 0 | AA55: =IF(M55="",0, IF(ISNUMBER(SEARCH("By yourself",M55)), 1, 0)) -> 1 | AB55: =IF(M55="", 0, IF(ISNUMBER(SEARCH("Friends", M55)), 1, 0)) -> 0 | AC55: =IF(M55="",0,IF(ISNUMBER(SEARCH("Family members", M55)), 1, 0)) -> 0 | AD55: =IF(M55="", 0, IF(ISNUMBER(SEARCH("Coworkers/Classmates", M55)), 1, 0)) -> 0 | AE55: =IF(M55="", 0, IF(ISNUMBER(SEARCH("Strangers", M55)), 1, 0)) -> 0 | AF55: =IF(N55="", 0, IF(ISNUMBER(SEARCH("Spring", N55)), 1, 0)) -> 1 | AG55: =IF(N55="", 0, IF(ISNUMBER(SEARCH("Summer", N55)), 1, 0)) -> 0 | AH55: =IF(N55="", 0, IF(ISNUMBER(SEARCH("Fall", N55)), 1, 0)) -> 0 | AI55: =IF(N55="", 0, IF(ISNUMBER(SEARCH("Winter", N55)), 1, 0)) -> 0
A56: 55 | B56: The Persistence of Memory | C56: 7 | D56: Makes me feel like I'm relaxed and it's time to sleep.¬† | E56: 4 - Agree | F56: 2 - Disagree | G56: 5 - Strongly agree | H56: 3 - Neutral/Unsure | I56: 3 | J56: 5 | K56: 50 | L56: Bathroom | M56: Strangers | N56: Fall | O56: mac and cheese | P56: ticks and drums | Q56: =IF(E56="", "", LEFT(E56, 1) * 1) -> 4 | R56: =IF(F56="","",VALUE(LEFT(F56,FIND(" ",F56)-1))) -> 2 | S56: =IF(G56="","",VALUE(LEFT(G56,FIND(" ",G56)-1))) -> 5 | T56: =IF(H56="","",VALUE(LEFT(H56,FIND(" ",H56)-1))) -> 3 | U56: 50 | V56: =IF(L56="",0,IF(ISNUMBER(SEARCH("Bathroom",L56)),1,0)) -> 1 | W56: =IF(L56="",0,IF(ISNUMBER(SEARCH("Dining room",L56)),1,0)) -> 0 | X56: =IF(L56="",0,IF(ISNUMBER(SEARCH("Office",L56)),1,0)) -> 0 | Y56: =IF(L56="",0,IF(ISNUMBER(SEARCH("Bedroom",L56)),1,0)) -> 0 | Z56: =IF(L56="",0,IF(ISNUMBER(SEARCH("Living room",L56)),1,0)) -> 0 | AA56: =IF(M56="",0, IF(ISNUMBER(SEARCH("By yourself",M56)), 1, 0)) -> 0 | AB56: =IF(M56="", 0, IF(ISNUMBER(SEARCH("Friends", M56)), 1, 0)) -> 0 | AC56: =IF(M56="",0,IF(ISNUMBER(SEARCH("Family members", M56)), 1, 0)) -> 0 | AD56: =IF(M56="", 0, IF(ISNUMBER(SEARCH("Coworkers/Classmates", M56)), 1, 0)) -> 0 | AE56: =IF(M56="", 0, IF(ISNUMBER(SEARCH("Strangers", M56)), 1, 0)) -> 1 | AF56: =IF(N56="", 0, IF(ISNUMBER(SEARCH("Spring", N56)), 1, 0)) -> 0 | AG56: =IF(N56="", 0, IF(ISNUMBER(SEARCH("Summer", N56)), 1, 0)) -> 0 | AH56: =IF(N56="", 0, IF(ISNUMBER(SEARCH("Fall", N56)), 1, 0)) -> 1 | AI56: =IF(N56="", 0, IF(ISNUMBER(SEARCH("Winter", N56)), 1, 0)) -> 0
A57: 56 | B57: The Persistence of Memory | C57: 9 | D57: It makes me feel kind of uncomfortable but also interested. Everything feels off in a weird way, like things are not normal, and that makes me slightly uneasy but curious at the same time. Makes me think about my life¬† | E57: 4 - Agree | F57: 2 - Disagree | G57: 2 - Disagree | H57: 4 - Agree | I57: 4 | J57: 7 | K57: 3500000 | L57: Office | M57: By yourself | N57: Summer | O57: Cottage cheese¬† | P57: Slow, quiet music with a slightly eerie haunting feeling. It feels stretched out and uncomfortable, like something is a bit off. Uncanny valley. | Q57: =IF(E57="", "", LEFT(E57, 1) * 1) -> 4 | R57: =IF(F57="","",VALUE(LEFT(F57,FIND(" ",F57)-1))) -> 2 | S57: =IF(G57="","",VALUE(LEFT(G57,FIND(" ",G57)-1))) -> 2 | T57: =IF(H57="","",VALUE(LEFT(H57,FIND(" ",H57)-1))) -> 4 | U57: 3500000 | V57: =IF(L57="",0,IF(ISNUMBER(SEARCH("Bathroom",L57)),1,0)) -> 0 | W57: =IF(L57="",0,IF(ISNUMBER(SEARCH("Dining room",L57)),1,0)) -> 0 | X57: =IF(L57="",0,IF(ISNUMBER(SEARCH("Office",L57)),1,0)) -> 1 | Y57: =IF(L57="",0,IF(ISNUMBER(SEARCH("Bedroom",L57)),1,0)) -> 0 | Z57: =IF(L57="",0,IF(ISNUMBER(SEARCH("Living room",L57)),1,0)) -> 0 | AA57: =IF(M57="",0, IF(ISNUMBER(SEARCH("By yourself",M57)), 1, 0)) -> 1 | AB57: =IF(M57="", 0, IF(ISNUMBER(SEARCH("Friends", M57)), 1, 0)) -> 0 | AC57: =IF(M57="",0,IF(ISNUMBER(SEARCH("Family members", M57)), 1, 0)) -> 0 | AD57: =IF(M57="", 0, IF(ISNUMBER(SEARCH("Coworkers/Classmates", M57)), 1, 0)) -> 0 | AE57: =IF(M57="", 0, IF(ISNUMBER(SEARCH("Strangers", M57)), 1, 0)) -> 0 | AF57: =IF(N57="", 0, IF(ISNUMBER(SEARCH("Spring", N57)), 1, 0)) -> 0 | AG57: =IF(N57="", 0, IF(ISNUMBER(SEARCH("Summer", N57)), 1, 0)) -> 1 | AH57: =IF(N57="", 0, IF(ISNUMBER(SEARCH("Fall", N57)), 1, 0)) -> 0 | AI57: =IF(N57="", 0, IF(ISNUMBER(SEARCH("Winter", N57)), 1, 0)) -> 0
A58: 57 | B58: The Persistence of Memory | C58: 5 | D58: the painting has an eerie and/or melancholic ambiance to it. The droopiness of the clocks makes me feel as though time is slipping through my fingers, that no matter how hard we try to control it (hang it, set it down or aside) it will inevitably slip through my hands. Ultimately reminding me that time is fluid and uncontrollable. The silence and calmness of the background, the still water contrasts the clocks and makes it seem like time has stopped moving. Its difficult to describe, but I the distorted nature of the objects paired with the eerie calm invokes an existential feeling, almost sad, but not quite.¬† | E58: 4 - Agree | F58: 2 - Disagree | G58: 5 - Strongly agree | H58: 5 - Strongly agree | I58: 5 | J58: 6 | K58: $100 dollars on the higher end.¬† | L58: Office,Living room | M58: Friends,Family members,By yourself | N58: Summer | O58: like an undercooked egg.¬† | P58: Something eerie to create an atmospheric tension. Maybe some deep humming in the back, with some slow metallic distortions. even more subtly, there could be some frantic sounds underneath it all, a faint skittering to emphasize the anxiety induced by the feeling of emptiness. But I'd want to, above all else, emphasize the silent calm so maybe the track could be very low volume for most of it and transition between the loud and quiet.¬† | Q58: =IF(E58="", "", LEFT(E58, 1) * 1) -> 4 | R58: =IF(F58="","",VALUE(LEFT(F58,FIND(" ",F58)-1))) -> 2 | S58: =IF(G58="","",VALUE(LEFT(G58,FIND(" ",G58)-1))) -> 5 | T58: =IF(H58="","",VALUE(LEFT(H58,FIND(" ",H58)-1))) -> 5 | U58: 100 | V58: =IF(L58="",0,IF(ISNUMBER(SEARCH("Bathroom",L58)),1,0)) -> 0 | W58: =IF(L58="",0,IF(ISNUMBER(SEARCH("Dining room",L58)),1,0)) -> 0 | X58: =IF(L58="",0,IF(ISNUMBER(SEARCH("Office",L58)),1,0)) -> 1 | Y58: =IF(L58="",0,IF(ISNUMBER(SEARCH("Bedroom",L58)),1,0)) -> 0 | Z58: =IF(L58="",0,IF(ISNUMBER(SEARCH("Living room",L58)),1,0)) -> 1 | AA58: =IF(M58="",0, IF(ISNUMBER(SEARCH("By yourself",M58)), 1, 0)) -> 1 | AB58: =IF(M58="", 0, IF(ISNUMBER(SEARCH("Friends", M58)), 1, 0)) -> 1 | AC58: =IF(M58="",0,IF(ISNUMBER(SEARCH("Family members", M58)), 1, 0)) -> 1 | AD58: =IF(M58="", 0, IF(ISNUMBER(SEARCH("Coworkers/Classmates", M58)), 1, 0)) -> 0 | AE58: =IF(M58="", 0, IF(ISNUMBER(SEARCH("Strangers", M58)), 1, 0)) -> 0 | AF58: =IF(N58="", 0, IF(ISNUMBER(SEARCH("Spring", N58)), 1, 0)) -> 0 | AG58: =IF(N58="", 0, IF(ISNUMBER(SEARCH("Summer", N58)), 1, 0)) -> 1 | AH58: =IF(N58="", 0, IF(ISNUMBER(SEARCH("Fall", N58)), 1, 0)) -> 0 | AI58: =IF(N58="", 0, IF(ISNUMBER(SEARCH("Winter", N58)), 1, 0)) -> 0
A59: 58 | B59: The Persistence of Memory | C59: 6 | D59: Like I am melting. | E59: 4 - Agree | F59: 3 - Neutral/Unsure | G59: 2 - Disagree | H59: 5 - Strongly agree | I59: 6 | J59: 5 | K59: 3000 | L59: Bedroom,Bathroom,Office,Living room,Dining room | M59: Family members,By yourself | N59: Fall | O59: cheese, maybe in a cheese board | P59: a semi-constant ticking with background nature white noise | Q59: =IF(E59="", "", LEFT(E59, 1) * 1) -> 4 | R59: =IF(F59="","",VALUE(LEFT(F59,FIND(" ",F59)-1))) -> 3 | S59: =IF(G59="","",VALUE(LEFT(G59,FIND(" ",G59)-1))) -> 2 | T59: =IF(H59="","",VALUE(LEFT(H59,FIND(" ",H59)-1))) -> 5 | U59: 3000 | V59: =IF(L59="",0,IF(ISNUMBER(SEARCH("Bathroom",L59)),1,0)) -> 1 | W59: =IF(L59="",0,IF(ISNUMBER(SEARCH("Dining room",L59)),1,0)) -> 1 | X59: =IF(L59="",0,IF(ISNUMBER(SEARCH("Office",L59)),1,0)) -> 1 | Y59: =IF(L59="",0,IF(ISNUMBER(SEARCH("Bedroom",L59)),1,0)) -> 1 | Z59: =IF(L59="",0,IF(ISNUMBER(SEARCH("Living room",L59)),1,0)) -> 1 | AA59: =IF(M59="",0, IF(ISNUMBER(SEARCH("By yourself",M59)), 1, 0)) -> 1 | AB59: =IF(M59="", 0, IF(ISNUMBER(SEARCH("Friends", M59)), 1, 0)) -> 0 | AC59: =IF(M59="",0,IF(ISNUMBER(SEARCH("Family members", M59)), 1, 0)) -> 1 | AD59: =IF(M59="", 0, IF(ISNUMBER(SEARCH("Coworkers/Classmates", M59)), 1, 0)) -> 0 | AE59: =IF(M59="", 0, IF(ISNUMBER(SEARCH("Strangers", M59)), 1, 0)) -> 0 | AF59: =IF(N59="", 0, IF(ISNUMBER(SEARCH("Spring", N59)), 1, 0)) -> 0 | AG59: =IF(N59="", 0, IF(ISNUMBER(SEARCH("Summer", N59)), 1, 0)) -> 0 | AH59: =IF(N59="", 0, IF(ISNUMBER(SEARCH("Fall", N59)), 1, 0)) -> 1 | AI59: =IF(N59="", 0, IF(ISNUMBER(SEARCH("Winter", N59)), 1, 0)) -> 0
A60: 59 | B60: The Persistence of Memory | C60: 7 | D60: Melancholic, Lonely, Abandoned, Pensiveness | E60: 5 - Strongly agree | F60: 3 - Neutral/Unsure | G60: 2 - Disagree | H60: 5 - Strongly agree | I60: 4 | J60: 6 | K60: 10000000 | L60: Living room | M60: By yourself | N60: Winter | O60: Shepherd's Pie | P60: Something out of a Christopher Nolan movie. Long, steady, sombre notes. | Q60: =IF(E60="", "", LEFT(E60, 1) * 1) -> 5 | R60: =IF(F60="","",VALUE(LEFT(F60,FIND(" ",F60)-1))) -> 3 | S60: =IF(G60="","",VALUE(LEFT(G60,FIND(" ",G60)-1))) -> 2 | T60: =IF(H60="","",VALUE(LEFT(H60,FIND(" ",H60)-1))) -> 5 | U60: 10000000 | V60: =IF(L60="",0,IF(ISNUMBER(SEARCH("Bathroom",L60)),1,0)) -> 0 | W60: =IF(L60="",0,IF(ISNUMBER(SEARCH("Dining room",L60)),1,0)) -> 0 | X60: =IF(L60="",0,IF(ISNUMBER(SEARCH("Office",L60)),1,0)) -> 0 | Y60: =IF(L60="",0,IF(ISNUMBER(SEARCH("Bedroom",L60)),1,0)) -> 0 | Z60: =IF(L60="",0,IF(ISNUMBER(SEARCH("Living room",L60)),1,0)) -> 1 | AA60: =IF(M60="",0, IF(ISNUMBER(SEARCH("By yourself",M60)), 1, 0)) -> 1 | AB60: =IF(M60="", 0, IF(ISNUMBER(SEARCH("Friends", M60)), 1, 0)) -> 0 | AC60: =IF(M60="",0,IF(ISNUMBER(SEARCH("Family members", M60)), 1, 0)) -> 0 | AD60: =IF(M60="", 0, IF(ISNUMBER(SEARCH("Coworkers/Classmates", M60)), 1, 0)) -> 0 | AE60: =IF(M60="", 0, IF(ISNUMBER(SEARCH("Strangers", M60)), 1, 0)) -> 0 | AF60: =IF(N60="", 0, IF(ISNUMBER(SEARCH("Spring", N60)), 1, 0)) -> 0 | AG60: =IF(N60="", 0, IF(ISNUMBER(SEARCH("Summer", N60)), 1, 0)) -> 0 | AH60: =IF(N60="", 0, IF(ISNUMBER(SEARCH("Fall", N60)), 1, 0)) -> 0 | AI60: =IF(N60="", 0, IF(ISNUMBER(SEARCH("Winter", N60)), 1, 0)) -> 1
A61: 60 | B61: The Persistence of Memory | C61: 5 | D61: This painting confuses me. I don‚Äôt usually associate the concept of time with a shoreline, as the two ideas feel quite contrasting. The shoreline suggests something natural and constant, while the clocks are "droopy" and create a sense of distortion.¬† | E61: 4 - Agree | F61: 2 - Disagree | G61: 2 - Disagree | H61: 4 - Agree | I61: 11 | J61: 12 | K61: 20 | L61: Office | M61: Strangers,By yourself | N61: Fall | O61: Popeyes¬† | P61: The soundtrack will be a slow, love song. Time at the beach alone with another. | Q61: =IF(E61="", "", LEFT(E61, 1) * 1) -> 4 | R61: =IF(F61="","",VALUE(LEFT(F61,FIND(" ",F61)-1))) -> 2 | S61: =IF(G61="","",VALUE(LEFT(G61,FIND(" ",G61)-1))) -> 2 | T61: =IF(H61="","",VALUE(LEFT(H61,FIND(" ",H61)-1))) -> 4 | U61: 20 | V61: =IF(L61="",0,IF(ISNUMBER(SEARCH("Bathroom",L61)),1,0)) -> 0 | W61: =IF(L61="",0,IF(ISNUMBER(SEARCH("Dining room",L61)),1,0)) -> 0 | X61: =IF(L61="",0,IF(ISNUMBER(SEARCH("Office",L61)),1,0)) -> 1 | Y61: =IF(L61="",0,IF(ISNUMBER(SEARCH("Bedroom",L61)),1,0)) -> 0 | Z61: =IF(L61="",0,IF(ISNUMBER(SEARCH("Living room",L61)),1,0)) -> 0 | AA61: =IF(M61="",0, IF(ISNUMBER(SEARCH("By yourself",M61)), 1, 0)) -> 1 | AB61: =IF(M61="", 0, IF(ISNUMBER(SEARCH("Friends", M61)), 1, 0)) -> 0 | AC61: =IF(M61="",0,IF(ISNUMBER(SEARCH("Family members", M61)), 1, 0)) -> 0 | AD61: =IF(M61="", 0, IF(ISNUMBER(SEARCH("Coworkers/Classmates", M61)), 1, 0)) -> 0 | AE61: =IF(M61="", 0, IF(ISNUMBER(SEARCH("Strangers", M61)), 1, 0)) -> 1 | AF61: =IF(N61="", 0, IF(ISNUMBER(SEARCH("Spring", N61)), 1, 0)) -> 0 | AG61: =IF(N61="", 0, IF(ISNUMBER(SEARCH("Summer", N61)), 1, 0)) -> 0 | AH61: =IF(N61="", 0, IF(ISNUMBER(SEARCH("Fall", N61)), 1, 0)) -> 1 | AI61: =IF(N61="", 0, IF(ISNUMBER(SEARCH("Winter", N61)), 1, 0)) -> 0
A62: 61 | B62: The Persistence of Memory | C62: 7 | D62: The painting makes me feel desperate, like I'm running out of time or that everything is on the verge of being lost. It's unsettling and somewhat confusing. There seems to be hope on the horizon but it's far and slipping away. | E62: 4 - Agree | F62: 1 - Strongly disagree | G62: 1 - Strongly disagree | H62: 5 - Strongly agree | I62: 4 | J62: 5 | K62: $10000? | L62: Office,Living room | M62: Friends,By yourself | N62: Fall,Winter | O62: Cold spaghetti. | P62: Sombre music, slightly fast tempo, a feeling of dread.¬† | Q62: =IF(E62="", "", LEFT(E62, 1) * 1) -> 4 | R62: =IF(F62="","",VALUE(LEFT(F62,FIND(" ",F62)-1))) -> 1 | S62: =IF(G62="","",VALUE(LEFT(G62,FIND(" ",G62)-1))) -> 1 | T62: =IF(H62="","",VALUE(LEFT(H62,FIND(" ",H62)-1))) -> 5 | U62: 10000 | V62: =IF(L62="",0,IF(ISNUMBER(SEARCH("Bathroom",L62)),1,0)) -> 0 | W62: =IF(L62="",0,IF(ISNUMBER(SEARCH("Dining room",L62)),1,0)) -> 0 | X62: =IF(L62="",0,IF(ISNUMBER(SEARCH("Office",L62)),1,0)) -> 1 | Y62: =IF(L62="",0,IF(ISNUMBER(SEARCH("Bedroom",L62)),1,0)) -> 0 | Z62: =IF(L62="",0,IF(ISNUMBER(SEARCH("Living room",L62)),1,0)) -> 1 | AA62: =IF(M62="",0, IF(ISNUMBER(SEARCH("By yourself",M62)), 1, 0)) -> 1 | AB62: =IF(M62="", 0, IF(ISNUMBER(SEARCH("Friends", M62)), 1, 0)) -> 1 | AC62: =IF(M62="",0,IF(ISNUMBER(SEARCH("Family members", M62)), 1, 0)) -> 0 | AD62: =IF(M62="", 0, IF(ISNUMBER(SEARCH("Coworkers/Classmates", M62)), 1, 0)) -> 0 | AE62: =IF(M62="", 0, IF(ISNUMBER(SEARCH("Strangers", M62)), 1, 0)) -> 0 | AF62: =IF(N62="", 0, IF(ISNUMBER(SEARCH("Spring", N62)), 1, 0)) -> 0 | AG62: =IF(N62="", 0, IF(ISNUMBER(SEARCH("Summer", N62)), 1, 0)) -> 0 | AH62: =IF(N62="", 0, IF(ISNUMBER(SEARCH("Fall", N62)), 1, 0)) -> 1 | AI62: =IF(N62="", 0, IF(ISNUMBER(SEARCH("Winter", N62)), 1, 0)) -> 1
A63: 62 | B63: The Persistence of Memory | C63: 4 | D63: It makes me feel a bit somber, calm, and nostalgic. | E63: 3 - Neutral/Unsure | F63: 4 - Agree | G63: 4 - Agree | H63: 2 - Disagree | I63: 4 | J63: 6 | K63: 5000 | L63: Dining room | M63: By yourself | N63: Fall | O63: Pear | P63: It would include like an acoustic guitar and a simple, slow, calm melody. Similar to like latin music.¬† | Q63: =IF(E63="", "", LEFT(E63, 1) * 1) -> 3 | R63: =IF(F63="","",VALUE(LEFT(F63,FIND(" ",F63)-1))) -> 4 | S63: =IF(G63="","",VALUE(LEFT(G63,FIND(" ",G63)-1))) -> 4 | T63: =IF(H63="","",VALUE(LEFT(H63,FIND(" ",H63)-1))) -> 2 | U63: 5000 | V63: =IF(L63="",0,IF(ISNUMBER(SEARCH("Bathroom",L63)),1,0)) -> 0 | W63: =IF(L63="",0,IF(ISNUMBER(SEARCH("Dining room",L63)),1,0)) -> 1 | X63: =IF(L63="",0,IF(ISNUMBER(SEARCH("Office",L63)),1,0)) -> 0 | Y63: =IF(L63="",0,IF(ISNUMBER(SEARCH("Bedroom",L63)),1,0)) -> 0 | Z63: =IF(L63="",0,IF(ISNUMBER(SEARCH("Living room",L63)),1,0)) -> 0 | AA63: =IF(M63="",0, IF(ISNUMBER(SEARCH("By yourself",M63)), 1, 0)) -> 1 | AB63: =IF(M63="", 0, IF(ISNUMBER(SEARCH("Friends", M63)), 1, 0)) -> 0 | AC63: =IF(M63="",0,IF(ISNUMBER(SEARCH("Family members", M63)), 1, 0)) -> 0 | AD63: =IF(M63="", 0, IF(ISNUMBER(SEARCH("Coworkers/Classmates", M63)), 1, 0)) -> 0 | AE63: =IF(M63="", 0, IF(ISNUMBER(SEARCH("Strangers", M63)), 1, 0)) -> 0 | AF63: =IF(N63="", 0, IF(ISNUMBER(SEARCH("Spring", N63)), 1, 0)) -> 0 | AG63: =IF(N63="", 0, IF(ISNUMBER(SEARCH("Summer", N63)), 1, 0)) -> 0 | AH63: =IF(N63="", 0, IF(ISNUMBER(SEARCH("Fall", N63)), 1, 0)) -> 1 | AI63: =IF(N63="", 0, IF(ISNUMBER(SEARCH("Winter", N63)), 1, 0)) -> 0
A64: 63 | B64: The Persistence of Memory | C64: 7 | D64: This painting makes me feel the fluidity of time, which in turn makes me feel a sense of existential dread. Overall, this painting makes me feel somewhat uncomfortable. | E64: 4 - Agree | F64: 2 - Disagree | G64: 2 - Disagree | H64: 5 - Strongly agree | I64: 7 | J64: 4 | K64: 80000 | L64: Office,Dining room | M64: By yourself | N64: Fall | O64: A piece of speck that has been left outside of it's packaging for 2 days, making it more dry. | P64: A piano composition that is very quiet, lowkey and elegant but composed in such a way that it feels uncomfortable and anxious to listen to. | Q64: =IF(E64="", "", LEFT(E64, 1) * 1) -> 4 | R64: =IF(F64="","",VALUE(LEFT(F64,FIND(" ",F64)-1))) -> 2 | S64: =IF(G64="","",VALUE(LEFT(G64,FIND(" ",G64)-1))) -> 2 | T64: =IF(H64="","",VALUE(LEFT(H64,FIND(" ",H64)-1))) -> 5 | U64: 80000 | V64: =IF(L64="",0,IF(ISNUMBER(SEARCH("Bathroom",L64)),1,0)) -> 0 | W64: =IF(L64="",0,IF(ISNUMBER(SEARCH("Dining room",L64)),1,0)) -> 1 | X64: =IF(L64="",0,IF(ISNUMBER(SEARCH("Office",L64)),1,0)) -> 1 | Y64: =IF(L64="",0,IF(ISNUMBER(SEARCH("Bedroom",L64)),1,0)) -> 0 | Z64: =IF(L64="",0,IF(ISNUMBER(SEARCH("Living room",L64)),1,0)) -> 0 | AA64: =IF(M64="",0, IF(ISNUMBER(SEARCH("By yourself",M64)), 1, 0)) -> 1 | AB64: =IF(M64="", 0, IF(ISNUMBER(SEARCH("Friends", M64)), 1, 0)) -> 0 | AC64: =IF(M64="",0,IF(ISNUMBER(SEARCH("Family members", M64)), 1, 0)) -> 0 | AD64: =IF(M64="", 0, IF(ISNUMBER(SEARCH("Coworkers/Classmates", M64)), 1, 0)) -> 0 | AE64: =IF(M64="", 0, IF(ISNUMBER(SEARCH("Strangers", M64)), 1, 0)) -> 0 | AF64: =IF(N64="", 0, IF(ISNUMBER(SEARCH("Spring", N64)), 1, 0)) -> 0 | AG64: =IF(N64="", 0, IF(ISNUMBER(SEARCH("Summer", N64)), 1, 0)) -> 0 | AH64: =IF(N64="", 0, IF(ISNUMBER(SEARCH("Fall", N64)), 1, 0)) -> 1 | AI64: =IF(N64="", 0, IF(ISNUMBER(SEARCH("Winter", N64)), 1, 0)) -> 0
A65: 64 | B65: The Persistence of Memory | C65: 5 | D65: I feel the painting illustrates the passage of time and the inevitable change it brings. This is demonstrated with the clocks melting overtime. | E65: 5 - Strongly agree | F65: 2 - Disagree | G65: 2 - Disagree | H65: 4 - Agree | I65: 3 | J65: 6 | K65: 200 | L65: Bedroom | M65: Family members,By yourself | N65: Fall | O65: Chocolate | P65: The sound track would have violin and piano, with long notes that fade out. | Q65: =IF(E65="", "", LEFT(E65, 1) * 1) -> 5 | R65: =IF(F65="","",VALUE(LEFT(F65,FIND(" ",F65)-1))) -> 2 | S65: =IF(G65="","",VALUE(LEFT(G65,FIND(" ",G65)-1))) -> 2 | T65: =IF(H65="","",VALUE(LEFT(H65,FIND(" ",H65)-1))) -> 4 | U65: 200 | V65: =IF(L65="",0,IF(ISNUMBER(SEARCH("Bathroom",L65)),1,0)) -> 0 | W65: =IF(L65="",0,IF(ISNUMBER(SEARCH("Dining room",L65)),1,0)) -> 0 | X65: =IF(L65="",0,IF(ISNUMBER(SEARCH("Office",L65)),1,0)) -> 0 | Y65: =IF(L65="",0,IF(ISNUMBER(SEARCH("Bedroom",L65)),1,0)) -> 1 | Z65: =IF(L65="",0,IF(ISNUMBER(SEARCH("Living room",L65)),1,0)) -> 0 | AA65: =IF(M65="",0, IF(ISNUMBER(SEARCH("By yourself",M65)), 1, 0)) -> 1 | AB65: =IF(M65="", 0, IF(ISNUMBER(SEARCH("Friends", M65)), 1, 0)) -> 0 | AC65: =IF(M65="",0,IF(ISNUMBER(SEARCH("Family members", M65)), 1, 0)) -> 1 | AD65: =IF(M65="", 0, IF(ISNUMBER(SEARCH("Coworkers/Classmates", M65)), 1, 0)) -> 0 | AE65: =IF(M65="", 0, IF(ISNUMBER(SEARCH("Strangers", M65)), 1, 0)) -> 0 | AF65: =IF(N65="", 0, IF(ISNUMBER(SEARCH("Spring", N65)), 1, 0)) -> 0 | AG65: =IF(N65="", 0, IF(ISNUMBER(SEARCH("Summer", N65)), 1, 0)) -> 0 | AH65: =IF(N65="", 0, IF(ISNUMBER(SEARCH("Fall", N65)), 1, 0)) -> 1 | AI65: =IF(N65="", 0, IF(ISNUMBER(SEARCH("Winter", N65)), 1, 0)) -> 0
A66: 65 | B66: The Persistence of Memory | C66: 4 | D66: This painting made me feel unrealistic, a little bit of conflict between chaos and peace. | E66: 2 - Disagree | F66: 2 - Disagree | G66: 3 - Neutral/Unsure | H66: 2 - Disagree | I66: 5 | J66: 4 | K66: 10 | L66: Bedroom,Living room | M66: Strangers,By yourself | N66: Fall | O66: A desert made of drinks like cocktail. | P66: clock ticking with a little breeze in the background. | Q66: =IF(E66="", "", LEFT(E66, 1) * 1) -> 2 | R66: =IF(F66="","",VALUE(LEFT(F66,FIND(" ",F66)-1))) -> 2 | S66: =IF(G66="","",VALUE(LEFT(G66,FIND(" ",G66)-1))) -> 3 | T66: =IF(H66="","",VALUE(LEFT(H66,FIND(" ",H66)-1))) -> 2 | U66: 10 | V66: =IF(L66="",0,IF(ISNUMBER(SEARCH("Bathroom",L66)),1,0)) -> 0 | W66: =IF(L66="",0,IF(ISNUMBER(SEARCH("Dining room",L66)),1,0)) -> 0 | X66: =IF(L66="",0,IF(ISNUMBER(SEARCH("Office",L66)),1,0)) -> 0 | Y66: =IF(L66="",0,IF(ISNUMBER(SEARCH("Bedroom",L66)),1,0)) -> 1 | Z66: =IF(L66="",0,IF(ISNUMBER(SEARCH("Living room",L66)),1,0)) -> 1 | AA66: =IF(M66="",0, IF(ISNUMBER(SEARCH("By yourself",M66)), 1, 0)) -> 1 | AB66: =IF(M66="", 0, IF(ISNUMBER(SEARCH("Friends", M66)), 1, 0)) -> 0 | AC66: =IF(M66="",0,IF(ISNUMBER(SEARCH("Family members", M66)), 1, 0)) -> 0 | AD66: =IF(M66="", 0, IF(ISNUMBER(SEARCH("Coworkers/Classmates", M66)), 1, 0)) -> 0 | AE66: =IF(M66="", 0, IF(ISNUMBER(SEARCH("Strangers", M66)), 1, 0)) -> 1 | AF66: =IF(N66="", 0, IF(ISNUMBER(SEARCH("Spring", N66)), 1, 0)) -> 0 | AG66: =IF(N66="", 0, IF(ISNUMBER(SEARCH("Summer", N66)), 1, 0)) -> 0 | AH66: =IF(N66="", 0, IF(ISNUMBER(SEARCH("Fall", N66)), 1, 0)) -> 1 | AI66: =IF(N66="", 0, IF(ISNUMBER(SEARCH("Winter", N66)), 1, 0)) -> 0
A67: 66 | B67: The Persistence of Memory | C67: 3 | D67: It is odd, I feel like it is a sad picture, but I cannot understand what happened in the picture, or what the message artist would like to tell us. | E67: 4 - Agree | F67: 1 - Strongly disagree | G67: 2 - Disagree | H67: 4 - Agree | I67: 12 | J67: 6 | K67: 0. I feel bad when I look at this picture. I have no reason to buy it. | L67: Bathroom | M67: By yourself | N67: Winter | O67: shawarma | P67: The music "Memories", in the movie Top Gun (1986), when Goose dies. It is not very sad, but a bit sad desolate, and the picture and the music makes me reflect on memories, and regret on past things,¬† that you can't go back. | Q67: =IF(E67="", "", LEFT(E67, 1) * 1) -> 4 | R67: =IF(F67="","",VALUE(LEFT(F67,FIND(" ",F67)-1))) -> 1 | S67: =IF(G67="","",VALUE(LEFT(G67,FIND(" ",G67)-1))) -> 2 | T67: =IF(H67="","",VALUE(LEFT(H67,FIND(" ",H67)-1))) -> 4 | U67: 0 | V67: =IF(L67="",0,IF(ISNUMBER(SEARCH("Bathroom",L67)),1,0)) -> 1 | W67: =IF(L67="",0,IF(ISNUMBER(SEARCH("Dining room",L67)),1,0)) -> 0 | X67: =IF(L67="",0,IF(ISNUMBER(SEARCH("Office",L67)),1,0)) -> 0 | Y67: =IF(L67="",0,IF(ISNUMBER(SEARCH("Bedroom",L67)),1,0)) -> 0 | Z67: =IF(L67="",0,IF(ISNUMBER(SEARCH("Living room",L67)),1,0)) -> 0 | AA67: =IF(M67="",0, IF(ISNUMBER(SEARCH("By yourself",M67)), 1, 0)) -> 1 | AB67: =IF(M67="", 0, IF(ISNUMBER(SEARCH("Friends", M67)), 1, 0)) -> 0 | AC67: =IF(M67="",0,IF(ISNUMBER(SEARCH("Family members", M67)), 1, 0)) -> 0 | AD67: =IF(M67="", 0, IF(ISNUMBER(SEARCH("Coworkers/Classmates", M67)), 1, 0)) -> 0 | AE67: =IF(M67="", 0, IF(ISNUMBER(SEARCH("Strangers", M67)), 1, 0)) -> 0 | AF67: =IF(N67="", 0, IF(ISNUMBER(SEARCH("Spring", N67)), 1, 0)) -> 0 | AG67: =IF(N67="", 0, IF(ISNUMBER(SEARCH("Summer", N67)), 1, 0)) -> 0 | AH67: =IF(N67="", 0, IF(ISNUMBER(SEARCH("Fall", N67)), 1, 0)) -> 0 | AI67: =IF(N67="", 0, IF(ISNUMBER(SEARCH("Winter", N67)), 1, 0)) -> 1
A68: 67 | B68: The Persistence of Memory | C68: 8 | D68: It provokes a daunting feeling in me. The unchanged solid landscape is juxtaposed with the melting clocks. Almost like that time is moving so fast it has melted but nothing has really changed. It reminds me of my own mortality and that the natural world does not care about our measures of time. Once our time is up the world does not relent. | E68: 5 - Strongly agree | F68: 1 - Strongly disagree | G68: 3 - Neutral/Unsure | H68: 4 - Agree | I68: 3 | J68: 6 | K68: 500 | L68: Living room | M68: Friends,By yourself | N68: Fall | O68: beef wellington | P68: A slow strumming of guitar. The vocalist, if there is one, has a mournful tone to their lyrics. The distant playing of drums. And at the end all the instruments start to fade. | Q68: =IF(E68="", "", LEFT(E68, 1) * 1) -> 5 | R68: =IF(F68="","",VALUE(LEFT(F68,FIND(" ",F68)-1))) -> 1 | S68: =IF(G68="","",VALUE(LEFT(G68,FIND(" ",G68)-1))) -> 3 | T68: =IF(H68="","",VALUE(LEFT(H68,FIND(" ",H68)-1))) -> 4 | U68: 500 | V68: =IF(L68="",0,IF(ISNUMBER(SEARCH("Bathroom",L68)),1,0)) -> 0 | W68: =IF(L68="",0,IF(ISNUMBER(SEARCH("Dining room",L68)),1,0)) -> 0 | X68: =IF(L68="",0,IF(ISNUMBER(SEARCH("Office",L68)),1,0)) -> 0 | Y68: =IF(L68="",0,IF(ISNUMBER(SEARCH("Bedroom",L68)),1,0)) -> 0 | Z68: =IF(L68="",0,IF(ISNUMBER(SEARCH("Living room",L68)),1,0)) -> 1 | AA68: =IF(M68="",0, IF(ISNUMBER(SEARCH("By yourself",M68)), 1, 0)) -> 1 | AB68: =IF(M68="", 0, IF(ISNUMBER(SEARCH("Friends", M68)), 1, 0)) -> 1 | AC68: =IF(M68="",0,IF(ISNUMBER(SEARCH("Family members", M68)), 1, 0)) -> 0 | AD68: =IF(M68="", 0, IF(ISNUMBER(SEARCH("Coworkers/Classmates", M68)), 1, 0)) -> 0 | AE68: =IF(M68="", 0, IF(ISNUMBER(SEARCH("Strangers", M68)), 1, 0)) -> 0 | AF68: =IF(N68="", 0, IF(ISNUMBER(SEARCH("Spring", N68)), 1, 0)) -> 0 | AG68: =IF(N68="", 0, IF(ISNUMBER(SEARCH("Summer", N68)), 1, 0)) -> 0 | AH68: =IF(N68="", 0, IF(ISNUMBER(SEARCH("Fall", N68)), 1, 0)) -> 1 | AI68: =IF(N68="", 0, IF(ISNUMBER(SEARCH("Winter", N68)), 1, 0)) -> 0
A69: 68 | B69: The Persistence of Memory | C69: 8 | D69: It makes me feel lonely and sad. | E69: 4 - Agree | F69: 1 - Strongly disagree | G69: 3 - Neutral/Unsure | H69: 4 - Agree | I69: 5 | J69: 7 | K69: 2000 | L69: Office | M69: By yourself | N69: Fall | O69: Pizza | P69: sad and dreary | Q69: =IF(E69="", "", LEFT(E69, 1) * 1) -> 4 | R69: =IF(F69="","",VALUE(LEFT(F69,FIND(" ",F69)-1))) -> 1 | S69: =IF(G69="","",VALUE(LEFT(G69,FIND(" ",G69)-1))) -> 3 | T69: =IF(H69="","",VALUE(LEFT(H69,FIND(" ",H69)-1))) -> 4 | U69: 2000 | V69: =IF(L69="",0,IF(ISNUMBER(SEARCH("Bathroom",L69)),1,0)) -> 0 | W69: =IF(L69="",0,IF(ISNUMBER(SEARCH("Dining room",L69)),1,0)) -> 0 | X69: =IF(L69="",0,IF(ISNUMBER(SEARCH("Office",L69)),1,0)) -> 1 | Y69: =IF(L69="",0,IF(ISNUMBER(SEARCH("Bedroom",L69)),1,0)) -> 0 | Z69: =IF(L69="",0,IF(ISNUMBER(SEARCH("Living room",L69)),1,0)) -> 0 | AA69: =IF(M69="",0, IF(ISNUMBER(SEARCH("By yourself",M69)), 1, 0)) -> 1 | AB69: =IF(M69="", 0, IF(ISNUMBER(SEARCH("Friends", M69)), 1, 0)) -> 0 | AC69: =IF(M69="",0,IF(ISNUMBER(SEARCH("Family members", M69)), 1, 0)) -> 0 | AD69: =IF(M69="", 0, IF(ISNUMBER(SEARCH("Coworkers/Classmates", M69)), 1, 0)) -> 0 | AE69: =IF(M69="", 0, IF(ISNUMBER(SEARCH("Strangers", M69)), 1, 0)) -> 0 | AF69: =IF(N69="", 0, IF(ISNUMBER(SEARCH("Spring", N69)), 1, 0)) -> 0 | AG69: =IF(N69="", 0, IF(ISNUMBER(SEARCH("Summer", N69)), 1, 0)) -> 0 | AH69: =IF(N69="", 0, IF(ISNUMBER(SEARCH("Fall", N69)), 1, 0)) -> 1 | AI69: =IF(N69="", 0, IF(ISNUMBER(SEARCH("Winter", N69)), 1, 0)) -> 0
A70: 69 | B70: The Persistence of Memory | C70: 8 | D70: The painting makes me feel that time is fading, and there's no hope left for the living species on earth since the horse (is it?) is almost dying. The clock, lying like a lump of mud on the table and hanging on a tree branch like a bathrobe, makes me feel that time already lost its meaning in this space. The empty space and dark colors made me feel oppressed. At the same time, the messy lines made me feel disordered. | E70: 5 - Strongly agree | F70: 2 - Disagree | G70: 2 - Disagree | H70: 5 - Strongly agree | I70: 4 | J70: 4 | K70: 6000000 | L70: Living room | M70: Friends | N70: Fall | O70: Crab. | P70: An indescribable sound of wind, accompanied by drumbeats without a fixed pattern. The deep sound of the piano is mixed with the faint sound of the violin. | Q70: =IF(E70="", "", LEFT(E70, 1) * 1) -> 5 | R70: =IF(F70="","",VALUE(LEFT(F70,FIND(" ",F70)-1))) -> 2 | S70: =IF(G70="","",VALUE(LEFT(G70,FIND(" ",G70)-1))) -> 2 | T70: =IF(H70="","",VALUE(LEFT(H70,FIND(" ",H70)-1))) -> 5 | U70: 6000000 | V70: =IF(L70="",0,IF(ISNUMBER(SEARCH("Bathroom",L70)),1,0)) -> 0 | W70: =IF(L70="",0,IF(ISNUMBER(SEARCH("Dining room",L70)),1,0)) -> 0 | X70: =IF(L70="",0,IF(ISNUMBER(SEARCH("Office",L70)),1,0)) -> 0 | Y70: =IF(L70="",0,IF(ISNUMBER(SEARCH("Bedroom",L70)),1,0)) -> 0 | Z70: =IF(L70="",0,IF(ISNUMBER(SEARCH("Living room",L70)),1,0)) -> 1 | AA70: =IF(M70="",0, IF(ISNUMBER(SEARCH("By yourself",M70)), 1, 0)) -> 0 | AB70: =IF(M70="", 0, IF(ISNUMBER(SEARCH("Friends", M70)), 1, 0)) -> 1 | AC70: =IF(M70="",0,IF(ISNUMBER(SEARCH("Family members", M70)), 1, 0)) -> 0 | AD70: =IF(M70="", 0, IF(ISNUMBER(SEARCH("Coworkers/Classmates", M70)), 1, 0)) -> 0 | AE70: =IF(M70="", 0, IF(ISNUMBER(SEARCH("Strangers", M70)), 1, 0)) -> 0 | AF70: =IF(N70="", 0, IF(ISNUMBER(SEARCH("Spring", N70)), 1, 0)) -> 0 | AG70: =IF(N70="", 0, IF(ISNUMBER(SEARCH("Summer", N70)), 1, 0)) -> 0 | AH70: =IF(N70="", 0, IF(ISNUMBER(SEARCH("Fall", N70)), 1, 0)) -> 1 | AI70: =IF(N70="", 0, IF(ISNUMBER(SEARCH("Winter", N70)), 1, 0)) -> 0
A71: 70 | B71: The Persistence of Memory | C71: 8 | D71: This picture makes me feel uneasy but also reflective. The melting clocks make time feel strange and unreliable, and the empty landscape feels sad and lonely. It's like telling us to beware that time is always ticking. | E71: 5 - Strongly agree | F71: 2 - Disagree | G71: 2 - Disagree | H71: 5 - Strongly agree | I71: 6 | J71: 6 | K71: 5 | L71: Bathroom | M71: Friends,Coworkers/Classmates,By yourself | N71: Fall | O71: Fried rice | P71: I imagine slow, echoing sounds with stretched notes and long pauses. The music would feel mellow and slightly unsettling, as if time is moving oddly and everything is suspended. | Q71: =IF(E71="", "", LEFT(E71, 1) * 1) -> 5 | R71: =IF(F71="","",VALUE(LEFT(F71,FIND(" ",F71)-1))) -> 2 | S71: =IF(G71="","",VALUE(LEFT(G71,FIND(" ",G71)-1))) -> 2 | T71: =IF(H71="","",VALUE(LEFT(H71,FIND(" ",H71)-1))) -> 5 | U71: 5 | V71: =IF(L71="",0,IF(ISNUMBER(SEARCH("Bathroom",L71)),1,0)) -> 1 | W71: =IF(L71="",0,IF(ISNUMBER(SEARCH("Dining room",L71)),1,0)) -> 0 | X71: =IF(L71="",0,IF(ISNUMBER(SEARCH("Office",L71)),1,0)) -> 0 | Y71: =IF(L71="",0,IF(ISNUMBER(SEARCH("Bedroom",L71)),1,0)) -> 0 | Z71: =IF(L71="",0,IF(ISNUMBER(SEARCH("Living room",L71)),1,0)) -> 0 | AA71: =IF(M71="",0, IF(ISNUMBER(SEARCH("By yourself",M71)), 1, 0)) -> 1 | AB71: =IF(M71="", 0, IF(ISNUMBER(SEARCH("Friends", M71)), 1, 0)) -> 1 | AC71: =IF(M71="",0,IF(ISNUMBER(SEARCH("Family members", M71)), 1, 0)) -> 0 | AD71: =IF(M71="", 0, IF(ISNUMBER(SEARCH("Coworkers/Classmates", M71)), 1, 0)) -> 1 | AE71: =IF(M71="", 0, IF(ISNUMBER(SEARCH("Strangers", M71)), 1, 0)) -> 0 | AF71: =IF(N71="", 0, IF(ISNUMBER(SEARCH("Spring", N71)), 1, 0)) -> 0 | AG71: =IF(N71="", 0, IF(ISNUMBER(SEARCH("Summer", N71)), 1, 0)) -> 0 | AH71: =IF(N71="", 0, IF(ISNUMBER(SEARCH("Fall", N71)), 1, 0)) -> 1 | AI71: =IF(N71="", 0, IF(ISNUMBER(SEARCH("Winter", N71)), 1, 0)) -> 0
A72: 71 | B72: The Persistence of Memory | C72: 6 | D72: eerie | E72: 4 - Agree | F72: 2 - Disagree | G72: 3 - Neutral/Unsure | H72: 5 - Strongly agree | I72: 4 | J72: 6 | K72: 10 | L72: Office,Living room | M72: By yourself | N72: Summer | O72: octopus | P72: slow, soft, sombre style | Q72: =IF(E72="", "", LEFT(E72, 1) * 1) -> 4 | R72: =IF(F72="","",VALUE(LEFT(F72,FIND(" ",F72)-1))) -> 2 | S72: =IF(G72="","",VALUE(LEFT(G72,FIND(" ",G72)-1))) -> 3 | T72: =IF(H72="","",VALUE(LEFT(H72,FIND(" ",H72)-1))) -> 5 | U72: 10 | V72: =IF(L72="",0,IF(ISNUMBER(SEARCH("Bathroom",L72)),1,0)) -> 0 | W72: =IF(L72="",0,IF(ISNUMBER(SEARCH("Dining room",L72)),1,0)) -> 0 | X72: =IF(L72="",0,IF(ISNUMBER(SEARCH("Office",L72)),1,0)) -> 1 | Y72: =IF(L72="",0,IF(ISNUMBER(SEARCH("Bedroom",L72)),1,0)) -> 0 | Z72: =IF(L72="",0,IF(ISNUMBER(SEARCH("Living room",L72)),1,0)) -> 1 | AA72: =IF(M72="",0, IF(ISNUMBER(SEARCH("By yourself",M72)), 1, 0)) -> 1 | AB72: =IF(M72="", 0, IF(ISNUMBER(SEARCH("Friends", M72)), 1, 0)) -> 0 | AC72: =IF(M72="",0,IF(ISNUMBER(SEARCH("Family members", M72)), 1, 0)) -> 0 | AD72: =IF(M72="", 0, IF(ISNUMBER(SEARCH("Coworkers/Classmates", M72)), 1, 0)) -> 0 | AE72: =IF(M72="", 0, IF(ISNUMBER(SEARCH("Strangers", M72)), 1, 0)) -> 0 | AF72: =IF(N72="", 0, IF(ISNUMBER(SEARCH("Spring", N72)), 1, 0)) -> 0 | AG72: =IF(N72="", 0, IF(ISNUMBER(SEARCH("Summer", N72)), 1, 0)) -> 1 | AH72: =IF(N72="", 0, IF(ISNUMBER(SEARCH("Fall", N72)), 1, 0)) -> 0 | AI72: =IF(N72="", 0, IF(ISNUMBER(SEARCH("Winter", N72)), 1, 0)) -> 0
A73: 72 | B73: The Persistence of Memory | C73: 8 | D73: This painting makes me feel calm. | E73: 2 - Disagree | F73: 4 - Agree | G73: 5 - Strongly agree | H73: 2 - Disagree | I73: 4 | J73: 5 | K73: I would pay 1000 dollars | L73: Bedroom,Bathroom,Living room,Dining room | M73: Friends,Family members,By yourself | N73: Spring,Summer | O73: a pizza | P73: A calm sountrack with a relaxing and laze inducing melody¬† | Q73: =IF(E73="", "", LEFT(E73, 1) * 1) -> 2 | R73: =IF(F73="","",VALUE(LEFT(F73,FIND(" ",F73)-1))) -> 4 | S73: =IF(G73="","",VALUE(LEFT(G73,FIND(" ",G73)-1))) -> 5 | T73: =IF(H73="","",VALUE(LEFT(H73,FIND(" ",H73)-1))) -> 2 | U73: 1000 | V73: =IF(L73="",0,IF(ISNUMBER(SEARCH("Bathroom",L73)),1,0)) -> 1 | W73: =IF(L73="",0,IF(ISNUMBER(SEARCH("Dining room",L73)),1,0)) -> 1 | X73: =IF(L73="",0,IF(ISNUMBER(SEARCH("Office",L73)),1,0)) -> 0 | Y73: =IF(L73="",0,IF(ISNUMBER(SEARCH("Bedroom",L73)),1,0)) -> 1 | Z73: =IF(L73="",0,IF(ISNUMBER(SEARCH("Living room",L73)),1,0)) -> 1 | AA73: =IF(M73="",0, IF(ISNUMBER(SEARCH("By yourself",M73)), 1, 0)) -> 1 | AB73: =IF(M73="", 0, IF(ISNUMBER(SEARCH("Friends", M73)), 1, 0)) -> 1 | AC73: =IF(M73="",0,IF(ISNUMBER(SEARCH("Family members", M73)), 1, 0)) -> 1 | AD73: =IF(M73="", 0, IF(ISNUMBER(SEARCH("Coworkers/Classmates", M73)), 1, 0)) -> 0 | AE73: =IF(M73="", 0, IF(ISNUMBER(SEARCH("Strangers", M73)), 1, 0)) -> 0 | AF73: =IF(N73="", 0, IF(ISNUMBER(SEARCH("Spring", N73)), 1, 0)) -> 1 | AG73: =IF(N73="", 0, IF(ISNUMBER(SEARCH("Summer", N73)), 1, 0)) -> 1 | AH73: =IF(N73="", 0, IF(ISNUMBER(SEARCH("Fall", N73)), 1, 0)) -> 0 | AI73: =IF(N73="", 0, IF(ISNUMBER(SEARCH("Winter", N73)), 1, 0)) -> 0
A74: 73 | B74: The Persistence of Memory | C74: 5 | D74: Surreal and sluggish as if everything is melting and slowing down | E74: 5 - Strongly agree | F74: 1 - Strongly disagree | G74: 1 - Strongly disagree | H74: 4 - Agree | I74: 7 | J74: 7 | K74: 10000000 | L74: Bedroom,Bathroom,Office,Living room,Dining room | M74: Friends,Family members,Coworkers/Classmates | N74: Fall | O74: melted cheese | P74: slow and slurry bass sounds with irregular rhythm | Q74: =IF(E74="", "", LEFT(E74, 1) * 1) -> 5 | R74: =IF(F74="","",VALUE(LEFT(F74,FIND(" ",F74)-1))) -> 1 | S74: =IF(G74="","",VALUE(LEFT(G74,FIND(" ",G74)-1))) -> 1 | T74: =IF(H74="","",VALUE(LEFT(H74,FIND(" ",H74)-1))) -> 4 | U74: 10000000 | V74: =IF(L74="",0,IF(ISNUMBER(SEARCH("Bathroom",L74)),1,0)) -> 1 | W74: =IF(L74="",0,IF(ISNUMBER(SEARCH("Dining room",L74)),1,0)) -> 1 | X74: =IF(L74="",0,IF(ISNUMBER(SEARCH("Office",L74)),1,0)) -> 1 | Y74: =IF(L74="",0,IF(ISNUMBER(SEARCH("Bedroom",L74)),1,0)) -> 1 | Z74: =IF(L74="",0,IF(ISNUMBER(SEARCH("Living room",L74)),1,0)) -> 1 | AA74: =IF(M74="",0, IF(ISNUMBER(SEARCH("By yourself",M74)), 1, 0)) -> 0 | AB74: =IF(M74="", 0, IF(ISNUMBER(SEARCH("Friends", M74)), 1, 0)) -> 1 | AC74: =IF(M74="",0,IF(ISNUMBER(SEARCH("Family members", M74)), 1, 0)) -> 1 | AD74: =IF(M74="", 0, IF(ISNUMBER(SEARCH("Coworkers/Classmates", M74)), 1, 0)) -> 1 | AE74: =IF(M74="", 0, IF(ISNUMBER(SEARCH("Strangers", M74)), 1, 0)) -> 0 | AF74: =IF(N74="", 0, IF(ISNUMBER(SEARCH("Spring", N74)), 1, 0)) -> 0 | AG74: =IF(N74="", 0, IF(ISNUMBER(SEARCH("Summer", N74)), 1, 0)) -> 0 | AH74: =IF(N74="", 0, IF(ISNUMBER(SEARCH("Fall", N74)), 1, 0)) -> 1 | AI74: =IF(N74="", 0, IF(ISNUMBER(SEARCH("Winter", N74)), 1, 0)) -> 0
A75: 74 | B75: The Persistence of Memory | C75: 8 | D75: I feel a sense of quiet isolation. The vast, empty landscape and the stillness of the water create a very calm atmosphere, despite the strange objects. It makes me feel lonely, as if I am the only person left in a world where time has stopped moving. | E75: 1 - Strongly disagree | F75: 3 - Neutral/Unsure | G75: 3 - Neutral/Unsure | H75: 4 - Agree | I75: 14 | J75: 10 | K75: 30000000 | L75: Office | M75: Friends,By yourself | N75: Fall | O75: noodle | P75: A very low-pitched voice, with a hollow quality. At the same time, the sound is sluggish. | Q75: =IF(E75="", "", LEFT(E75, 1) * 1) -> 1 | R75: =IF(F75="","",VALUE(LEFT(F75,FIND(" ",F75)-1))) -> 3 | S75: =IF(G75="","",VALUE(LEFT(G75,FIND(" ",G75)-1))) -> 3 | T75: =IF(H75="","",VALUE(LEFT(H75,FIND(" ",H75)-1))) -> 4 | U75: 30000000 | V75: =IF(L75="",0,IF(ISNUMBER(SEARCH("Bathroom",L75)),1,0)) -> 0 | W75: =IF(L75="",0,IF(ISNUMBER(SEARCH("Dining room",L75)),1,0)) -> 0 | X75: =IF(L75="",0,IF(ISNUMBER(SEARCH("Office",L75)),1,0)) -> 1 | Y75: =IF(L75="",0,IF(ISNUMBER(SEARCH("Bedroom",L75)),1,0)) -> 0 | Z75: =IF(L75="",0,IF(ISNUMBER(SEARCH("Living room",L75)),1,0)) -> 0 | AA75: =IF(M75="",0, IF(ISNUMBER(SEARCH("By yourself",M75)), 1, 0)) -> 1 | AB75: =IF(M75="", 0, IF(ISNUMBER(SEARCH("Friends", M75)), 1, 0)) -> 1 | AC75: =IF(M75="",0,IF(ISNUMBER(SEARCH("Family members", M75)), 1, 0)) -> 0 | AD75: =IF(M75="", 0, IF(ISNUMBER(SEARCH("Coworkers/Classmates", M75)), 1, 0)) -> 0 | AE75: =IF(M75="", 0, IF(ISNUMBER(SEARCH("Strangers", M75)), 1, 0)) -> 0 | AF75: =IF(N75="", 0, IF(ISNUMBER(SEARCH("Spring", N75)), 1, 0)) -> 0 | AG75: =IF(N75="", 0, IF(ISNUMBER(SEARCH("Summer", N75)), 1, 0)) -> 0 | AH75: =IF(N75="", 0, IF(ISNUMBER(SEARCH("Fall", N75)), 1, 0)) -> 1 | AI75: =IF(N75="", 0, IF(ISNUMBER(SEARCH("Winter", N75)), 1, 0)) -> 0
A76: 75 | B76: The Persistence of Memory | C76: 9 | D76: weird, not sure what meaning does it want to convey, terrible, distortion. | E76: 4 - Agree | F76: 1 - Strongly disagree | G76: 1 - Strongly disagree | H76: 5 - Strongly agree | I76: 4 | J76: 8 | K76: 0 | L76: Living room | M76: By yourself | N76: Winter | O76: Ginger | P76: The metallic sound mingled with coldness, distortion, dissonance, and emptiness. | Q76: =IF(E76="", "", LEFT(E76, 1) * 1) -> 4 | R76: =IF(F76="","",VALUE(LEFT(F76,FIND(" ",F76)-1))) -> 1 | S76: =IF(G76="","",VALUE(LEFT(G76,FIND(" ",G76)-1))) -> 1 | T76: =IF(H76="","",VALUE(LEFT(H76,FIND(" ",H76)-1))) -> 5 | U76: 0 | V76: =IF(L76="",0,IF(ISNUMBER(SEARCH("Bathroom",L76)),1,0)) -> 0 | W76: =IF(L76="",0,IF(ISNUMBER(SEARCH("Dining room",L76)),1,0)) -> 0 | X76: =IF(L76="",0,IF(ISNUMBER(SEARCH("Office",L76)),1,0)) -> 0 | Y76: =IF(L76="",0,IF(ISNUMBER(SEARCH("Bedroom",L76)),1,0)) -> 0 | Z76: =IF(L76="",0,IF(ISNUMBER(SEARCH("Living room",L76)),1,0)) -> 1 | AA76: =IF(M76="",0, IF(ISNUMBER(SEARCH("By yourself",M76)), 1, 0)) -> 1 | AB76: =IF(M76="", 0, IF(ISNUMBER(SEARCH("Friends", M76)), 1, 0)) -> 0 | AC76: =IF(M76="",0,IF(ISNUMBER(SEARCH("Family members", M76)), 1, 0)) -> 0 | AD76: =IF(M76="", 0, IF(ISNUMBER(SEARCH("Coworkers/Classmates", M76)), 1, 0)) -> 0 | AE76: =IF(M76="", 0, IF(ISNUMBER(SEARCH("Strangers", M76)), 1, 0)) -> 0 | AF76: =IF(N76="", 0, IF(ISNUMBER(SEARCH("Spring", N76)), 1, 0)) -> 0 | AG76: =IF(N76="", 0, IF(ISNUMBER(SEARCH("Summer", N76)), 1, 0)) -> 0 | AH76: =IF(N76="", 0, IF(ISNUMBER(SEARCH("Fall", N76)), 1, 0)) -> 0 | AI76: =IF(N76="", 0, IF(ISNUMBER(SEARCH("Winter", N76)), 1, 0)) -> 1
A77: 76 | B77: The Persistence of Memory | C77: 9 | D77: This painting makes me feel sad, clocks usually represent time, and it looks like the time is ending. It seems tired and sad. | E77: 5 - Strongly agree | F77: 1 - Strongly disagree | G77: 3 - Neutral/Unsure | H77: 4 - Agree | I77: 4 | J77: 4 | K77: I would pay 10,000 CAD for that painting. | L77: Living room | M77: Friends,Coworkers/Classmates | N77: Fall | O77: Like a burnt soup. | P77: It must be a slow pace soundtrack and deep. | Q77: =IF(E77="", "", LEFT(E77, 1) * 1) -> 5 | R77: =IF(F77="","",VALUE(LEFT(F77,FIND(" ",F77)-1))) -> 1 | S77: =IF(G77="","",VALUE(LEFT(G77,FIND(" ",G77)-1))) -> 3 | T77: =IF(H77="","",VALUE(LEFT(H77,FIND(" ",H77)-1))) -> 4 | U77: 10000 | V77: =IF(L77="",0,IF(ISNUMBER(SEARCH("Bathroom",L77)),1,0)) -> 0 | W77: =IF(L77="",0,IF(ISNUMBER(SEARCH("Dining room",L77)),1,0)) -> 0 | X77: =IF(L77="",0,IF(ISNUMBER(SEARCH("Office",L77)),1,0)) -> 0 | Y77: =IF(L77="",0,IF(ISNUMBER(SEARCH("Bedroom",L77)),1,0)) -> 0 | Z77: =IF(L77="",0,IF(ISNUMBER(SEARCH("Living room",L77)),1,0)) -> 1 | AA77: =IF(M77="",0, IF(ISNUMBER(SEARCH("By yourself",M77)), 1, 0)) -> 0 | AB77: =IF(M77="", 0, IF(ISNUMBER(SEARCH("Friends", M77)), 1, 0)) -> 1 | AC77: =IF(M77="",0,IF(ISNUMBER(SEARCH("Family members", M77)), 1, 0)) -> 0 | AD77: =IF(M77="", 0, IF(ISNUMBER(SEARCH("Coworkers/Classmates", M77)), 1, 0)) -> 1 | AE77: =IF(M77="", 0, IF(ISNUMBER(SEARCH("Strangers", M77)), 1, 0)) -> 0 | AF77: =IF(N77="", 0, IF(ISNUMBER(SEARCH("Spring", N77)), 1, 0)) -> 0 | AG77: =IF(N77="", 0, IF(ISNUMBER(SEARCH("Summer", N77)), 1, 0)) -> 0 | AH77: =IF(N77="", 0, IF(ISNUMBER(SEARCH("Fall", N77)), 1, 0)) -> 1 | AI77: =IF(N77="", 0, IF(ISNUMBER(SEARCH("Winter", N77)), 1, 0)) -> 0
A78: 77 | B78: The Persistence of Memory | C78: 7 | D78: Time is wasted | E78: 4 - Agree | F78: 2 - Disagree | G78: 4 - Agree | H78: 4 - Agree | I78: 4 | J78: 4 | K78: 15 | L78: Bathroom | M78: By yourself | N78: Fall | O78: Apple | P78: Instrumental | Q78: =IF(E78="", "", LEFT(E78, 1) * 1) -> 4 | R78: =IF(F78="","",VALUE(LEFT(F78,FIND(" ",F78)-1))) -> 2 | S78: =IF(G78="","",VALUE(LEFT(G78,FIND(" ",G78)-1))) -> 4 | T78: =IF(H78="","",VALUE(LEFT(H78,FIND(" ",H78)-1))) -> 4 | U78: 15 | V78: =IF(L78="",0,IF(ISNUMBER(SEARCH("Bathroom",L78)),1,0)) -> 1 | W78: =IF(L78="",0,IF(ISNUMBER(SEARCH("Dining room",L78)),1,0)) -> 0 | X78: =IF(L78="",0,IF(ISNUMBER(SEARCH("Office",L78)),1,0)) -> 0 | Y78: =IF(L78="",0,IF(ISNUMBER(SEARCH("Bedroom",L78)),1,0)) -> 0 | Z78: =IF(L78="",0,IF(ISNUMBER(SEARCH("Living room",L78)),1,0)) -> 0 | AA78: =IF(M78="",0, IF(ISNUMBER(SEARCH("By yourself",M78)), 1, 0)) -> 1 | AB78: =IF(M78="", 0, IF(ISNUMBER(SEARCH("Friends", M78)), 1, 0)) -> 0 | AC78: =IF(M78="",0,IF(ISNUMBER(SEARCH("Family members", M78)), 1, 0)) -> 0 | AD78: =IF(M78="", 0, IF(ISNUMBER(SEARCH("Coworkers/Classmates", M78)), 1, 0)) -> 0 | AE78: =IF(M78="", 0, IF(ISNUMBER(SEARCH("Strangers", M78)), 1, 0)) -> 0 | AF78: =IF(N78="", 0, IF(ISNUMBER(SEARCH("Spring", N78)), 1, 0)) -> 0 | AG78: =IF(N78="", 0, IF(ISNUMBER(SEARCH("Summer", N78)), 1, 0)) -> 0 | AH78: =IF(N78="", 0, IF(ISNUMBER(SEARCH("Fall", N78)), 1, 0)) -> 1 | AI78: =IF(N78="", 0, IF(ISNUMBER(SEARCH("Winter", N78)), 1, 0)) -> 0
A79: 78 | B79: The Persistence of Memory | C79: 7 | D79: It makes me feel warm and sad. Because the light seems warm but the melting clocks and shadow(darkness) seems a bit cold and sad. | E79: 4 - Agree | F79: 2 - Disagree | G79: 4 - Agree | H79: 4 - Agree | I79: 5 | J79: 9 | K79: 10000 | L79: Office | M79: By yourself | N79: Winter | O79: Iced American a little while ago | P79: Sam Smith ‚Äì Too Good at Goodbyes ¬† | Q79: =IF(E79="", "", LEFT(E79, 1) * 1) -> 4 | R79: =IF(F79="","",VALUE(LEFT(F79,FIND(" ",F79)-1))) -> 2 | S79: =IF(G79="","",VALUE(LEFT(G79,FIND(" ",G79)-1))) -> 4 | T79: =IF(H79="","",VALUE(LEFT(H79,FIND(" ",H79)-1))) -> 4 | U79: 10000 | V79: =IF(L79="",0,IF(ISNUMBER(SEARCH("Bathroom",L79)),1,0)) -> 0 | W79: =IF(L79="",0,IF(ISNUMBER(SEARCH("Dining room",L79)),1,0)) -> 0 | X79: =IF(L79="",0,IF(ISNUMBER(SEARCH("Office",L79)),1,0)) -> 1 | Y79: =IF(L79="",0,IF(ISNUMBER(SEARCH("Bedroom",L79)),1,0)) -> 0 | Z79: =IF(L79="",0,IF(ISNUMBER(SEARCH("Living room",L79)),1,0)) -> 0 | AA79: =IF(M79="",0, IF(ISNUMBER(SEARCH("By yourself",M79)), 1, 0)) -> 1 | AB79: =IF(M79="", 0, IF(ISNUMBER(SEARCH("Friends", M79)), 1, 0)) -> 0 | AC79: =IF(M79="",0,IF(ISNUMBER(SEARCH("Family members", M79)), 1, 0)) -> 0 | AD79: =IF(M79="", 0, IF(ISNUMBER(SEARCH("Coworkers/Classmates", M79)), 1, 0)) -> 0 | AE79: =IF(M79="", 0, IF(ISNUMBER(SEARCH("Strangers", M79)), 1, 0)) -> 0 | AF79: =IF(N79="", 0, IF(ISNUMBER(SEARCH("Spring", N79)), 1, 0)) -> 0 | AG79: =IF(N79="", 0, IF(ISNUMBER(SEARCH("Summer", N79)), 1, 0)) -> 0 | AH79: =IF(N79="", 0, IF(ISNUMBER(SEARCH("Fall", N79)), 1, 0)) -> 0 | AI79: =IF(N79="", 0, IF(ISNUMBER(SEARCH("Winter", N79)), 1, 0)) -> 1
A80: 79 | B80: The Persistence of Memory | C80: 7 | D80: This painting makes me feel calm and uneasy, it let me feel the time is going through anywhere. The distort clock let me rethink the meaning of time differs from people to people. | E80: 3 - Neutral/Unsure | F80: 3 - Neutral/Unsure | G80: 4 - Agree | H80: 4 - Agree | I80: 3 | J80: 5 | K80: 1000000$ | L80: Office | M80: By yourself | N80: Fall | O80: wine. | P80: The soundtrack will be peaceful, but we will be able to hear the rhythm like time passing, which like going through thousands of years. | Q80: =IF(E80="", "", LEFT(E80, 1) * 1) -> 3 | R80: =IF(F80="","",VALUE(LEFT(F80,FIND(" ",F80)-1))) -> 3 | S80: =IF(G80="","",VALUE(LEFT(G80,FIND(" ",G80)-1))) -> 4 | T80: =IF(H80="","",VALUE(LEFT(H80,FIND(" ",H80)-1))) -> 4 | U80: 1000000 | V80: =IF(L80="",0,IF(ISNUMBER(SEARCH("Bathroom",L80)),1,0)) -> 0 | W80: =IF(L80="",0,IF(ISNUMBER(SEARCH("Dining room",L80)),1,0)) -> 0 | X80: =IF(L80="",0,IF(ISNUMBER(SEARCH("Office",L80)),1,0)) -> 1 | Y80: =IF(L80="",0,IF(ISNUMBER(SEARCH("Bedroom",L80)),1,0)) -> 0 | Z80: =IF(L80="",0,IF(ISNUMBER(SEARCH("Living room",L80)),1,0)) -> 0 | AA80: =IF(M80="",0, IF(ISNUMBER(SEARCH("By yourself",M80)), 1, 0)) -> 1 | AB80: =IF(M80="", 0, IF(ISNUMBER(SEARCH("Friends", M80)), 1, 0)) -> 0 | AC80: =IF(M80="",0,IF(ISNUMBER(SEARCH("Family members", M80)), 1, 0)) -> 0 | AD80: =IF(M80="", 0, IF(ISNUMBER(SEARCH("Coworkers/Classmates", M80)), 1, 0)) -> 0 | AE80: =IF(M80="", 0, IF(ISNUMBER(SEARCH("Strangers", M80)), 1, 0)) -> 0 | AF80: =IF(N80="", 0, IF(ISNUMBER(SEARCH("Spring", N80)), 1, 0)) -> 0 | AG80: =IF(N80="", 0, IF(ISNUMBER(SEARCH("Summer", N80)), 1, 0)) -> 0 | AH80: =IF(N80="", 0, IF(ISNUMBER(SEARCH("Fall", N80)), 1, 0)) -> 1 | AI80: =IF(N80="", 0, IF(ISNUMBER(SEARCH("Winter", N80)), 1, 0)) -> 0
A81: 80 | B81: The Persistence of Memory | C81: 9 | D81: sad¬† tired¬† feels depressing and lonely¬† hopeless running out of time¬† no hope left | E81: 4 - Agree | F81: 2 - Disagree | G81: 2 - Disagree | H81: 4 - Agree | I81: 5 | J81: 6 | K81: 50 | L81: Bathroom,Office,Living room,Dining room | M81: Strangers,By yourself | N81: Fall,Winter | O81: burnt toast | P81: very sad and melancholic¬† slow tempo with violins playing sadly in background¬† womp womp | Q81: =IF(E81="", "", LEFT(E81, 1) * 1) -> 4 | R81: =IF(F81="","",VALUE(LEFT(F81,FIND(" ",F81)-1))) -> 2 | S81: =IF(G81="","",VALUE(LEFT(G81,FIND(" ",G81)-1))) -> 2 | T81: =IF(H81="","",VALUE(LEFT(H81,FIND(" ",H81)-1))) -> 4 | U81: 50 | V81: =IF(L81="",0,IF(ISNUMBER(SEARCH("Bathroom",L81)),1,0)) -> 1 | W81: =IF(L81="",0,IF(ISNUMBER(SEARCH("Dining room",L81)),1,0)) -> 1 | X81: =IF(L81="",0,IF(ISNUMBER(SEARCH("Office",L81)),1,0)) -> 1 | Y81: =IF(L81="",0,IF(ISNUMBER(SEARCH("Bedroom",L81)),1,0)) -> 0 | Z81: =IF(L81="",0,IF(ISNUMBER(SEARCH("Living room",L81)),1,0)) -> 1 | AA81: =IF(M81="",0, IF(ISNUMBER(SEARCH("By yourself",M81)), 1, 0)) -> 1 | AB81: =IF(M81="", 0, IF(ISNUMBER(SEARCH("Friends", M81)), 1, 0)) -> 0 | AC81: =IF(M81="",0,IF(ISNUMBER(SEARCH("Family members", M81)), 1, 0)) -> 0 | AD81: =IF(M81="", 0, IF(ISNUMBER(SEARCH("Coworkers/Classmates", M81)), 1, 0)) -> 0 | AE81: =IF(M81="", 0, IF(ISNUMBER(SEARCH("Strangers", M81)), 1, 0)) -> 1 | AF81: =IF(N81="", 0, IF(ISNUMBER(SEARCH("Spring", N81)), 1, 0)) -> 0 | AG81: =IF(N81="", 0, IF(ISNUMBER(SEARCH("Summer", N81)), 1, 0)) -> 0 | AH81: =IF(N81="", 0, IF(ISNUMBER(SEARCH("Fall", N81)), 1, 0)) -> 1 | AI81: =IF(N81="", 0, IF(ISNUMBER(SEARCH("Winter", N81)), 1, 0)) -> 1
A82: 81 | B82: The Persistence of Memory | C82: 6 | D82: makes me feel uncomfortable knowing that time is passing.¬† | E82: 4 - Agree | F82: 2 - Disagree | G82: 3 - Neutral/Unsure | H82: 4 - Agree | I82: 3 | J82: 5 | K82: 200 CAD | L82: Office,Living room | M82: By yourself | N82: Summer | O82: spaghetti | P82: A tame impala album | Q82: =IF(E82="", "", LEFT(E82, 1) * 1) -> 4 | R82: =IF(F82="","",VALUE(LEFT(F82,FIND(" ",F82)-1))) -> 2 | S82: =IF(G82="","",VALUE(LEFT(G82,FIND(" ",G82)-1))) -> 3 | T82: =IF(H82="","",VALUE(LEFT(H82,FIND(" ",H82)-1))) -> 4 | U82: 200 | V82: =IF(L82="",0,IF(ISNUMBER(SEARCH("Bathroom",L82)),1,0)) -> 0 | W82: =IF(L82="",0,IF(ISNUMBER(SEARCH("Dining room",L82)),1,0)) -> 0 | X82: =IF(L82="",0,IF(ISNUMBER(SEARCH("Office",L82)),1,0)) -> 1 | Y82: =IF(L82="",0,IF(ISNUMBER(SEARCH("Bedroom",L82)),1,0)) -> 0 | Z82: =IF(L82="",0,IF(ISNUMBER(SEARCH("Living room",L82)),1,0)) -> 1 | AA82: =IF(M82="",0, IF(ISNUMBER(SEARCH("By yourself",M82)), 1, 0)) -> 1 | AB82: =IF(M82="", 0, IF(ISNUMBER(SEARCH("Friends", M82)), 1, 0)) -> 0 | AC82: =IF(M82="",0,IF(ISNUMBER(SEARCH("Family members", M82)), 1, 0)) -> 0 | AD82: =IF(M82="", 0, IF(ISNUMBER(SEARCH("Coworkers/Classmates", M82)), 1, 0)) -> 0 | AE82: =IF(M82="", 0, IF(ISNUMBER(SEARCH("Strangers", M82)), 1, 0)) -> 0 | AF82: =IF(N82="", 0, IF(ISNUMBER(SEARCH("Spring", N82)), 1, 0)) -> 0 | AG82: =IF(N82="", 0, IF(ISNUMBER(SEARCH("Summer", N82)), 1, 0)) -> 1 | AH82: =IF(N82="", 0, IF(ISNUMBER(SEARCH("Fall", N82)), 1, 0)) -> 0 | AI82: =IF(N82="", 0, IF(ISNUMBER(SEARCH("Winter", N82)), 1, 0)) -> 0
A83: 82 | B83: The Persistence of Memory | C83: 6 | D83: This painting makes me feel a little confused, but also quiet and calm. The melting clocks make time feel strange and unreal, like it doesn‚Äôt follow normal rules. The empty background feels lonely, which makes me think about time passing and how memories can fade. Overall, it feels like a dream that is slow and silent. | E83: 4 - Agree | F83: 3 - Neutral/Unsure | G83: 4 - Agree | H83: 4 - Agree | I83: 5 | J83: 5 | K83: 10 | L83: Office | M83: By yourself | N83: Fall | O83: A piece of pizza left out too long. | P83: The soundtrack would be slow and very quiet, with long pauses between sounds. Soft, stretched notes would drift in and out, like they‚Äôre bending and fading before fully settling. The tempo would feel uncertain, never quite steady, making it hard to tell where one moment ends and the next begins. | Q83: =IF(E83="", "", LEFT(E83, 1) * 1) -> 4 | R83: =IF(F83="","",VALUE(LEFT(F83,FIND(" ",F83)-1))) -> 3 | S83: =IF(G83="","",VALUE(LEFT(G83,FIND(" ",G83)-1))) -> 4 | T83: =IF(H83="","",VALUE(LEFT(H83,FIND(" ",H83)-1))) -> 4 | U83: 10 | V83: =IF(L83="",0,IF(ISNUMBER(SEARCH("Bathroom",L83)),1,0)) -> 0 | W83: =IF(L83="",0,IF(ISNUMBER(SEARCH("Dining room",L83)),1,0)) -> 0 | X83: =IF(L83="",0,IF(ISNUMBER(SEARCH("Office",L83)),1,0)) -> 1 | Y83: =IF(L83="",0,IF(ISNUMBER(SEARCH("Bedroom",L83)),1,0)) -> 0 | Z83: =IF(L83="",0,IF(ISNUMBER(SEARCH("Living room",L83)),1,0)) -> 0 | AA83: =IF(M83="",0, IF(ISNUMBER(SEARCH("By yourself",M83)), 1, 0)) -> 1 | AB83: =IF(M83="", 0, IF(ISNUMBER(SEARCH("Friends", M83)), 1, 0)) -> 0 | AC83: =IF(M83="",0,IF(ISNUMBER(SEARCH("Family members", M83)), 1, 0)) -> 0 | AD83: =IF(M83="", 0, IF(ISNUMBER(SEARCH("Coworkers/Classmates", M83)), 1, 0)) -> 0 | AE83: =IF(M83="", 0, IF(ISNUMBER(SEARCH("Strangers", M83)), 1, 0)) -> 0 | AF83: =IF(N83="", 0, IF(ISNUMBER(SEARCH("Spring", N83)), 1, 0)) -> 0 | AG83: =IF(N83="", 0, IF(ISNUMBER(SEARCH("Summer", N83)), 1, 0)) -> 0 | AH83: =IF(N83="", 0, IF(ISNUMBER(SEARCH("Fall", N83)), 1, 0)) -> 1 | AI83: =IF(N83="", 0, IF(ISNUMBER(SEARCH("Winter", N83)), 1, 0)) -> 0
A84: 83 | B84: The Persistence of Memory | C84: 8 | D84: It makes me feel uneasy and disoriented. It depresses me.¬† | E84: 4 - Agree | F84: 1 - Strongly disagree | G84: 1 - Strongly disagree | H84: 5 - Strongly agree | I84: 3 | J84: 3 | K84: 1000 | L84: Living room | M84: By yourself | N84: Fall,Winter | O84: A cold and tasteless soup | P84: A slow and calm music, yet there's sadness or darkness in it. It gives the listener uneasiness.¬† | Q84: =IF(E84="", "", LEFT(E84, 1) * 1) -> 4 | R84: =IF(F84="","",VALUE(LEFT(F84,FIND(" ",F84)-1))) -> 1 | S84: =IF(G84="","",VALUE(LEFT(G84,FIND(" ",G84)-1))) -> 1 | T84: =IF(H84="","",VALUE(LEFT(H84,FIND(" ",H84)-1))) -> 5 | U84: 1000 | V84: =IF(L84="",0,IF(ISNUMBER(SEARCH("Bathroom",L84)),1,0)) -> 0 | W84: =IF(L84="",0,IF(ISNUMBER(SEARCH("Dining room",L84)),1,0)) -> 0 | X84: =IF(L84="",0,IF(ISNUMBER(SEARCH("Office",L84)),1,0)) -> 0 | Y84: =IF(L84="",0,IF(ISNUMBER(SEARCH("Bedroom",L84)),1,0)) -> 0 | Z84: =IF(L84="",0,IF(ISNUMBER(SEARCH("Living room",L84)),1,0)) -> 1 | AA84: =IF(M84="",0, IF(ISNUMBER(SEARCH("By yourself",M84)), 1, 0)) -> 1 | AB84: =IF(M84="", 0, IF(ISNUMBER(SEARCH("Friends", M84)), 1, 0)) -> 0 | AC84: =IF(M84="",0,IF(ISNUMBER(SEARCH("Family members", M84)), 1, 0)) -> 0 | AD84: =IF(M84="", 0, IF(ISNUMBER(SEARCH("Coworkers/Classmates", M84)), 1, 0)) -> 0 | AE84: =IF(M84="", 0, IF(ISNUMBER(SEARCH("Strangers", M84)), 1, 0)) -> 0 | AF84: =IF(N84="", 0, IF(ISNUMBER(SEARCH("Spring", N84)), 1, 0)) -> 0 | AG84: =IF(N84="", 0, IF(ISNUMBER(SEARCH("Summer", N84)), 1, 0)) -> 0 | AH84: =IF(N84="", 0, IF(ISNUMBER(SEARCH("Fall", N84)), 1, 0)) -> 1 | AI84: =IF(N84="", 0, IF(ISNUMBER(SEARCH("Winter", N84)), 1, 0)) -> 1
A85: 84 | B85: The Persistence of Memory | C85: 5 | D85: this painting makes me feel like time is a warped concept as per the warped clocks. | E85: 3 - Neutral/Unsure | F85: 2 - Disagree | G85: 2 - Disagree | H85: 3 - Neutral/Unsure | I85: 2 | J85: 5 | K85: 100 | L85: Living room | M85: Friends | N85: Fall | O85: carrot | P85: smooth jazz | Q85: =IF(E85="", "", LEFT(E85, 1) * 1) -> 3 | R85: =IF(F85="","",VALUE(LEFT(F85,FIND(" ",F85)-1))) -> 2 | S85: =IF(G85="","",VALUE(LEFT(G85,FIND(" ",G85)-1))) -> 2 | T85: =IF(H85="","",VALUE(LEFT(H85,FIND(" ",H85)-1))) -> 3 | U85: 100 | V85: =IF(L85="",0,IF(ISNUMBER(SEARCH("Bathroom",L85)),1,0)) -> 0 | W85: =IF(L85="",0,IF(ISNUMBER(SEARCH("Dining room",L85)),1,0)) -> 0 | X85: =IF(L85="",0,IF(ISNUMBER(SEARCH("Office",L85)),1,0)) -> 0 | Y85: =IF(L85="",0,IF(ISNUMBER(SEARCH("Bedroom",L85)),1,0)) -> 0 | Z85: =IF(L85="",0,IF(ISNUMBER(SEARCH("Living room",L85)),1,0)) -> 1 | AA85: =IF(M85="",0, IF(ISNUMBER(SEARCH("By yourself",M85)), 1, 0)) -> 0 | AB85: =IF(M85="", 0, IF(ISNUMBER(SEARCH("Friends", M85)), 1, 0)) -> 1 | AC85: =IF(M85="",0,IF(ISNUMBER(SEARCH("Family members", M85)), 1, 0)) -> 0 | AD85: =IF(M85="", 0, IF(ISNUMBER(SEARCH("Coworkers/Classmates", M85)), 1, 0)) -> 0 | AE85: =IF(M85="", 0, IF(ISNUMBER(SEARCH("Strangers", M85)), 1, 0)) -> 0 | AF85: =IF(N85="", 0, IF(ISNUMBER(SEARCH("Spring", N85)), 1, 0)) -> 0 | AG85: =IF(N85="", 0, IF(ISNUMBER(SEARCH("Summer", N85)), 1, 0)) -> 0 | AH85: =IF(N85="", 0, IF(ISNUMBER(SEARCH("Fall", N85)), 1, 0)) -> 1 | AI85: =IF(N85="", 0, IF(ISNUMBER(SEARCH("Winter", N85)), 1, 0)) -> 0
A86: 85 | B86: The Persistence of Memory | C86: 7 | D86: The colors chosen in this painting makes me feel dull and a little uneasy. | E86: 5 - Strongly agree | F86: 2 - Disagree | G86: 2 - Disagree | H86: 4 - Agree | I86: 1 | J86: 4 | K86: 2500 | L86: Office,Living room | M86: Coworkers/Classmates,By yourself | N86: Fall | O86: soup | P86: The soundtrack is a slow-burning, mix of soft strings and pulsing synths that creates a suspenseful, haunting mood. | Q86: =IF(E86="", "", LEFT(E86, 1) * 1) -> 5 | R86: =IF(F86="","",VALUE(LEFT(F86,FIND(" ",F86)-1))) -> 2 | S86: =IF(G86="","",VALUE(LEFT(G86,FIND(" ",G86)-1))) -> 2 | T86: =IF(H86="","",VALUE(LEFT(H86,FIND(" ",H86)-1))) -> 4 | U86: 2500 | V86: =IF(L86="",0,IF(ISNUMBER(SEARCH("Bathroom",L86)),1,0)) -> 0 | W86: =IF(L86="",0,IF(ISNUMBER(SEARCH("Dining room",L86)),1,0)) -> 0 | X86: =IF(L86="",0,IF(ISNUMBER(SEARCH("Office",L86)),1,0)) -> 1 | Y86: =IF(L86="",0,IF(ISNUMBER(SEARCH("Bedroom",L86)),1,0)) -> 0 | Z86: =IF(L86="",0,IF(ISNUMBER(SEARCH("Living room",L86)),1,0)) -> 1 | AA86: =IF(M86="",0, IF(ISNUMBER(SEARCH("By yourself",M86)), 1, 0)) -> 1 | AB86: =IF(M86="", 0, IF(ISNUMBER(SEARCH("Friends", M86)), 1, 0)) -> 0 | AC86: =IF(M86="",0,IF(ISNUMBER(SEARCH("Family members", M86)), 1, 0)) -> 0 | AD86: =IF(M86="", 0, IF(ISNUMBER(SEARCH("Coworkers/Classmates", M86)), 1, 0)) -> 1 | AE86: =IF(M86="", 0, IF(ISNUMBER(SEARCH("Strangers", M86)), 1, 0)) -> 0 | AF86: =IF(N86="", 0, IF(ISNUMBER(SEARCH("Spring", N86)), 1, 0)) -> 0 | AG86: =IF(N86="", 0, IF(ISNUMBER(SEARCH("Summer", N86)), 1, 0)) -> 0 | AH86: =IF(N86="", 0, IF(ISNUMBER(SEARCH("Fall", N86)), 1, 0)) -> 1 | AI86: =IF(N86="", 0, IF(ISNUMBER(SEARCH("Winter", N86)), 1, 0)) -> 0
A87: 86 | B87: The Persistence of Memory | C87: 4 | D87: This painting mostly makes me feel uncomfortable and confused. It looks very strange, with everything warped and distorted, especially the way time seems to be shown. It feels like it is trying to say something about time or memory, but I‚Äôm not sure what exactly. The colours are quite dark and heavy, and the whole scene feels oddly still in a way that is not peaceful, more like a quiet that makes me uneasy. Overall, I don‚Äôt really like it and it does not give me any pleasant emotion. | E87: 4 - Agree | F87: 1 - Strongly disagree | G87: 2 - Disagree | H87: 5 - Strongly agree | I87: 6 | J87: 6 | K87: 0 ‚Äì I personally would not buy this painting. | L87: Office | M87: Friends,Family members | N87: Summer | O87: If this painting was a food, it would be something unpleasant and hard to swallow. I imagine it as a dish with a strange, almost rotten taste, where the flavours don‚Äôt match and make you feel uneasy as you eat it. The texture would be soft and limp in a way that feels wrong, and there might be a bitter or metallic aftertaste that lingers in your mouth. It is not comforting or satisfying at all ‚Äì instead, it would be the kind of food that makes you lose your appetite and feel slightly disturbed, even after you stop eating. | P87: The soundtrack would be slow and minimal, with long, low notes that seem to hang in the air. There would be a soft, dull rhythm in the background, but nothing sharp or loud. The music would feel slightly out of tune or warped at times, creating a strange, heavy atmosphere. It would sound quiet on the surface, but underneath there would be a subtle tension that makes me feel a little uneasy. | Q87: =IF(E87="", "", LEFT(E87, 1) * 1) -> 4 | R87: =IF(F87="","",VALUE(LEFT(F87,FIND(" ",F87)-1))) -> 1 | S87: =IF(G87="","",VALUE(LEFT(G87,FIND(" ",G87)-1))) -> 2 | T87: =IF(H87="","",VALUE(LEFT(H87,FIND(" ",H87)-1))) -> 5 | U87: 0 | V87: =IF(L87="",0,IF(ISNUMBER(SEARCH("Bathroom",L87)),1,0)) -> 0 | W87: =IF(L87="",0,IF(ISNUMBER(SEARCH("Dining room",L87)),1,0)) -> 0 | X87: =IF(L87="",0,IF(ISNUMBER(SEARCH("Office",L87)),1,0)) -> 1 | Y87: =IF(L87="",0,IF(ISNUMBER(SEARCH("Bedroom",L87)),1,0)) -> 0 | Z87: =IF(L87="",0,IF(ISNUMBER(SEARCH("Living room",L87)),1,0)) -> 0 | AA87: =IF(M87="",0, IF(ISNUMBER(SEARCH("By yourself",M87)), 1, 0)) -> 0 | AB87: =IF(M87="", 0, IF(ISNUMBER(SEARCH("Friends", M87)), 1, 0)) -> 1 | AC87: =IF(M87="",0,IF(ISNUMBER(SEARCH("Family members", M87)), 1, 0)) -> 1 | AD87: =IF(M87="", 0, IF(ISNUMBER(SEARCH("Coworkers/Classmates", M87)), 1, 0)) -> 0 | AE87: =IF(M87="", 0, IF(ISNUMBER(SEARCH("Strangers", M87)), 1, 0)) -> 0 | AF87: =IF(N87="", 0, IF(ISNUMBER(SEARCH("Spring", N87)), 1, 0)) -> 0 | AG87: =IF(N87="", 0, IF(ISNUMBER(SEARCH("Summer", N87)), 1, 0)) -> 1 | AH87: =IF(N87="", 0, IF(ISNUMBER(SEARCH("Fall", N87)), 1, 0)) -> 0 | AI87: =IF(N87="", 0, IF(ISNUMBER(SEARCH("Winter", N87)), 1, 0)) -> 0
A88: 87 | B88: The Persistence of Memory | C88: 6 | D88: It makes me feel unsettled yet curious, like everything has a time and things are going to die. There‚Äôs a sense of distortion that pulls me in and makes me reflect on how fragile and strange reality can feel, just like the dripping clock. Also in the left corner there is a slab (looks like a mirror), which makes me question why is it there and what is the painter trying to depict here. | E88: 3 - Neutral/Unsure | F88: 2 - Disagree | G88: 2 - Disagree | H88: 3 - Neutral/Unsure | I88: 3 | J88: 4 | K88: 100 | L88: Bathroom | M88: Friends,Strangers,By yourself | N88: Fall | O88: m&m cookies | P88: Slow, echoing tones with long pauses between notes, creating a stretched, surreal atmosphere that feels slightly uncomfortable, like water waves with no sound, but deeply immersive. | Q88: =IF(E88="", "", LEFT(E88, 1) * 1) -> 3 | R88: =IF(F88="","",VALUE(LEFT(F88,FIND(" ",F88)-1))) -> 2 | S88: =IF(G88="","",VALUE(LEFT(G88,FIND(" ",G88)-1))) -> 2 | T88: =IF(H88="","",VALUE(LEFT(H88,FIND(" ",H88)-1))) -> 3 | U88: 100 | V88: =IF(L88="",0,IF(ISNUMBER(SEARCH("Bathroom",L88)),1,0)) -> 1 | W88: =IF(L88="",0,IF(ISNUMBER(SEARCH("Dining room",L88)),1,0)) -> 0 | X88: =IF(L88="",0,IF(ISNUMBER(SEARCH("Office",L88)),1,0)) -> 0 | Y88: =IF(L88="",0,IF(ISNUMBER(SEARCH("Bedroom",L88)),1,0)) -> 0 | Z88: =IF(L88="",0,IF(ISNUMBER(SEARCH("Living room",L88)),1,0)) -> 0 | AA88: =IF(M88="",0, IF(ISNUMBER(SEARCH("By yourself",M88)), 1, 0)) -> 1 | AB88: =IF(M88="", 0, IF(ISNUMBER(SEARCH("Friends", M88)), 1, 0)) -> 1 | AC88: =IF(M88="",0,IF(ISNUMBER(SEARCH("Family members", M88)), 1, 0)) -> 0 | AD88: =IF(M88="", 0, IF(ISNUMBER(SEARCH("Coworkers/Classmates", M88)), 1, 0)) -> 0 | AE88: =IF(M88="", 0, IF(ISNUMBER(SEARCH("Strangers", M88)), 1, 0)) -> 1 | AF88: =IF(N88="", 0, IF(ISNUMBER(SEARCH("Spring", N88)), 1, 0)) -> 0 | AG88: =IF(N88="", 0, IF(ISNUMBER(SEARCH("Summer", N88)), 1, 0)) -> 0 | AH88: =IF(N88="", 0, IF(ISNUMBER(SEARCH("Fall", N88)), 1, 0)) -> 1 | AI88: =IF(N88="", 0, IF(ISNUMBER(SEARCH("Winter", N88)), 1, 0)) -> 0
A89: 88 | B89: The Persistence of Memory | C89: 8 | D89: alone and alarmed.¬† | E89: 4 - Agree | F89: 2 - Disagree | G89: 1 - Strongly disagree | H89: 4 - Agree | I89: 4 | J89: 5 | K89: 100 | L89: Office | M89: Family members | N89: Winter | O89: kiwi | P89: desolate harrowing note low tempo with fluid melodies slowly morphing into structured high tempo base and drums and back into mellow fluid but still odd melodies.¬† | Q89: =IF(E89="", "", LEFT(E89, 1) * 1) -> 4 | R89: =IF(F89="","",VALUE(LEFT(F89,FIND(" ",F89)-1))) -> 2 | S89: =IF(G89="","",VALUE(LEFT(G89,FIND(" ",G89)-1))) -> 1 | T89: =IF(H89="","",VALUE(LEFT(H89,FIND(" ",H89)-1))) -> 4 | U89: 100 | V89: =IF(L89="",0,IF(ISNUMBER(SEARCH("Bathroom",L89)),1,0)) -> 0 | W89: =IF(L89="",0,IF(ISNUMBER(SEARCH("Dining room",L89)),1,0)) -> 0 | X89: =IF(L89="",0,IF(ISNUMBER(SEARCH("Office",L89)),1,0)) -> 1 | Y89: =IF(L89="",0,IF(ISNUMBER(SEARCH("Bedroom",L89)),1,0)) -> 0 | Z89: =IF(L89="",0,IF(ISNUMBER(SEARCH("Living room",L89)),1,0)) -> 0 | AA89: =IF(M89="",0, IF(ISNUMBER(SEARCH("By yourself",M89)), 1, 0)) -> 0 | AB89: =IF(M89="", 0, IF(ISNUMBER(SEARCH("Friends", M89)), 1, 0)) -> 0 | AC89: =IF(M89="",0,IF(ISNUMBER(SEARCH("Family members", M89)), 1, 0)) -> 1 | AD89: =IF(M89="", 0, IF(ISNUMBER(SEARCH("Coworkers/Classmates", M89)), 1, 0)) -> 0 | AE89: =IF(M89="", 0, IF(ISNUMBER(SEARCH("Strangers", M89)), 1, 0)) -> 0 | AF89: =IF(N89="", 0, IF(ISNUMBER(SEARCH("Spring", N89)), 1, 0)) -> 0 | AG89: =IF(N89="", 0, IF(ISNUMBER(SEARCH("Summer", N89)), 1, 0)) -> 0 | AH89: =IF(N89="", 0, IF(ISNUMBER(SEARCH("Fall", N89)), 1, 0)) -> 0 | AI89: =IF(N89="", 0, IF(ISNUMBER(SEARCH("Winter", N89)), 1, 0)) -> 1
A90: 89 | B90: The Persistence of Memory | C90: 8 | D90: The passaway of time. | E90: 3 - Neutral/Unsure | F90: 3 - Neutral/Unsure | G90: 3 - Neutral/Unsure | H90: 3 - Neutral/Unsure | I90: 6 | J90: 3 | K90: 1000000 | L90: Living room | M90: Friends,Family members | N90: Fall | O90: Pizza | P90: The soundtrack will be very serene and tranquil. | Q90: =IF(E90="", "", LEFT(E90, 1) * 1) -> 3 | R90: =IF(F90="","",VALUE(LEFT(F90,FIND(" ",F90)-1))) -> 3 | S90: =IF(G90="","",VALUE(LEFT(G90,FIND(" ",G90)-1))) -> 3 | T90: =IF(H90="","",VALUE(LEFT(H90,FIND(" ",H90)-1))) -> 3 | U90: 1000000 | V90: =IF(L90="",0,IF(ISNUMBER(SEARCH("Bathroom",L90)),1,0)) -> 0 | W90: =IF(L90="",0,IF(ISNUMBER(SEARCH("Dining room",L90)),1,0)) -> 0 | X90: =IF(L90="",0,IF(ISNUMBER(SEARCH("Office",L90)),1,0)) -> 0 | Y90: =IF(L90="",0,IF(ISNUMBER(SEARCH("Bedroom",L90)),1,0)) -> 0 | Z90: =IF(L90="",0,IF(ISNUMBER(SEARCH("Living room",L90)),1,0)) -> 1 | AA90: =IF(M90="",0, IF(ISNUMBER(SEARCH("By yourself",M90)), 1, 0)) -> 0 | AB90: =IF(M90="", 0, IF(ISNUMBER(SEARCH("Friends", M90)), 1, 0)) -> 1 | AC90: =IF(M90="",0,IF(ISNUMBER(SEARCH("Family members", M90)), 1, 0)) -> 1 | AD90: =IF(M90="", 0, IF(ISNUMBER(SEARCH("Coworkers/Classmates", M90)), 1, 0)) -> 0 | AE90: =IF(M90="", 0, IF(ISNUMBER(SEARCH("Strangers", M90)), 1, 0)) -> 0 | AF90: =IF(N90="", 0, IF(ISNUMBER(SEARCH("Spring", N90)), 1, 0)) -> 0 | AG90: =IF(N90="", 0, IF(ISNUMBER(SEARCH("Summer", N90)), 1, 0)) -> 0 | AH90: =IF(N90="", 0, IF(ISNUMBER(SEARCH("Fall", N90)), 1, 0)) -> 1 | AI90: =IF(N90="", 0, IF(ISNUMBER(SEARCH("Winter", N90)), 1, 0)) -> 0
A91: 90 | B91: The Persistence of Memory | C91: 2 | D91: Weird cause there's hard things like watches that are soft and flimsy | E91: 5 - Strongly agree | F91: 2 - Disagree | G91: 2 - Disagree | H91: 4 - Agree | I91: 5 | J91: 4 | K91: 5 | L91: Bathroom | M91: By yourself | N91: Fall | O91: asparagus | P91: It would be uneasy sounds of nature | Q91: =IF(E91="", "", LEFT(E91, 1) * 1) -> 5 | R91: =IF(F91="","",VALUE(LEFT(F91,FIND(" ",F91)-1))) -> 2 | S91: =IF(G91="","",VALUE(LEFT(G91,FIND(" ",G91)-1))) -> 2 | T91: =IF(H91="","",VALUE(LEFT(H91,FIND(" ",H91)-1))) -> 4 | U91: 5 | V91: =IF(L91="",0,IF(ISNUMBER(SEARCH("Bathroom",L91)),1,0)) -> 1 | W91: =IF(L91="",0,IF(ISNUMBER(SEARCH("Dining room",L91)),1,0)) -> 0 | X91: =IF(L91="",0,IF(ISNUMBER(SEARCH("Office",L91)),1,0)) -> 0 | Y91: =IF(L91="",0,IF(ISNUMBER(SEARCH("Bedroom",L91)),1,0)) -> 0 | Z91: =IF(L91="",0,IF(ISNUMBER(SEARCH("Living room",L91)),1,0)) -> 0 | AA91: =IF(M91="",0, IF(ISNUMBER(SEARCH("By yourself",M91)), 1, 0)) -> 1 | AB91: =IF(M91="", 0, IF(ISNUMBER(SEARCH("Friends", M91)), 1, 0)) -> 0 | AC91: =IF(M91="",0,IF(ISNUMBER(SEARCH("Family members", M91)), 1, 0)) -> 0 | AD91: =IF(M91="", 0, IF(ISNUMBER(SEARCH("Coworkers/Classmates", M91)), 1, 0)) -> 0 | AE91: =IF(M91="", 0, IF(ISNUMBER(SEARCH("Strangers", M91)), 1, 0)) -> 0 | AF91: =IF(N91="", 0, IF(ISNUMBER(SEARCH("Spring", N91)), 1, 0)) -> 0 | AG91: =IF(N91="", 0, IF(ISNUMBER(SEARCH("Summer", N91)), 1, 0)) -> 0 | AH91: =IF(N91="", 0, IF(ISNUMBER(SEARCH("Fall", N91)), 1, 0)) -> 1 | AI91: =IF(N91="", 0, IF(ISNUMBER(SEARCH("Winter", N91)), 1, 0)) -> 0
A92: 91 | B92: The Persistence of Memory | C92: 9 | D92: Nostaligic, empty, floating in time. | E92: 4 - Agree | F92: 2 - Disagree | G92: 3 - Neutral/Unsure | H92: 4 - Agree | I92: 6 | J92: 7 | K92: 100000 CAD | L92: Bedroom | M92: By yourself | N92: Summer,Fall | O92: A homecooked meal like a stew. | P92: A calm, quiet piano melody.¬† | Q92: =IF(E92="", "", LEFT(E92, 1) * 1) -> 4 | R92: =IF(F92="","",VALUE(LEFT(F92,FIND(" ",F92)-1))) -> 2 | S92: =IF(G92="","",VALUE(LEFT(G92,FIND(" ",G92)-1))) -> 3 | T92: =IF(H92="","",VALUE(LEFT(H92,FIND(" ",H92)-1))) -> 4 | U92: 100000 | V92: =IF(L92="",0,IF(ISNUMBER(SEARCH("Bathroom",L92)),1,0)) -> 0 | W92: =IF(L92="",0,IF(ISNUMBER(SEARCH("Dining room",L92)),1,0)) -> 0 | X92: =IF(L92="",0,IF(ISNUMBER(SEARCH("Office",L92)),1,0)) -> 0 | Y92: =IF(L92="",0,IF(ISNUMBER(SEARCH("Bedroom",L92)),1,0)) -> 1 | Z92: =IF(L92="",0,IF(ISNUMBER(SEARCH("Living room",L92)),1,0)) -> 0 | AA92: =IF(M92="",0, IF(ISNUMBER(SEARCH("By yourself",M92)), 1, 0)) -> 1 | AB92: =IF(M92="", 0, IF(ISNUMBER(SEARCH("Friends", M92)), 1, 0)) -> 0 | AC92: =IF(M92="",0,IF(ISNUMBER(SEARCH("Family members", M92)), 1, 0)) -> 0 | AD92: =IF(M92="", 0, IF(ISNUMBER(SEARCH("Coworkers/Classmates", M92)), 1, 0)) -> 0 | AE92: =IF(M92="", 0, IF(ISNUMBER(SEARCH("Strangers", M92)), 1, 0)) -> 0 | AF92: =IF(N92="", 0, IF(ISNUMBER(SEARCH("Spring", N92)), 1, 0)) -> 0 | AG92: =IF(N92="", 0, IF(ISNUMBER(SEARCH("Summer", N92)), 1, 0)) -> 1 | AH92: =IF(N92="", 0, IF(ISNUMBER(SEARCH("Fall", N92)), 1, 0)) -> 1 | AI92: =IF(N92="", 0, IF(ISNUMBER(SEARCH("Winter", N92)), 1, 0)) -> 0
A93: 92 | B93: The Persistence of Memory | C93: 7 | D93: It makes me question the concept of time and the time I have wasted throughout the years | E93: 4 - Agree | F93: 2 - Disagree | G93: 4 - Agree | H93: 4 - Agree | I93: 8 | J93: 9 | K93: 1000 | L93: Office,Living room | M93: By yourself | N93: Fall | O93: Day old bread | P93: Slow and quiet instrumental piece | Q93: =IF(E93="", "", LEFT(E93, 1) * 1) -> 4 | R93: =IF(F93="","",VALUE(LEFT(F93,FIND(" ",F93)-1))) -> 2 | S93: =IF(G93="","",VALUE(LEFT(G93,FIND(" ",G93)-1))) -> 4 | T93: =IF(H93="","",VALUE(LEFT(H93,FIND(" ",H93)-1))) -> 4 | U93: 1000 | V93: =IF(L93="",0,IF(ISNUMBER(SEARCH("Bathroom",L93)),1,0)) -> 0 | W93: =IF(L93="",0,IF(ISNUMBER(SEARCH("Dining room",L93)),1,0)) -> 0 | X93: =IF(L93="",0,IF(ISNUMBER(SEARCH("Office",L93)),1,0)) -> 1 | Y93: =IF(L93="",0,IF(ISNUMBER(SEARCH("Bedroom",L93)),1,0)) -> 0 | Z93: =IF(L93="",0,IF(ISNUMBER(SEARCH("Living room",L93)),1,0)) -> 1 | AA93: =IF(M93="",0, IF(ISNUMBER(SEARCH("By yourself",M93)), 1, 0)) -> 1 | AB93: =IF(M93="", 0, IF(ISNUMBER(SEARCH("Friends", M93)), 1, 0)) -> 0 | AC93: =IF(M93="",0,IF(ISNUMBER(SEARCH("Family members", M93)), 1, 0)) -> 0 | AD93: =IF(M93="", 0, IF(ISNUMBER(SEARCH("Coworkers/Classmates", M93)), 1, 0)) -> 0 | AE93: =IF(M93="", 0, IF(ISNUMBER(SEARCH("Strangers", M93)), 1, 0)) -> 0 | AF93: =IF(N93="", 0, IF(ISNUMBER(SEARCH("Spring", N93)), 1, 0)) -> 0 | AG93: =IF(N93="", 0, IF(ISNUMBER(SEARCH("Summer", N93)), 1, 0)) -> 0 | AH93: =IF(N93="", 0, IF(ISNUMBER(SEARCH("Fall", N93)), 1, 0)) -> 1 | AI93: =IF(N93="", 0, IF(ISNUMBER(SEARCH("Winter", N93)), 1, 0)) -> 0
A94: 93 | B94: The Persistence of Memory | C94: 9 | D94: I feel disturbed. There is a lot happening in this painting. For example, why are the clocks melting? What is that red thing at the left? What is the white thing in the middle that one of the clocks is resting on? There are a lot of questions unanswered. Also, the difference between the background, which is serene and relaxing is quite stark against the objects in the foreground. I don't understand what the painting is trying to convey. | E94: 5 - Strongly agree | F94: 4 - Agree | G94: 1 - Strongly disagree | H94: 5 - Strongly agree | I94: 3 | J94: 3 | K94: 0 | L94: Office | M94: By yourself | N94: Spring | O94: Can of beans | P94: Unsettling instrumental, no lyrics, almost like horror movie music but a little more depressing than scary (not the type designed to increase your heart rate). | Q94: =IF(E94="", "", LEFT(E94, 1) * 1) -> 5 | R94: =IF(F94="","",VALUE(LEFT(F94,FIND(" ",F94)-1))) -> 4 | S94: =IF(G94="","",VALUE(LEFT(G94,FIND(" ",G94)-1))) -> 1 | T94: =IF(H94="","",VALUE(LEFT(H94,FIND(" ",H94)-1))) -> 5 | U94: 0 | V94: =IF(L94="",0,IF(ISNUMBER(SEARCH("Bathroom",L94)),1,0)) -> 0 | W94: =IF(L94="",0,IF(ISNUMBER(SEARCH("Dining room",L94)),1,0)) -> 0 | X94: =IF(L94="",0,IF(ISNUMBER(SEARCH("Office",L94)),1,0)) -> 1 | Y94: =IF(L94="",0,IF(ISNUMBER(SEARCH("Bedroom",L94)),1,0)) -> 0 | Z94: =IF(L94="",0,IF(ISNUMBER(SEARCH("Living room",L94)),1,0)) -> 0 | AA94: =IF(M94="",0, IF(ISNUMBER(SEARCH("By yourself",M94)), 1, 0)) -> 1 | AB94: =IF(M94="", 0, IF(ISNUMBER(SEARCH("Friends", M94)), 1, 0)) -> 0 | AC94: =IF(M94="",0,IF(ISNUMBER(SEARCH("Family members", M94)), 1, 0)) -> 0 | AD94: =IF(M94="", 0, IF(ISNUMBER(SEARCH("Coworkers/Classmates", M94)), 1, 0)) -> 0 | AE94: =IF(M94="", 0, IF(ISNUMBER(SEARCH("Strangers", M94)), 1, 0)) -> 0 | AF94: =IF(N94="", 0, IF(ISNUMBER(SEARCH("Spring", N94)), 1, 0)) -> 1 | AG94: =IF(N94="", 0, IF(ISNUMBER(SEARCH("Summer", N94)), 1, 0)) -> 0 | AH94: =IF(N94="", 0, IF(ISNUMBER(SEARCH("Fall", N94)), 1, 0)) -> 0 | AI94: =IF(N94="", 0, IF(ISNUMBER(SEARCH("Winter", N94)), 1, 0)) -> 0
A95: 94 | B95: The Persistence of Memory | C95: 6 | D95: The painting makes me feel old and sad and uneasy and reflective about my time here on Earth. I feel sad that time never stops and it keeps on going as I am stuck and reflecting on the memories of the past and the fleeting time I have.¬† ¬† ¬† ¬† | E95: 4 - Agree | F95: 2 - Disagree | G95: 3 - Neutral/Unsure | H95: 4 - Agree | I95: 5 | J95: 5 | K95: 250 | L95: Office | M95: By yourself | N95: Fall | O95: dark chocolate | P95: A slow ambient track with soft long notes and pauses between sounds. Music would feel empty with little bit of tension as if it is building up to the never ending climax.¬† | Q95: =IF(E95="", "", LEFT(E95, 1) * 1) -> 4 | R95: =IF(F95="","",VALUE(LEFT(F95,FIND(" ",F95)-1))) -> 2 | S95: =IF(G95="","",VALUE(LEFT(G95,FIND(" ",G95)-1))) -> 3 | T95: =IF(H95="","",VALUE(LEFT(H95,FIND(" ",H95)-1))) -> 4 | U95: 250 | V95: =IF(L95="",0,IF(ISNUMBER(SEARCH("Bathroom",L95)),1,0)) -> 0 | W95: =IF(L95="",0,IF(ISNUMBER(SEARCH("Dining room",L95)),1,0)) -> 0 | X95: =IF(L95="",0,IF(ISNUMBER(SEARCH("Office",L95)),1,0)) -> 1 | Y95: =IF(L95="",0,IF(ISNUMBER(SEARCH("Bedroom",L95)),1,0)) -> 0 | Z95: =IF(L95="",0,IF(ISNUMBER(SEARCH("Living room",L95)),1,0)) -> 0 | AA95: =IF(M95="",0, IF(ISNUMBER(SEARCH("By yourself",M95)), 1, 0)) -> 1 | AB95: =IF(M95="", 0, IF(ISNUMBER(SEARCH("Friends", M95)), 1, 0)) -> 0 | AC95: =IF(M95="",0,IF(ISNUMBER(SEARCH("Family members", M95)), 1, 0)) -> 0 | AD95: =IF(M95="", 0, IF(ISNUMBER(SEARCH("Coworkers/Classmates", M95)), 1, 0)) -> 0 | AE95: =IF(M95="", 0, IF(ISNUMBER(SEARCH("Strangers", M95)), 1, 0)) -> 0 | AF95: =IF(N95="", 0, IF(ISNUMBER(SEARCH("Spring", N95)), 1, 0)) -> 0 | AG95: =IF(N95="", 0, IF(ISNUMBER(SEARCH("Summer", N95)), 1, 0)) -> 0 | AH95: =IF(N95="", 0, IF(ISNUMBER(SEARCH("Fall", N95)), 1, 0)) -> 1 | AI95: =IF(N95="", 0, IF(ISNUMBER(SEARCH("Winter", N95)), 1, 0)) -> 0
A96: 95 | B96: The Persistence of Memory | C96: 7 | D96: I find it slightly uncanny. | E96: 2 - Disagree | F96: 1 - Strongly disagree | G96: 2 - Disagree | H96: 4 - Agree | I96: 8 | J96: 4 | K96: 20 | L96: Bathroom | M96: Friends,Family members | N96: Summer | O96: expired Jell-O | P96: Ominous, largely monotone apart from a shrill sound in the background. | Q96: =IF(E96="", "", LEFT(E96, 1) * 1) -> 2 | R96: =IF(F96="","",VALUE(LEFT(F96,FIND(" ",F96)-1))) -> 1 | S96: =IF(G96="","",VALUE(LEFT(G96,FIND(" ",G96)-1))) -> 2 | T96: =IF(H96="","",VALUE(LEFT(H96,FIND(" ",H96)-1))) -> 4 | U96: 20 | V96: =IF(L96="",0,IF(ISNUMBER(SEARCH("Bathroom",L96)),1,0)) -> 1 | W96: =IF(L96="",0,IF(ISNUMBER(SEARCH("Dining room",L96)),1,0)) -> 0 | X96: =IF(L96="",0,IF(ISNUMBER(SEARCH("Office",L96)),1,0)) -> 0 | Y96: =IF(L96="",0,IF(ISNUMBER(SEARCH("Bedroom",L96)),1,0)) -> 0 | Z96: =IF(L96="",0,IF(ISNUMBER(SEARCH("Living room",L96)),1,0)) -> 0 | AA96: =IF(M96="",0, IF(ISNUMBER(SEARCH("By yourself",M96)), 1, 0)) -> 0 | AB96: =IF(M96="", 0, IF(ISNUMBER(SEARCH("Friends", M96)), 1, 0)) -> 1 | AC96: =IF(M96="",0,IF(ISNUMBER(SEARCH("Family members", M96)), 1, 0)) -> 1 | AD96: =IF(M96="", 0, IF(ISNUMBER(SEARCH("Coworkers/Classmates", M96)), 1, 0)) -> 0 | AE96: =IF(M96="", 0, IF(ISNUMBER(SEARCH("Strangers", M96)), 1, 0)) -> 0 | AF96: =IF(N96="", 0, IF(ISNUMBER(SEARCH("Spring", N96)), 1, 0)) -> 0 | AG96: =IF(N96="", 0, IF(ISNUMBER(SEARCH("Summer", N96)), 1, 0)) -> 1 | AH96: =IF(N96="", 0, IF(ISNUMBER(SEARCH("Fall", N96)), 1, 0)) -> 0 | AI96: =IF(N96="", 0, IF(ISNUMBER(SEARCH("Winter", N96)), 1, 0)) -> 0
A97: 96 | B97: The Persistence of Memory | C97: 8 | D97: anxious, sad, nostalgic | E97: 5 - Strongly agree | F97: 1 - Strongly disagree | G97: 2 - Disagree | H97: 4 - Agree | I97: 4 | J97: 3 | K97: 250000 | L97: Office,Living room | M97: By yourself | N97: Fall,Winter | O97: Juice boxes | P97: A quiet wind sound with low piano in the background.¬† | Q97: =IF(E97="", "", LEFT(E97, 1) * 1) -> 5 | R97: =IF(F97="","",VALUE(LEFT(F97,FIND(" ",F97)-1))) -> 1 | S97: =IF(G97="","",VALUE(LEFT(G97,FIND(" ",G97)-1))) -> 2 | T97: =IF(H97="","",VALUE(LEFT(H97,FIND(" ",H97)-1))) -> 4 | U97: 250000 | V97: =IF(L97="",0,IF(ISNUMBER(SEARCH("Bathroom",L97)),1,0)) -> 0 | W97: =IF(L97="",0,IF(ISNUMBER(SEARCH("Dining room",L97)),1,0)) -> 0 | X97: =IF(L97="",0,IF(ISNUMBER(SEARCH("Office",L97)),1,0)) -> 1 | Y97: =IF(L97="",0,IF(ISNUMBER(SEARCH("Bedroom",L97)),1,0)) -> 0 | Z97: =IF(L97="",0,IF(ISNUMBER(SEARCH("Living room",L97)),1,0)) -> 1 | AA97: =IF(M97="",0, IF(ISNUMBER(SEARCH("By yourself",M97)), 1, 0)) -> 1 | AB97: =IF(M97="", 0, IF(ISNUMBER(SEARCH("Friends", M97)), 1, 0)) -> 0 | AC97: =IF(M97="",0,IF(ISNUMBER(SEARCH("Family members", M97)), 1, 0)) -> 0 | AD97: =IF(M97="", 0, IF(ISNUMBER(SEARCH("Coworkers/Classmates", M97)), 1, 0)) -> 0 | AE97: =IF(M97="", 0, IF(ISNUMBER(SEARCH("Strangers", M97)), 1, 0)) -> 0 | AF97: =IF(N97="", 0, IF(ISNUMBER(SEARCH("Spring", N97)), 1, 0)) -> 0 | AG97: =IF(N97="", 0, IF(ISNUMBER(SEARCH("Summer", N97)), 1, 0)) -> 0 | AH97: =IF(N97="", 0, IF(ISNUMBER(SEARCH("Fall", N97)), 1, 0)) -> 1 | AI97: =IF(N97="", 0, IF(ISNUMBER(SEARCH("Winter", N97)), 1, 0)) -> 1
A98: 97 | B98: The Persistence of Memory | C98: 7 | D98: This painting makes me feel heat, like a day summer's day.¬† | E98: 4 - Agree | F98: 2 - Disagree | G98: 2 - Disagree | H98: 4 - Agree | I98: 6 | J98: 4 | K98: 100 | L98: Office | M98: By yourself | N98: Summer | O98: Crackers with olive tapenade | P98: A whistling wind, a slow accordion plays a wistful tune.¬† | Q98: =IF(E98="", "", LEFT(E98, 1) * 1) -> 4 | R98: =IF(F98="","",VALUE(LEFT(F98,FIND(" ",F98)-1))) -> 2 | S98: =IF(G98="","",VALUE(LEFT(G98,FIND(" ",G98)-1))) -> 2 | T98: =IF(H98="","",VALUE(LEFT(H98,FIND(" ",H98)-1))) -> 4 | U98: 100 | V98: =IF(L98="",0,IF(ISNUMBER(SEARCH("Bathroom",L98)),1,0)) -> 0 | W98: =IF(L98="",0,IF(ISNUMBER(SEARCH("Dining room",L98)),1,0)) -> 0 | X98: =IF(L98="",0,IF(ISNUMBER(SEARCH("Office",L98)),1,0)) -> 1 | Y98: =IF(L98="",0,IF(ISNUMBER(SEARCH("Bedroom",L98)),1,0)) -> 0 | Z98: =IF(L98="",0,IF(ISNUMBER(SEARCH("Living room",L98)),1,0)) -> 0 | AA98: =IF(M98="",0, IF(ISNUMBER(SEARCH("By yourself",M98)), 1, 0)) -> 1 | AB98: =IF(M98="", 0, IF(ISNUMBER(SEARCH("Friends", M98)), 1, 0)) -> 0 | AC98: =IF(M98="",0,IF(ISNUMBER(SEARCH("Family members", M98)), 1, 0)) -> 0 | AD98: =IF(M98="", 0, IF(ISNUMBER(SEARCH("Coworkers/Classmates", M98)), 1, 0)) -> 0 | AE98: =IF(M98="", 0, IF(ISNUMBER(SEARCH("Strangers", M98)), 1, 0)) -> 0 | AF98: =IF(N98="", 0, IF(ISNUMBER(SEARCH("Spring", N98)), 1, 0)) -> 0 | AG98: =IF(N98="", 0, IF(ISNUMBER(SEARCH("Summer", N98)), 1, 0)) -> 1 | AH98: =IF(N98="", 0, IF(ISNUMBER(SEARCH("Fall", N98)), 1, 0)) -> 0 | AI98: =IF(N98="", 0, IF(ISNUMBER(SEARCH("Winter", N98)), 1, 0)) -> 0
A99: 98 | B99: The Persistence of Memory | C99: 8 | D99: It makes me feel nostalgic.¬† | E99: 5 - Strongly agree | F99: 3 - Neutral/Unsure | G99: 4 - Agree | H99: 4 - Agree | I99: 5 | J99: 6 | K99: 15 | L99: Office | M99: By yourself | N99: Summer | O99: grilled cheese | P99: a mellow, eerie tune.¬† | Q99: =IF(E99="", "", LEFT(E99, 1) * 1) -> 5 | R99: =IF(F99="","",VALUE(LEFT(F99,FIND(" ",F99)-1))) -> 3 | S99: =IF(G99="","",VALUE(LEFT(G99,FIND(" ",G99)-1))) -> 4 | T99: =IF(H99="","",VALUE(LEFT(H99,FIND(" ",H99)-1))) -> 4 | U99: 15 | V99: =IF(L99="",0,IF(ISNUMBER(SEARCH("Bathroom",L99)),1,0)) -> 0 | W99: =IF(L99="",0,IF(ISNUMBER(SEARCH("Dining room",L99)),1,0)) -> 0 | X99: =IF(L99="",0,IF(ISNUMBER(SEARCH("Office",L99)),1,0)) -> 1 | Y99: =IF(L99="",0,IF(ISNUMBER(SEARCH("Bedroom",L99)),1,0)) -> 0 | Z99: =IF(L99="",0,IF(ISNUMBER(SEARCH("Living room",L99)),1,0)) -> 0 | AA99: =IF(M99="",0, IF(ISNUMBER(SEARCH("By yourself",M99)), 1, 0)) -> 1 | AB99: =IF(M99="", 0, IF(ISNUMBER(SEARCH("Friends", M99)), 1, 0)) -> 0 | AC99: =IF(M99="",0,IF(ISNUMBER(SEARCH("Family members", M99)), 1, 0)) -> 0 | AD99: =IF(M99="", 0, IF(ISNUMBER(SEARCH("Coworkers/Classmates", M99)), 1, 0)) -> 0 | AE99: =IF(M99="", 0, IF(ISNUMBER(SEARCH("Strangers", M99)), 1, 0)) -> 0 | AF99: =IF(N99="", 0, IF(ISNUMBER(SEARCH("Spring", N99)), 1, 0)) -> 0 | AG99: =IF(N99="", 0, IF(ISNUMBER(SEARCH("Summer", N99)), 1, 0)) -> 1 | AH99: =IF(N99="", 0, IF(ISNUMBER(SEARCH("Fall", N99)), 1, 0)) -> 0 | AI99: =IF(N99="", 0, IF(ISNUMBER(SEARCH("Winter", N99)), 1, 0)) -> 0
A100: 99 | B100: The Persistence of Memory | C100: 8 | D100: Uneasy, and a little sad. | E100: 5 - Strongly agree | F100: 1 - Strongly disagree | G100: 2 - Disagree | H100: 5 - Strongly agree | I100: 4 | J100: 4 | K100: 50 | L100: Living room | M100: By yourself | N100: Fall,Winter | O100: Pie crust | P100: Solemn, slow tempo, cello as the only instrument | Q100: =IF(E100="", "", LEFT(E100, 1) * 1) -> 5 | R100: =IF(F100="","",VALUE(LEFT(F100,FIND(" ",F100)-1))) -> 1 | S100: =IF(G100="","",VALUE(LEFT(G100,FIND(" ",G100)-1))) -> 2 | T100: =IF(H100="","",VALUE(LEFT(H100,FIND(" ",H100)-1))) -> 5 | U100: 50 | V100: =IF(L100="",0,IF(ISNUMBER(SEARCH("Bathroom",L100)),1,0)) -> 0 | W100: =IF(L100="",0,IF(ISNUMBER(SEARCH("Dining room",L100)),1,0)) -> 0 | X100: =IF(L100="",0,IF(ISNUMBER(SEARCH("Office",L100)),1,0)) -> 0 | Y100: =IF(L100="",0,IF(ISNUMBER(SEARCH("Bedroom",L100)),1,0)) -> 0 | Z100: =IF(L100="",0,IF(ISNUMBER(SEARCH("Living room",L100)),1,0)) -> 1 | AA100: =IF(M100="",0, IF(ISNUMBER(SEARCH("By yourself",M100)), 1, 0)) -> 1 | AB100: =IF(M100="", 0, IF(ISNUMBER(SEARCH("Friends", M100)), 1, 0)) -> 0 | AC100: =IF(M100="",0,IF(ISNUMBER(SEARCH("Family members", M100)), 1, 0)) -> 0 | AD100: =IF(M100="", 0, IF(ISNUMBER(SEARCH("Coworkers/Classmates", M100)), 1, 0)) -> 0 | AE100: =IF(M100="", 0, IF(ISNUMBER(SEARCH("Strangers", M100)), 1, 0)) -> 0 | AF100: =IF(N100="", 0, IF(ISNUMBER(SEARCH("Spring", N100)), 1, 0)) -> 0 | AG100: =IF(N100="", 0, IF(ISNUMBER(SEARCH("Summer", N100)), 1, 0)) -> 0 | AH100: =IF(N100="", 0, IF(ISNUMBER(SEARCH("Fall", N100)), 1, 0)) -> 1 | AI100: =IF(N100="", 0, IF(ISNUMBER(SEARCH("Winter", N100)), 1, 0)) -> 1
A101: 100 | B101: The Persistence of Memory | C101: 8 | D101: Melancholic, bittersweet, peaceful | E101: 4 - Agree | F101: 4 - Agree | G101: 4 - Agree | H101: 2 - Disagree | I101: 3 | J101: 4 | K101: 50 | L101: Office | M101: Friends,Family members,Coworkers/Classmates,By yourself | N101: Fall | O101: Blueberry | P101: Classical piano sombre | Q101: =IF(E101="", "", LEFT(E101, 1) * 1) -> 4 | R101: =IF(F101="","",VALUE(LEFT(F101,FIND(" ",F101)-1))) -> 4 | S101: =IF(G101="","",VALUE(LEFT(G101,FIND(" ",G101)-1))) -> 4 | T101: =IF(H101="","",VALUE(LEFT(H101,FIND(" ",H101)-1))) -> 2 | U101: 50 | V101: =IF(L101="",0,IF(ISNUMBER(SEARCH("Bathroom",L101)),1,0)) -> 0 | W101: =IF(L101="",0,IF(ISNUMBER(SEARCH("Dining room",L101)),1,0)) -> 0 | X101: =IF(L101="",0,IF(ISNUMBER(SEARCH("Office",L101)),1,0)) -> 1 | Y101: =IF(L101="",0,IF(ISNUMBER(SEARCH("Bedroom",L101)),1,0)) -> 0 | Z101: =IF(L101="",0,IF(ISNUMBER(SEARCH("Living room",L101)),1,0)) -> 0 | AA101: =IF(M101="",0, IF(ISNUMBER(SEARCH("By yourself",M101)), 1, 0)) -> 1 | AB101: =IF(M101="", 0, IF(ISNUMBER(SEARCH("Friends", M101)), 1, 0)) -> 1 | AC101: =IF(M101="",0,IF(ISNUMBER(SEARCH("Family members", M101)), 1, 0)) -> 1 | AD101: =IF(M101="", 0, IF(ISNUMBER(SEARCH("Coworkers/Classmates", M101)), 1, 0)) -> 1 | AE101: =IF(M101="", 0, IF(ISNUMBER(SEARCH("Strangers", M101)), 1, 0)) -> 0 | AF101: =IF(N101="", 0, IF(ISNUMBER(SEARCH("Spring", N101)), 1, 0)) -> 0 | AG101: =IF(N101="", 0, IF(ISNUMBER(SEARCH("Summer", N101)), 1, 0)) -> 0 | AH101: =IF(N101="", 0, IF(ISNUMBER(SEARCH("Fall", N101)), 1, 0)) -> 1 | AI101: =IF(N101="", 0, IF(ISNUMBER(SEARCH("Winter", N101)), 1, 0)) -> 0
A102: 101 | B102: The Persistence of Memory | C102: 4 | D102: Personally, I don't see any emotion conveyed here- I googled what this painting was about and it confirmed my belief- it's not exactly trying to convey any certain emotion. Currently I am in a moody state, so I completely misinterpreted this. | E102: 4 - Agree | F102: 3 - Neutral/Unsure | G102: 4 - Agree | H102: 2 - Disagree | I102: 6 | J102: 8 | K102: I would say $1,000,000 CAD due to it's beauty, and it's historical aura. | L102: Living room | M102: By yourself | N102: Fall | O102: French Onion with cheese | P102: Psychedelic, slow, monotonistic, sitar, no percussion, repetitive, unfixed tempo | Q102: =IF(E102="", "", LEFT(E102, 1) * 1) -> 4 | R102: =IF(F102="","",VALUE(LEFT(F102,FIND(" ",F102)-1))) -> 3 | S102: =IF(G102="","",VALUE(LEFT(G102,FIND(" ",G102)-1))) -> 4 | T102: =IF(H102="","",VALUE(LEFT(H102,FIND(" ",H102)-1))) -> 2 | U102: 1000000 | V102: =IF(L102="",0,IF(ISNUMBER(SEARCH("Bathroom",L102)),1,0)) -> 0 | W102: =IF(L102="",0,IF(ISNUMBER(SEARCH("Dining room",L102)),1,0)) -> 0 | X102: =IF(L102="",0,IF(ISNUMBER(SEARCH("Office",L102)),1,0)) -> 0 | Y102: =IF(L102="",0,IF(ISNUMBER(SEARCH("Bedroom",L102)),1,0)) -> 0 | Z102: =IF(L102="",0,IF(ISNUMBER(SEARCH("Living room",L102)),1,0)) -> 1 | AA102: =IF(M102="",0, IF(ISNUMBER(SEARCH("By yourself",M102)), 1, 0)) -> 1 | AB102: =IF(M102="", 0, IF(ISNUMBER(SEARCH("Friends", M102)), 1, 0)) -> 0 | AC102: =IF(M102="",0,IF(ISNUMBER(SEARCH("Family members", M102)), 1, 0)) -> 0 | AD102: =IF(M102="", 0, IF(ISNUMBER(SEARCH("Coworkers/Classmates", M102)), 1, 0)) -> 0 | AE102: =IF(M102="", 0, IF(ISNUMBER(SEARCH("Strangers", M102)), 1, 0)) -> 0 | AF102: =IF(N102="", 0, IF(ISNUMBER(SEARCH("Spring", N102)), 1, 0)) -> 0 | AG102: =IF(N102="", 0, IF(ISNUMBER(SEARCH("Summer", N102)), 1, 0)) -> 0 | AH102: =IF(N102="", 0, IF(ISNUMBER(SEARCH("Fall", N102)), 1, 0)) -> 1 | AI102: =IF(N102="", 0, IF(ISNUMBER(SEARCH("Winter", N102)), 1, 0)) -> 0
A103: 102 | B103: The Persistence of Memory | C103: 8 | D103: It makes me feel existential about the passage of time.¬† | E103: 5 - Strongly agree | F103: 2 - Disagree | G103: 3 - Neutral/Unsure | H103: 4 - Agree | I103: 8 | J103: 7 | K103: 10000 | L103: Office | M103: Friends,By yourself | N103: Summer | O103: soggy waffles | P103: long, dragging notes, in a minor scale.¬† | Q103: =IF(E103="", "", LEFT(E103, 1) * 1) -> 5 | R103: =IF(F103="","",VALUE(LEFT(F103,FIND(" ",F103)-1))) -> 2 | S103: =IF(G103="","",VALUE(LEFT(G103,FIND(" ",G103)-1))) -> 3 | T103: =IF(H103="","",VALUE(LEFT(H103,FIND(" ",H103)-1))) -> 4 | U103: 10000 | V103: =IF(L103="",0,IF(ISNUMBER(SEARCH("Bathroom",L103)),1,0)) -> 0 | W103: =IF(L103="",0,IF(ISNUMBER(SEARCH("Dining room",L103)),1,0)) -> 0 | X103: =IF(L103="",0,IF(ISNUMBER(SEARCH("Office",L103)),1,0)) -> 1 | Y103: =IF(L103="",0,IF(ISNUMBER(SEARCH("Bedroom",L103)),1,0)) -> 0 | Z103: =IF(L103="",0,IF(ISNUMBER(SEARCH("Living room",L103)),1,0)) -> 0 | AA103: =IF(M103="",0, IF(ISNUMBER(SEARCH("By yourself",M103)), 1, 0)) -> 1 | AB103: =IF(M103="", 0, IF(ISNUMBER(SEARCH("Friends", M103)), 1, 0)) -> 1 | AC103: =IF(M103="",0,IF(ISNUMBER(SEARCH("Family members", M103)), 1, 0)) -> 0 | AD103: =IF(M103="", 0, IF(ISNUMBER(SEARCH("Coworkers/Classmates", M103)), 1, 0)) -> 0 | AE103: =IF(M103="", 0, IF(ISNUMBER(SEARCH("Strangers", M103)), 1, 0)) -> 0 | AF103: =IF(N103="", 0, IF(ISNUMBER(SEARCH("Spring", N103)), 1, 0)) -> 0 | AG103: =IF(N103="", 0, IF(ISNUMBER(SEARCH("Summer", N103)), 1, 0)) -> 1 | AH103: =IF(N103="", 0, IF(ISNUMBER(SEARCH("Fall", N103)), 1, 0)) -> 0 | AI103: =IF(N103="", 0, IF(ISNUMBER(SEARCH("Winter", N103)), 1, 0)) -> 0
A104: 103 | B104: The Persistence of Memory | C104: 5 | D104: This painting makes me feel intrigued, slightly weird and uneasy.¬† | E104: 4 - Agree | F104: 3 - Neutral/Unsure | G104: 2 - Disagree | H104: 4 - Agree | I104: 3 | J104: 4 | K104: 1000000 | L104: Office | M104: By yourself | N104: Summer | O104: Spaghetti | P104: Slow, reverb, smooth | Q104: =IF(E104="", "", LEFT(E104, 1) * 1) -> 4 | R104: =IF(F104="","",VALUE(LEFT(F104,FIND(" ",F104)-1))) -> 3 | S104: =IF(G104="","",VALUE(LEFT(G104,FIND(" ",G104)-1))) -> 2 | T104: =IF(H104="","",VALUE(LEFT(H104,FIND(" ",H104)-1))) -> 4 | U104: 1000000 | V104: =IF(L104="",0,IF(ISNUMBER(SEARCH("Bathroom",L104)),1,0)) -> 0 | W104: =IF(L104="",0,IF(ISNUMBER(SEARCH("Dining room",L104)),1,0)) -> 0 | X104: =IF(L104="",0,IF(ISNUMBER(SEARCH("Office",L104)),1,0)) -> 1 | Y104: =IF(L104="",0,IF(ISNUMBER(SEARCH("Bedroom",L104)),1,0)) -> 0 | Z104: =IF(L104="",0,IF(ISNUMBER(SEARCH("Living room",L104)),1,0)) -> 0 | AA104: =IF(M104="",0, IF(ISNUMBER(SEARCH("By yourself",M104)), 1, 0)) -> 1 | AB104: =IF(M104="", 0, IF(ISNUMBER(SEARCH("Friends", M104)), 1, 0)) -> 0 | AC104: =IF(M104="",0,IF(ISNUMBER(SEARCH("Family members", M104)), 1, 0)) -> 0 | AD104: =IF(M104="", 0, IF(ISNUMBER(SEARCH("Coworkers/Classmates", M104)), 1, 0)) -> 0 | AE104: =IF(M104="", 0, IF(ISNUMBER(SEARCH("Strangers", M104)), 1, 0)) -> 0 | AF104: =IF(N104="", 0, IF(ISNUMBER(SEARCH("Spring", N104)), 1, 0)) -> 0 | AG104: =IF(N104="", 0, IF(ISNUMBER(SEARCH("Summer", N104)), 1, 0)) -> 1 | AH104: =IF(N104="", 0, IF(ISNUMBER(SEARCH("Fall", N104)), 1, 0)) -> 0 | AI104: =IF(N104="", 0, IF(ISNUMBER(SEARCH("Winter", N104)), 1, 0)) -> 0
...

Sheet EDA
B1: The Persistence of Memory | C1: The Starry Night | D1: The Water Lily Pond
A2: Emotion Intensity Mean | B2: =AVERAGEIF(ml_challenge_dataset!B:B, "The Persistence of Memory", ml_challenge_dataset!C:C) -> 6.3580586 | C2: =AVERAGEIF(ml_challenge_dataset!B:B, "The Starry Night", ml_challenge_dataset!C:C) -> 6.5262963 | D2: =AVERAGEIF(ml_challenge_dataset!B:B, "The Water Lily Pond", ml_challenge_dataset!C:C) -> 6.0786916
A3: Emotion Intensity Deviation | B3: {=STDEV(IF(ml_challenge_dataset!B:B="The Persistence of Memory", ml_challenge_dataset!C:C))} -> 2.2217263 | C3: {=STDEV(IF(ml_challenge_dataset!B:B="The Starry Night", ml_challenge_dataset!C:C))} -> 2.5323298 | D3: {=STDEV(IF(ml_challenge_dataset!B:B="The Water Lily Pond",ml_challenge_dataset!C:C))} -> 2.6253359
A4: Sombre Mean | B4: =AVERAGEIF(ml_challenge_dataset!B:B, "The Persistence of Memory", ml_challenge_dataset!Q:Q) -> 3.907919 | C4: =AVERAGEIF(ml_challenge_dataset!B:B, "The Starry Night", ml_challenge_dataset!Q:Q) -> 2.7616387 | D4: =AVERAGEIF(ml_challenge_dataset!B:B, "The Water Lily Pond", ml_challenge_dataset!Q:Q) -> 1.6436567
A5: Sombre Deviation | B5: {=STDEV(IF(ml_challenge_dataset!B:B="The Persistence of Memory", ml_challenge_dataset!Q:Q))} -> 0.84978394 | C5: {=STDEV(IF(ml_challenge_dataset!B:B="The Starry Night", ml_challenge_dataset!Q:Q))} -> 1.1714019 | D5: {=STDEV(IF(ml_challenge_dataset!B:B="The Water Lily Pond", ml_challenge_dataset!Q:Q))} -> 1.0184636
A6: Content Mean | B6: =AVERAGEIF(ml_challenge_dataset!B:B, "The Persistence of Memory", ml_challenge_dataset!R:R) -> 2.1491713 | C6: =AVERAGEIF(ml_challenge_dataset!B:B, "The Starry Night", ml_challenge_dataset!R:R) -> 3.6175373 | D6: =AVERAGEIF(ml_challenge_dataset!B:B, "The Water Lily Pond", ml_challenge_dataset!R:R) -> 4.4074766
A7: Content Deviation | B7: {=STDEV(IF(ml_challenge_dataset!B:B="The Persistence of Memory", ml_challenge_dataset!R:R))} -> 0.87071791 | C7: {=STDEV(IF(ml_challenge_dataset!B:B="The Starry Night", ml_challenge_dataset!R:R))} -> 0.98264867 | D7: {=STDEV(IF(ml_challenge_dataset!B:B="The Water Lily Pond", ml_challenge_dataset!R:R))} -> 0.77793794
A8: Calm Mean | B8: =AVERAGEIF(ml_challenge_dataset!B:B, "The Persistence of Memory", ml_challenge_dataset!S:S) -> 2.6464088 | C8: =AVERAGEIF(ml_challenge_dataset!B:B, "The Starry Night", ml_challenge_dataset!S:S) -> 3.9123134 | D8: =AVERAGEIF(ml_challenge_dataset!B:B, "The Water Lily Pond", ml_challenge_dataset!S:S) -> 4.4720149
A9: Calm Deviation | B9: {=STDEV(IF(ml_challenge_dataset!B:B="The Persistence of Memory", ml_challenge_dataset!S:S))} -> 1.0345601 | C9: {=STDEV(IF(ml_challenge_dataset!B:B="The Starry Night", ml_challenge_dataset!S:S))} -> 1.0293621 | D9: {=STDEV(IF(ml_challenge_dataset!B:B="The Water Lily Pond", ml_challenge_dataset!S:S))} -> 0.76802967
A10: Uneasy Mean | B10: =AVERAGEIF(ml_challenge_dataset!B:B, "The Persistence of Memory", ml_challenge_dataset!T:T) -> 3.8489871 | C10: =AVERAGEIF(ml_challenge_dataset!B:B, "The Starry Night", ml_challenge_dataset!T:T) -> 2.1063433 | D10: =AVERAGEIF(ml_challenge_dataset!B:B, "The Water Lily Pond", ml_challenge_dataset!T:T) -> 1.3563433
A11: Uneasy Deviation | B11: {=STDEV(IF(ml_challenge_dataset!B:B="The Persistence of Memory", ml_challenge_dataset!T:T))} -> 0.9658533 | C11: {=STDEV(IF(ml_challenge_dataset!B:B="The Starry Night", ml_challenge_dataset!T:T))} -> 1.0527564 | D11: {=STDEV(IF(ml_challenge_dataset!B:B="The Water Lily Pond", ml_challenge_dataset!T:T))} -> 0.68486772
A12: Prominent Colors Mean | B12: =AVERAGEIF(ml_challenge_dataset!B:B, "The Persistence of Memory", ml_challenge_dataset!I:I) -> 4.7859779 | C12: =AVERAGEIF(ml_challenge_dataset!B:B, "The Starry Night", ml_challenge_dataset!I:I) -> 3.8992537 | D12: =AVERAGEIF(ml_challenge_dataset!B:B, "The Water Lily Pond", ml_challenge_dataset!I:I) -> 2.9363296
A13: Prominent Colors Deviation | B13: {=STDEV(IF(ml_challenge_dataset!B:B="The Persistence of Memory", ml_challenge_dataset!I:I))} -> 2.4381776 | C13: {=STDEV(IF(ml_challenge_dataset!B:B="The Starry Night", ml_challenge_dataset!I:I))} -> 4.7933369 | D13: {=STDEV(IF(ml_challenge_dataset!B:B="The Water Lily Pond", ml_challenge_dataset!I:I))} -> 2.5301125
A14: Objects Catching Eyes Mean | B14: =AVERAGEIF(ml_challenge_dataset!B:B, "The Persistence of Memory", ml_challenge_dataset!J:J) -> 5.2643253 | C14: =AVERAGEIF(ml_challenge_dataset!B:B, "The Starry Night", ml_challenge_dataset!J:J) -> 4.2649254 | D14: =AVERAGEIF(ml_challenge_dataset!B:B, "The Water Lily Pond", ml_challenge_dataset!J:J) -> 2.3869159
A15: Objects Catching Eyes Deviation | B15: {=STDEV(IF(ml_challenge_dataset!B:B="The Persistence of Memory", ml_challenge_dataset!J:J))} -> 2.1233909 | C15: {=STDEV(IF(ml_challenge_dataset!B:B="The Starry Night", ml_challenge_dataset!J:J))} -> 5.4709459 | D15: {=STDEV(IF(ml_challenge_dataset!B:B="The Water Lily Pond", ml_challenge_dataset!J:J))} -> 2.3519806
A16: Bathroom Mean | B16: =AVERAGEIF(ml_challenge_dataset!B:B, "The Persistence of Memory", ml_challenge_dataset!V:V) -> 0.26156584 | C16: =AVERAGEIF(ml_challenge_dataset!B:B, "The Starry Night", ml_challenge_dataset!V:V) -> 0.17081851 | D16: =AVERAGEIF(ml_challenge_dataset!B:B, "The Water Lily Pond", ml_challenge_dataset!V:V) -> 0.29359431
A17: Bathroom Deviation | B17: {=STDEV(IF(ml_challenge_dataset!B:B="The Persistence of Memory", ml_challenge_dataset!V:V))} -> 0.4398789 | C17: {=STDEV(IF(ml_challenge_dataset!B:B="The Starry Night", ml_challenge_dataset!V:V))} -> 0.37668557 | D17: {=STDEV(IF(ml_challenge_dataset!B:B="The Water Lily Pond", ml_challenge_dataset!V:V))} -> 0.45581398
A18: Dining room Mean | B18: =AVERAGEIF(ml_challenge_dataset!B:B, "The Persistence of Memory", ml_challenge_dataset!W:W) -> 0.14234875 | C18: =AVERAGEIF(ml_challenge_dataset!B:B, "The Starry Night", ml_challenge_dataset!W:W) -> 0.3113879 | D18: =AVERAGEIF(ml_challenge_dataset!B:B, "The Water Lily Pond", ml_challenge_dataset!W:W) -> 0.39857651
A19: Dining room Deviation | B19: {=STDEV(IF(ml_challenge_dataset!B:B="The Persistence of Memory", ml_challenge_dataset!W:W))} -> 0.34971876 | C19: {=STDEV(IF(ml_challenge_dataset!B:B="The Starry Night", ml_challenge_dataset!W:W))} -> 0.46347351 | D19: {=STDEV(IF(ml_challenge_dataset!B:B="The Water Lily Pond", ml_challenge_dataset!W:W))} -> 0.4900414
A20: Office Mean | B20: =AVERAGEIF(ml_challenge_dataset!B:B, "The Persistence of Memory", ml_challenge_dataset!X:X) -> 0.49644128 | C20: =AVERAGEIF(ml_challenge_dataset!B:B, "The Starry Night", ml_challenge_dataset!X:X) -> 0.29893238 | D20: =AVERAGEIF(ml_challenge_dataset!B:B, "The Water Lily Pond", ml_challenge_dataset!X:X) -> 0.32562278
A21: Office Deviation | B21: {=STDEV(IF(ml_challenge_dataset!B:B="The Persistence of Memory", ml_challenge_dataset!X:X))} -> 0.50043276 | C21: {=STDEV(IF(ml_challenge_dataset!B:B="The Starry Night", ml_challenge_dataset!X:X))} -> 0.45819797 | D21: {=STDEV(IF(ml_challenge_dataset!B:B="The Water Lily Pond", ml_challenge_dataset!X:X))} -> 0.46902453
A22: Bedroom Mean | B22: =AVERAGEIF(ml_challenge_dataset!B:B, "The Persistence of Memory", ml_challenge_dataset!Y:Y) -> 0.10320285 | C22: =AVERAGEIF(ml_challenge_dataset!B:B, "The Starry Night", ml_challenge_dataset!Y:Y) -> 0.59786477 | D22: =AVERAGEIF(ml_challenge_dataset!B:B, "The Water Lily Pond", ml_challenge_dataset!Y:Y) -> 0.47864769
A23: Bedroom Deviation | B23: {=STDEV(IF(ml_challenge_dataset!B:B="The Persistence of Memory", ml_challenge_dataset!Y:Y))} -> 0.30449466 | C23: {=STDEV(IF(ml_challenge_dataset!B:B="The Starry Night", ml_challenge_dataset!Y:Y))} -> 0.49076578 | D23: {=STDEV(IF(ml_challenge_dataset!B:B="The Water Lily Pond", ml_challenge_dataset!Y:Y))} -> 0.4999889
A24: Living room Mean | B24: =AVERAGEIF(ml_challenge_dataset!B:B, "The Persistence of Memory", ml_challenge_dataset!Z:Z) -> 0.31494662 | C24: =AVERAGEIF(ml_challenge_dataset!B:B, "The Starry Night", ml_challenge_dataset!Z:Z) -> 0.55871886 | D24: =AVERAGEIF(ml_challenge_dataset!B:B, "The Water Lily Pond", ml_challenge_dataset!Z:Z) -> 0.67081851
A25: Living room Deviation | B25: {=STDEV(IF(ml_challenge_dataset!B:B="The Persistence of Memory", ml_challenge_dataset!Z:Z))} -> 0.46490842 | C25: {=STDEV(IF(ml_challenge_dataset!B:B="The Starry Night", ml_challenge_dataset!Z:Z))} -> 0.49698248 | D25: {=STDEV(IF(ml_challenge_dataset!B:B="The Water Lily Pond", ml_challenge_dataset!Z:Z))} -> 0.47033462
A26: By Yourself Mean | B26: =AVERAGEIF(ml_challenge_dataset!B:B, "The Persistence of Memory", ml_challenge_dataset!AA:AA) -> 0.65658363 | C26: =AVERAGEIF(ml_challenge_dataset!B:B, "The Starry Night", ml_challenge_dataset!AA:AA) -> 0.54092527 | D26: =AVERAGEIF(ml_challenge_dataset!B:B, "The Water Lily Pond", ml_challenge_dataset!AA:AA) -> 0.5088968
A27: By Yourself Deviation | B27: {=STDEV(IF(ml_challenge_dataset!B:B="The Persistence of Memory", ml_challenge_dataset!AA:AA))} -> 0.47527202 | C27: {=STDEV(IF(ml_challenge_dataset!B:B="The Starry Night", ml_challenge_dataset!AA:AA))} -> 0.49876625 | D27: {=STDEV(IF(ml_challenge_dataset!B:B="The Water Lily Pond", ml_challenge_dataset!AA:AA))} -> 0.5003662
A28: Friends Mean | B28: =AVERAGEIF(ml_challenge_dataset!B:B, "The Persistence of Memory", ml_challenge_dataset!AB:AB) -> 0.34875445 | C28: =AVERAGEIF(ml_challenge_dataset!B:B, "The Starry Night", ml_challenge_dataset!AB:AB) -> 0.64234875 | D28: =AVERAGEIF(ml_challenge_dataset!B:B, "The Water Lily Pond", ml_challenge_dataset!AB:AB) -> 0.62989324
A29: Friends Deviation | B29: {=STDEV(IF(ml_challenge_dataset!B:B="The Persistence of Memory", ml_challenge_dataset!AB:AB))} -> 0.47700067 | C29: {=STDEV(IF(ml_challenge_dataset!B:B="The Starry Night", ml_challenge_dataset!AB:AB))} -> 0.4797357 | D29: {=STDEV(IF(ml_challenge_dataset!B:B="The Water Lily Pond", ml_challenge_dataset!AB:AB))} -> 0.48326318
A30: Family members Mean | B30: =AVERAGEIF(ml_challenge_dataset!B:B, "The Persistence of Memory", ml_challenge_dataset!AC:AC) -> 0.20640569 | C30: =AVERAGEIF(ml_challenge_dataset!B:B, "The Starry Night", ml_challenge_dataset!AC:AC) -> 0.613879 | D30: =AVERAGEIF(ml_challenge_dataset!B:B, "The Water Lily Pond", ml_challenge_dataset!AC:AC) -> 0.69039146
A31: Family members Deviation | B31: {=STDEV(IF(ml_challenge_dataset!B:B="The Persistence of Memory", ml_challenge_dataset!AC:AC))} -> 0.40508563 | C31: {=STDEV(IF(ml_challenge_dataset!B:B="The Starry Night", ml_challenge_dataset!AC:AC))} -> 0.48729261 | D31: {=STDEV(IF(ml_challenge_dataset!B:B="The Water Lily Pond", ml_challenge_dataset!AC:AC))} -> 0.46274411
A32: Coworkers/Classmates Mean | B32: =AVERAGEIF(ml_challenge_dataset!B:B, "The Persistence of Memory", ml_challenge_dataset!AD:AD) -> 0.15124555 | C32: =AVERAGEIF(ml_challenge_dataset!B:B, "The Starry Night", ml_challenge_dataset!AD:AD) -> 0.27402135 | D32: =AVERAGEIF(ml_challenge_dataset!B:B, "The Water Lily Pond", ml_challenge_dataset!AD:AD) -> 0.27046263
A33: Coworkers/Classmates Deviation | B33: {=STDEV(IF(ml_challenge_dataset!B:B="The Persistence of Memory", ml_challenge_dataset!AD:AD))} -> 0.35860725 | C33: {=STDEV(IF(ml_challenge_dataset!B:B="The Starry Night", ml_challenge_dataset!AD:AD))} -> 0.44641713 | D33: {=STDEV(IF(ml_challenge_dataset!B:B="The Water Lily Pond", ml_challenge_dataset!AD:AD))} -> 0.44459455
A34: Strangers Mean | B34: =AVERAGEIF(ml_challenge_dataset!B:B, "The Persistence of Memory", ml_challenge_dataset!AE:AE) -> 0.22241993 | C34: =AVERAGEIF(ml_challenge_dataset!B:B, "The Starry Night", ml_challenge_dataset!AE:AE) -> 0.22597865 | D34: =AVERAGEIF(ml_challenge_dataset!B:B, "The Water Lily Pond", ml_challenge_dataset!AE:AE) -> 0.20996441
A35: Strangers Deviation | B35: {=STDEV(IF(ml_challenge_dataset!B:B="The Persistence of Memory", ml_challenge_dataset!AE:AE))} -> 0.41624223 | C35: {=STDEV(IF(ml_challenge_dataset!B:B="The Starry Night", ml_challenge_dataset!AE:AE))} -> 0.41859776 | D35: {=STDEV(IF(ml_challenge_dataset!B:B="The Water Lily Pond", ml_challenge_dataset!AE:AE))} -> 0.40764573
A36: Spring Mean | B36: =AVERAGEIF(ml_challenge_dataset!B:B, "The Persistence of Memory", ml_challenge_dataset!AF:AF) -> 0.080071174 | C36: =AVERAGEIF(ml_challenge_dataset!B:B, "The Starry Night", ml_challenge_dataset!AF:AF) -> 0.20462633 | D36: =AVERAGEIF(ml_challenge_dataset!B:B, "The Water Lily Pond", ml_challenge_dataset!AF:AF) -> 0.8024911
A37: Spring Deviation | B37: {=STDEV(IF(ml_challenge_dataset!B:B="The Persistence of Memory", ml_challenge_dataset!AF:AF))} -> 0.27164514 | C37: {=STDEV(IF(ml_challenge_dataset!B:B="The Starry Night", ml_challenge_dataset!AF:AF))} -> 0.40378771 | D37: {=STDEV(IF(ml_challenge_dataset!B:B="The Water Lily Pond", ml_challenge_dataset!AF:AF))} -> 0.39847417
A38: Summer Mean | B38: =AVERAGEIF(ml_challenge_dataset!B:B, "The Persistence of Memory", ml_challenge_dataset!AG:AG) -> 0.26868327 | C38: =AVERAGEIF(ml_challenge_dataset!B:B, "The Starry Night", ml_challenge_dataset!AG:AG) -> 0.37010676 | D38: =AVERAGEIF(ml_challenge_dataset!B:B, "The Water Lily Pond", ml_challenge_dataset!AG:AG) -> 0.53202847
A39: Summer Deviation | B39: {=STDEV(IF(ml_challenge_dataset!B:B="The Persistence of Memory", ml_challenge_dataset!AG:AG))} -> 0.44366973 | C39: {=STDEV(IF(ml_challenge_dataset!B:B="The Starry Night", ml_challenge_dataset!AG:AG))} -> 0.48326318 | D39: {=STDEV(IF(ml_challenge_dataset!B:B="The Water Lily Pond", ml_challenge_dataset!AG:AG))} -> 0.49941764
A40: Fall Mean | B40: =AVERAGEIF(ml_challenge_dataset!B:B, "The Persistence of Memory", ml_challenge_dataset!AH:AH) -> 0.58540925 | C40: =AVERAGEIF(ml_challenge_dataset!B:B, "The Starry Night", ml_challenge_dataset!AH:AH) -> 0.17615658 | D40: =AVERAGEIF(ml_challenge_dataset!B:B, "The Water Lily Pond", ml_challenge_dataset!AH:AH) -> 0.021352313
A41: Fall Deviation | B41: {=STDEV(IF(ml_challenge_dataset!B:B="The Persistence of Memory", ml_challenge_dataset!AH:AH))} -> 0.49309014 | C41: {=STDEV(IF(ml_challenge_dataset!B:B="The Starry Night", ml_challenge_dataset!AH:AH))} -> 0.38129271 | D41: {=STDEV(IF(ml_challenge_dataset!B:B="The Water Lily Pond", ml_challenge_dataset!AH:AH))} -> 0.14468462
A42: Winter Mean | B42: =AVERAGEIF(ml_challenge_dataset!B:B, "The Persistence of Memory", ml_challenge_dataset!AI:AI) -> 0.1975089 | C42: =AVERAGEIF(ml_challenge_dataset!B:B, "The Starry Night", ml_challenge_dataset!AI:AI) -> 0.52135231 | D42: =AVERAGEIF(ml_challenge_dataset!B:B, "The Water Lily Pond", ml_challenge_dataset!AI:AI) -> 0.0017793594
A43: Winter Deviation | B43: {=STDEV(IF(ml_challenge_dataset!B:B="The Persistence of Memory", ml_challenge_dataset!AI:AI))} -> 0.39847417 | C43: {=STDEV(IF(ml_challenge_dataset!B:B="The Starry Night", ml_challenge_dataset!AI:AI))} -> 0.4999889 | D43: {=STDEV(IF(ml_challenge_dataset!B:B="The Water Lily Pond", ml_challenge_dataset!AI:AI))} -> 0.042182454
